Workbook

Sheet Premissas
A1: PROPOSTA PIXELPULSELAB — PREMISSAS DA ANÁLISE DE SENSIBILIDADE
A2: Fonte: proposta de trabalho PixelPulseLab (Order-to-Delivery → Adaptive Layer™ → LLM/agentes), Grupo Orfeu, 06/08/2026
A3: Premissa | B3: Valor | C3: Nota
A4: Investimento mínimo (proposta) | B4: 960000 | C4: R$ — engagement mensal R$120k × 8 meses
A5: Investimento máximo (proposta) | B5: 1040000 | C5: R$ — engagement mensal R$130k × 8 meses
A6: Investimento médio (base da análise) | B6: =AVERAGE(B4:B5) | C6: R$ — ponto médio usado nas sensibilidades
A7: Horizonte do engagement | B7: 8 | C7: meses
A8: Margem de contribuição (cenário Receita) | B8: 0.3 | C8: Premissa fornecida pela Orfeu
A9: Custo médio QLP por pessoa/mês | B9: 15000 | C9: Premissa fornecida pela Orfeu (custo carregado)
A10: Receita base 2026 (referência) | B10: 170000000 | C10: R$ — Plano de Ação Orfeu, validado 07/08/2026
A11: % do investimento alocado a áreas (M1 Piloto + M3 Rollout QWs) | B11: 0.4 | C11: Milestones que entregam os 10 quick wins específicos
A12: % do investimento em infraestrutura compartilhada (M0+M2+M4+M5) | B12: =1-B11 | C12: Mobilização, Adaptive Layer™, produção, LLM/agentes
A13: % da infra compartilhada atribuída à lente Receita | B13: 0.5 | C13: Premissa de modelagem — infraestrutura beneficia ambas as lentes
A14: % da infra compartilhada atribuída à lente QLP | B14: =1-B13 | C14: Premissa de modelagem — infraestrutura beneficia ambas as lentes
A17: Nota metodológica
A18: A proposta da PixelPulseLab não segmenta o investimento por 'meios vs. canais diretos' — é uma proposta de automação de sistemas (order-to-delivery), não de mídia. Esta análise usa duas lentes reais extraídas da proposta: (1) MEIOS = squad/papel alocado (Tech Lead, Devs, IA, QA), por horas; (2) CANAL/ÁREA = área de negócio da Orfeu tocada pelos 10 quick wins (Comercial, Financeiro, Logística, Jurídico, Backoffice, Pós-venda). A atribuição de benefício (Receita vs. QLP) por área segue a natureza de cada quick win, conforme descrito na própria proposta (ver aba 'Fonte — Quick Wins').

Sheet Distribuição Investimento
A1: COMO O INVESTIMENTO ESTÁ DISTRIBUÍDO
A3: 1. Por MEIOS — squad alocado (base: horas × 8 meses)
A4: Papel | B4: Dedicação | C4: h/mês | D4: h totais (8m) | E4: % do total | F4: R$ alocado (base)
A5: Tech Lead / Arquiteto de integrações | B5: Parcial | C5: 60 | D5: =C5*Premissas!$B$7 | E5: =D5/D$10 | F5: =E5*Premissas!$B$6
A6: Dev sênior back-end / integrações | B6: Dedicado (full-time) | C6: 168 | D6: =C6*Premissas!$B$7 | E6: =D6/D$10 | F6: =E6*Premissas!$B$6
A7: Dev pleno full-stack | B7: Dedicado | C7: 132 | D7: =C7*Premissas!$B$7 | E7: =D7/D$10 | F7: =E7*Premissas!$B$6
A8: Especialista IA / agentes | B8: Parcial | C8: 50 | D8: =C8*Premissas!$B$7 | E8: =D8/D$10 | F8: =E8*Premissas!$B$6
A9: QA / automação de testes | B9: Parcial | C9: 50 | D9: =C9*Premissas!$B$7 | E9: =D9/D$10 | F9: =E9*Premissas!$B$6
A10: Total | C10: =SUM(C5:C9) | D10: =SUM(D5:D9) | E10: =D10/D$10 | F10: =E10*Premissas!$B$6
A13: 2. Por CANAL/ÁREA — negócio tocado pelos 10 quick wins
A14: Área | B14: # Quick Wins | C14: Lente de benefício | D14: % do investimento área-específico | E14: R$ alocado
A15: Comercial | B15: 3 | C15: Receita | D15: =B15/B$21 | E15: =D15*Premissas!$B$6*Premissas!$B$11
A16: Financeiro | B16: 2 | C16: QLP | D16: =B16/B$21 | E16: =D16*Premissas!$B$6*Premissas!$B$11
A17: Logística | B17: 2 | C17: QLP | D17: =B17/B$21 | E17: =D17*Premissas!$B$6*Premissas!$B$11
A18: Jurídico | B18: 1 | C18: QLP | D18: =B18/B$21 | E18: =D18*Premissas!$B$6*Premissas!$B$11
A19: Backoffice | B19: 1 | C19: Receita | D19: =B19/B$21 | E19: =D19*Premissas!$B$6*Premissas!$B$11
A20: Pós-venda | B20: 1 | C20: Receita | D20: =B20/B$21 | E20: =D20*Premissas!$B$6*Premissas!$B$11
A21: Total (área-específico) | B21: =SUM(B15:B20) | D21: =B21/B$21 | E21: =D21*Premissas!$B$6*Premissas!$B$11
A23: Infraestrutura compartilhada (M0 Mobilização + M2 Adaptive Layer™ + M4 Produção + M5 LLM/Agentes) | E23: =Premissas!$B$6*(1-Premissas!$B$11)
A26: 3. Investimento por LENTE DE BENEFÍCIO (para a sensibilidade)
A27: Lente | B27: Investimento área-específico | C27: + parcela infra compartilhada | D27: Investimento total na lente
A28: Receita (Comercial + Backoffice + Pós-venda) | B28: =SUMIF(C15:C20,"Receita",E15:E20) | C28: =Premissas!$B$6*(1-Premissas!$B$11)*Premissas!$B$13 | D28: =B28+C28
A29: QLP (Financeiro + Logística + Jurídico) | B29: =SUMIF(C15:C20,"QLP",E15:E20) | C29: =Premissas!$B$6*(1-Premissas!$B$11)*Premissas!$B$14 | D29: =B29+C29

Sheet Sensibilidade Receita
A1: SENSIBILIDADE — CENÁRIO RECEITA (margem de contribuição 30%)
A2: Lentes de benefício: Comercial (leads/propostas mais rápidos), Backoffice (menos ruptura → receita recuperada), Pós-venda (recompra). Fonte: expectedGain dos quick wins QW-01, QW-02, QW-03, QW-05, QW-10.
A4: Investimento na lente Receita | B4: ='Distribuição Investimento'!D28
A5: Receita base 2026 (referência) | B5: =Premissas!B10
A6: Margem de contribuição | B6: =Premissas!B8
A8: % de aumento de receita (anual) | B8: Receita incremental anual | C8: Benefício anual (margem) | D8: Payback (meses) | E8: ROI ano 1
A9: 0.0025 | B9: =A9*$B$5 | C9: =B9*$B$6 | D9: =$B$4/C9*12 | E9: =(C9-$B$4)/$B$4
A10: 0.005 | B10: =A10*$B$5 | C10: =B10*$B$6 | D10: =$B$4/C10*12 | E10: =(C10-$B$4)/$B$4
A11: 0.0075 | B11: =A11*$B$5 | C11: =B11*$B$6 | D11: =$B$4/C11*12 | E11: =(C11-$B$4)/$B$4
A12: 0.01 | B12: =A12*$B$5 | C12: =B12*$B$6 | D12: =$B$4/C12*12 | E12: =(C12-$B$4)/$B$4
A13: 0.0125 | B13: =A13*$B$5 | C13: =B13*$B$6 | D13: =$B$4/C13*12 | E13: =(C13-$B$4)/$B$4
A14: 0.015 | B14: =A14*$B$5 | C14: =B14*$B$6 | D14: =$B$4/C14*12 | E14: =(C14-$B$4)/$B$4
A15: 0.02 | B15: =A15*$B$5 | C15: =B15*$B$6 | D15: =$B$4/C15*12 | E15: =(C15-$B$4)/$B$4
A16: 0.025 | B16: =A16*$B$5 | C16: =B16*$B$6 | D16: =$B$4/C16*12 | E16: =(C16-$B$4)/$B$4
A17: 0.03 | B17: =A17*$B$5 | C17: =B17*$B$6 | D17: =$B$4/C17*12 | E17: =(C17-$B$4)/$B$4
A19: Breakeven exato (payback = 12 meses)
A20: % de aumento de receita necessário | B20: =($B$4/$B$6)/$B$5
A21: Receita incremental necessária (R$) | B21: =$B$4/$B$6

Sheet Sensibilidade QLP
A1: SENSIBILIDADE — CENÁRIO ECONOMIA DE QLP (R$15k/pessoa/mês)
A2: Lentes de benefício: Financeiro (faturamento/crédito sem intervenção manual), Logística (separação sem papel, menos reentrega), Jurídico (contrato digital). Fonte: businessRisk/expectedGain dos quick wins QW-04, QW-06, QW-07, QW-08, QW-09.
A4: Investimento na lente QLP | B4: ='Distribuição Investimento'!D29
A5: Custo médio QLP por pessoa/mês | B5: =Premissas!B9
A6: Custo anual por pessoa (headcount equivalente) | B6: =B5*12
A8: FTEs de trabalho manual eliminados | B8: Economia anual | C8: Payback (meses) | D8: ROI ano 1
A9: 0.5 | B9: =A9*$B$6 | C9: =$B$4/B9*12 | D9: =(B9-$B$4)/$B$4
A10: 1 | B10: =A10*$B$6 | C10: =$B$4/B10*12 | D10: =(B10-$B$4)/$B$4
A11: 1.5 | B11: =A11*$B$6 | C11: =$B$4/B11*12 | D11: =(B11-$B$4)/$B$4
A12: 2 | B12: =A12*$B$6 | C12: =$B$4/B12*12 | D12: =(B12-$B$4)/$B$4
A13: 2.5 | B13: =A13*$B$6 | C13: =$B$4/B13*12 | D13: =(B13-$B$4)/$B$4
A14: 3 | B14: =A14*$B$6 | C14: =$B$4/B14*12 | D14: =(B14-$B$4)/$B$4
A15: 4 | B15: =A15*$B$6 | C15: =$B$4/B15*12 | D15: =(B15-$B$4)/$B$4
A16: 5 | B16: =A16*$B$6 | C16: =$B$4/B16*12 | D16: =(B16-$B$4)/$B$4
A18: Breakeven exato (payback = 12 meses)
A19: FTEs necessários | B19: =$B$4/$B$6

Sheet Matriz Combinada
A1: MATRIZ COMBINADA — PAYBACK (MESES) DO INVESTIMENTO TOTAL
A2: Combina as duas lentes sobre o investimento total (R$960k–1.040k, base R$1M): linhas = % de aumento de receita · colunas = FTEs de trabalho manual eliminados. Célula = payback em meses do programa completo.
A4: Investimento total (base) | B4: =Premissas!B6
A6: % receita ↓ / FTEs → | B6: 0.5 | C6: 1 | D6: 1.5 | E6: 2 | F6: 2.5 | G6: 3 | H6: 4 | I6: 5
A7: 0.0025 | B7: =$B$4/((A7*Premissas!$B$10*Premissas!$B$8) + (B$6*Premissas!$B$9*12))*12 | C7: =$B$4/((A7*Premissas!$B$10*Premissas!$B$8) + (C$6*Premissas!$B$9*12))*12 | D7: =$B$4/((A7*Premissas!$B$10*Premissas!$B$8) + (D$6*Premissas!$B$9*12))*12 | E7: =$B$4/((A7*Premissas!$B$10*Premissas!$B$8) + (E$6*Premissas!$B$9*12))*12 | F7: =$B$4/((A7*Premissas!$B$10*Premissas!$B$8) + (F$6*Premissas!$B$9*12))*12 | G7: =$B$4/((A7*Premissas!$B$10*Premissas!$B$8) + (G$6*Premissas!$B$9*12))*12 | H7: =$B$4/((A7*Premissas!$B$10*Premissas!$B$8) + (H$6*Premissas!$B$9*12))*12 | I7: =$B$4/((A7*Premissas!$B$10*Premissas!$B$8) + (I$6*Premissas!$B$9*12))*12
A8: 0.005 | B8: =$B$4/((A8*Premissas!$B$10*Premissas!$B$8) + (B$6*Premissas!$B$9*12))*12 | C8: =$B$4/((A8*Premissas!$B$10*Premissas!$B$8) + (C$6*Premissas!$B$9*12))*12 | D8: =$B$4/((A8*Premissas!$B$10*Premissas!$B$8) + (D$6*Premissas!$B$9*12))*12 | E8: =$B$4/((A8*Premissas!$B$10*Premissas!$B$8) + (E$6*Premissas!$B$9*12))*12 | F8: =$B$4/((A8*Premissas!$B$10*Premissas!$B$8) + (F$6*Premissas!$B$9*12))*12 | G8: =$B$4/((A8*Premissas!$B$10*Premissas!$B$8) + (G$6*Premissas!$B$9*12))*12 | H8: =$B$4/((A8*Premissas!$B$10*Premissas!$B$8) + (H$6*Premissas!$B$9*12))*12 | I8: =$B$4/((A8*Premissas!$B$10*Premissas!$B$8) + (I$6*Premissas!$B$9*12))*12
A9: 0.0075 | B9: =$B$4/((A9*Premissas!$B$10*Premissas!$B$8) + (B$6*Premissas!$B$9*12))*12 | C9: =$B$4/((A9*Premissas!$B$10*Premissas!$B$8) + (C$6*Premissas!$B$9*12))*12 | D9: =$B$4/((A9*Premissas!$B$10*Premissas!$B$8) + (D$6*Premissas!$B$9*12))*12 | E9: =$B$4/((A9*Premissas!$B$10*Premissas!$B$8) + (E$6*Premissas!$B$9*12))*12 | F9: =$B$4/((A9*Premissas!$B$10*Premissas!$B$8) + (F$6*Premissas!$B$9*12))*12 | G9: =$B$4/((A9*Premissas!$B$10*Premissas!$B$8) + (G$6*Premissas!$B$9*12))*12 | H9: =$B$4/((A9*Premissas!$B$10*Premissas!$B$8) + (H$6*Premissas!$B$9*12))*12 | I9: =$B$4/((A9*Premissas!$B$10*Premissas!$B$8) + (I$6*Premissas!$B$9*12))*12
A10: 0.01 | B10: =$B$4/((A10*Premissas!$B$10*Premissas!$B$8) + (B$6*Premissas!$B$9*12))*12 | C10: =$B$4/((A10*Premissas!$B$10*Premissas!$B$8) + (C$6*Premissas!$B$9*12))*12 | D10: =$B$4/((A10*Premissas!$B$10*Premissas!$B$8) + (D$6*Premissas!$B$9*12))*12 | E10: =$B$4/((A10*Premissas!$B$10*Premissas!$B$8) + (E$6*Premissas!$B$9*12))*12 | F10: =$B$4/((A10*Premissas!$B$10*Premissas!$B$8) + (F$6*Premissas!$B$9*12))*12 | G10: =$B$4/((A10*Premissas!$B$10*Premissas!$B$8) + (G$6*Premissas!$B$9*12))*12 | H10: =$B$4/((A10*Premissas!$B$10*Premissas!$B$8) + (H$6*Premissas!$B$9*12))*12 | I10: =$B$4/((A10*Premissas!$B$10*Premissas!$B$8) + (I$6*Premissas!$B$9*12))*12
A11: 0.0125 | B11: =$B$4/((A11*Premissas!$B$10*Premissas!$B$8) + (B$6*Premissas!$B$9*12))*12 | C11: =$B$4/((A11*Premissas!$B$10*Premissas!$B$8) + (C$6*Premissas!$B$9*12))*12 | D11: =$B$4/((A11*Premissas!$B$10*Premissas!$B$8) + (D$6*Premissas!$B$9*12))*12 | E11: =$B$4/((A11*Premissas!$B$10*Premissas!$B$8) + (E$6*Premissas!$B$9*12))*12 | F11: =$B$4/((A11*Premissas!$B$10*Premissas!$B$8) + (F$6*Premissas!$B$9*12))*12 | G11: =$B$4/((A11*Premissas!$B$10*Premissas!$B$8) + (G$6*Premissas!$B$9*12))*12 | H11: =$B$4/((A11*Premissas!$B$10*Premissas!$B$8) + (H$6*Premissas!$B$9*12))*12 | I11: =$B$4/((A11*Premissas!$B$10*Premissas!$B$8) + (I$6*Premissas!$B$9*12))*12
A12: 0.015 | B12: =$B$4/((A12*Premissas!$B$10*Premissas!$B$8) + (B$6*Premissas!$B$9*12))*12 | C12: =$B$4/((A12*Premissas!$B$10*Premissas!$B$8) + (C$6*Premissas!$B$9*12))*12 | D12: =$B$4/((A12*Premissas!$B$10*Premissas!$B$8) + (D$6*Premissas!$B$9*12))*12 | E12: =$B$4/((A12*Premissas!$B$10*Premissas!$B$8) + (E$6*Premissas!$B$9*12))*12 | F12: =$B$4/((A12*Premissas!$B$10*Premissas!$B$8) + (F$6*Premissas!$B$9*12))*12 | G12: =$B$4/((A12*Premissas!$B$10*Premissas!$B$8) + (G$6*Premissas!$B$9*12))*12 | H12: =$B$4/((A12*Premissas!$B$10*Premissas!$B$8) + (H$6*Premissas!$B$9*12))*12 | I12: =$B$4/((A12*Premissas!$B$10*Premissas!$B$8) + (I$6*Premissas!$B$9*12))*12
A13: 0.02 | B13: =$B$4/((A13*Premissas!$B$10*Premissas!$B$8) + (B$6*Premissas!$B$9*12))*12 | C13: =$B$4/((A13*Premissas!$B$10*Premissas!$B$8) + (C$6*Premissas!$B$9*12))*12 | D13: =$B$4/((A13*Premissas!$B$10*Premissas!$B$8) + (D$6*Premissas!$B$9*12))*12 | E13: =$B$4/((A13*Premissas!$B$10*Premissas!$B$8) + (E$6*Premissas!$B$9*12))*12 | F13: =$B$4/((A13*Premissas!$B$10*Premissas!$B$8) + (F$6*Premissas!$B$9*12))*12 | G13: =$B$4/((A13*Premissas!$B$10*Premissas!$B$8) + (G$6*Premissas!$B$9*12))*12 | H13: =$B$4/((A13*Premissas!$B$10*Premissas!$B$8) + (H$6*Premissas!$B$9*12))*12 | I13: =$B$4/((A13*Premissas!$B$10*Premissas!$B$8) + (I$6*Premissas!$B$9*12))*12
A14: 0.025 | B14: =$B$4/((A14*Premissas!$B$10*Premissas!$B$8) + (B$6*Premissas!$B$9*12))*12 | C14: =$B$4/((A14*Premissas!$B$10*Premissas!$B$8) + (C$6*Premissas!$B$9*12))*12 | D14: =$B$4/((A14*Premissas!$B$10*Premissas!$B$8) + (D$6*Premissas!$B$9*12))*12 | E14: =$B$4/((A14*Premissas!$B$10*Premissas!$B$8) + (E$6*Premissas!$B$9*12))*12 | F14: =$B$4/((A14*Premissas!$B$10*Premissas!$B$8) + (F$6*Premissas!$B$9*12))*12 | G14: =$B$4/((A14*Premissas!$B$10*Premissas!$B$8) + (G$6*Premissas!$B$9*12))*12 | H14: =$B$4/((A14*Premissas!$B$10*Premissas!$B$8) + (H$6*Premissas!$B$9*12))*12 | I14: =$B$4/((A14*Premissas!$B$10*Premissas!$B$8) + (I$6*Premissas!$B$9*12))*12
A15: 0.03 | B15: =$B$4/((A15*Premissas!$B$10*Premissas!$B$8) + (B$6*Premissas!$B$9*12))*12 | C15: =$B$4/((A15*Premissas!$B$10*Premissas!$B$8) + (C$6*Premissas!$B$9*12))*12 | D15: =$B$4/((A15*Premissas!$B$10*Premissas!$B$8) + (D$6*Premissas!$B$9*12))*12 | E15: =$B$4/((A15*Premissas!$B$10*Premissas!$B$8) + (E$6*Premissas!$B$9*12))*12 | F15: =$B$4/((A15*Premissas!$B$10*Premissas!$B$8) + (F$6*Premissas!$B$9*12))*12 | G15: =$B$4/((A15*Premissas!$B$10*Premissas!$B$8) + (G$6*Premissas!$B$9*12))*12 | H15: =$B$4/((A15*Premissas!$B$10*Premissas!$B$8) + (H$6*Premissas!$B$9*12))*12 | I15: =$B$4/((A15*Premissas!$B$10*Premissas!$B$8) + (I$6*Premissas!$B$9*12))*12

Sheet Fonte — Quick Wins
A1: FONTE — OS 10 QUICK WINS OTD DA PROPOSTA PIXELPULSELAB
A2: Extraído de https://pixelpulselab.dev/pt/adaptive/proposta (senha orfeu2026), acessado 07/08/2026.
A4: ID | B4: Quick Win | C4: Área | D4: Lente de benefício | E4: Ganho esperado (expectedGain, texto original da proposta)
A5: QW-OTD-01 | B5: Lead na Jornada do Vendedor sem e-mail/retrabalho | C5: Comercial | D5: Receita | E5: Entrada única do lead, distribuição automática, histórico preservado — vendedor inicia abordagem com contexto e prazo.
A6: QW-OTD-02 | B6: Proposta e pricing no fluxo (sair de Word/e-mail) | C6: Comercial | D6: Receita | E6: Proposta gerada com preço, margem e alçadas controlados; aprovação no próprio fluxo.
A7: QW-OTD-03 | B7: Cadastro e análise de crédito no portal | C7: Comercial | D7: Receita | E7: Cadastro único com pendências visíveis e passagem automática para crédito quando completo.
A8: QW-OTD-04 | B8: Contrato digital no Protheus / Jurídico | C8: Jurídico | D8: QLP | E8: Contrato montado a partir do cadastro, com modelo correto, assinatura e status integrados.
A9: QW-OTD-05 | B9: Input pedido com estoque e ruptura visíveis | C9: Backoffice | D9: Receita | E9: Estoque e risco de ruptura visíveis antes da confirmação; receita recuperada por substituição.
A10: QW-OTD-06 | B10: Liberação de crédito no fluxo pré-faturamento | C10: Financeiro | D10: QLP | E10: Pré-validação de crédito, fila única de exceções, liberação orientada por regra e risco.
A11: QW-OTD-07 | B11: Faturamento B2B automático (NF-e + boletos) | C11: Financeiro | D11: QLP | E11: Faturamento orquestrado com validações; intervenção humana apenas em desvio.
A12: QW-OTD-08 | B12: Separação/WMS sem papel (coletor + conferência) | C12: Logística | D12: QLP | E12: Separação orientada por coletor, conferência digital; divergência bloqueada antes da expedição.
A13: QW-OTD-09 | B13: Expedição e EDI no fluxo de tracking | C13: Logística | D13: QLP | E13: Eventos consolidados, ETA e desvios visíveis, alerta proativo — menos contatos manuais de status.
A14: QW-OTD-10 | B14: Alerta de recompra automático | C14: Pós-venda | D14: Receita | E14: Alerta diário priorizado com próxima ação sugerida; receita/margem recuperada por recompra.
