Workbook

Sheet Premissas
A1: SIMULADOR COMERCIAL ORFEU — PREMISSAS
A3: 1. Crescimento e Aceleração
A4: Crescimento orgânico anual — Varejo | B4: 0.255
A5: Crescimento orgânico anual — B2B | B5: 0.255
A6: Bônus de aceleração — ano de entrada na prioridade | B6: 0.25
A7: Bônus de aceleração — 1 ano após entrada | B7: 0.2
A8: Bônus de aceleração — 2 anos após entrada | B8: 0.1
A9: Crescimento orgânico anual — Online | B9: 0.25
A10: 2. Produtividade Comercial (dimensionamento de time)
A11: Meta de faturamento mensal por vendedor (full ramp) | B11: 300000
A12: Meses de ramp-up até atingir a meta | B12: 6
A13: Capacidade anual — ano da contratação (com ramp-up) | B13: =B11*12-B11*B12/2
A14: Capacidade anual — full run-rate (a partir do 2º ano) | B14: =B11*12
A15: Promotores/Abordadores por R$1M incremental (base — antes da sinergia regional, seção 7) | B15: 0.25
A16: Baristas por Comercial consolidado (cidades foco B2B) | B16: 0.5
A18: 3. Span of Control
A19: Mínimo de subordinados por líder | B19: 6
A20: Máximo de subordinados por líder | B20: 12
A21: Médio (referência p/ cálculo de líderes sugeridos) | B21: 9
A23: 4. Metas da Companhia (referência)
A24: Fechamento 2026 (real — atualizado ago/2026) | B24: 163000000
A25: Ambição 2030 | B25: 400000000 | C25: Ambição 2030 é SOMENTE Brasil. Meta consolidada da companhia = R$ 500M (R$ 400M BR + R$ 100M EUA/exportação — ver 'Metas 2030' no Plano de Ação). Sem divergência entre os arquivos.
A27: 5. Priorização de Mercados — fonte: Mercados foco (jul/2026)
A28: Estado | B28: Segmento | C28: Ano de Entrada na Prioridade | G28: Cidades-chave / Observação
A29: SP | B29: Colheita | C29: — | G29: Interior: Campinas (ativo); Sorocaba, SJC, Ribeirão Preto, Jundiaí (2027)
A30: RJ | B30: Colheita | C30: — | G30: —
A31: SC | B31: Plantio | C31: 2026 | G31: Florianópolis, Balneário Camboriú, Itapema (ativo); Blumenau, Joinville (2028)
A32: DF | B32: Plantio | C32: 2026 | G32: Brasília
A33: PR | B33: Plantio | C33: 2026 | G33: Curitiba
A34: RS | B34: Plantio | C34: 2027 | G34: Porto Alegre + Serra Gaúcha (Hoteleiro)
A35: MG | B35: Plantio | C35: 2027 | G35: Belo Horizonte + Nova Lima
A36: ES | B36: Plantio | C36: 2028 | G36: Vitória
A37: BA | B37: Plantio | C37: 2029 | G37: Salvador + Trancoso (Hoteleiro)
A38: CE | B38: Plantio | C38: 2029 | G38: Fortaleza
A39: PE | B39: Plantio | C39: 2029 | G39: Recife + Muro Alto (Hoteleiro)
A40: MS | B40: Plantio | C40: 2030 | G40: Campo Grande + Pantanal (Hoteleiro)
A41: MT | B41: Plantio | C41: 2030 | G41: Cuiabá
A42: AM | B42: Plantio | C42: 2030 | G42: Manaus
A43: AC | B43: Sem priorização definida | C43: — | G43: —
A44: AL | B44: Sem priorização definida | C44: — | G44: —
A45: AP | B45: Sem priorização definida | C45: — | G45: —
A46: GO | B46: Plantio | C46: 2027 | G46: Goiânia. Adicionado — receita 2025 (R$1,01M) supera vários estados já priorizados (AM, CE, ES, MS).
A47: MA | B47: Plantio | C47: 2028 | G47: São Luís. Adicionado — receita 2025 (R$385k) supera ES e MS, já priorizados.
A48: PA | B48: Plantio | C48: 2028 | G48: Belém. Adicionado — receita 2025 (R$324k) supera ES e MS, já priorizados.
A49: PB | B49: Sem priorização definida | C49: — | G49: —
A50: PI | B50: Sem priorização definida | C50: — | G50: —
A51: RN | B51: Sem priorização definida | C51: — | G51: —
A52: RO | B52: Sem priorização definida | C52: — | G52: —
A53: RR | B53: Sem priorização definida | C53: — | G53: —
A54: SE | B54: Sem priorização definida | C54: — | G54: ⚠ Receita 2025 (R$8,19M — 4º maior UF) NÃO recomendada para priorização sem validação: a aba 'B2B — Top 25 Cidades' mostra 'SE' associado a cidades São Paulo e Rio de Janeiro, sugerindo que 'SE' pode ser um código de canal/distribuidor coincidente com o UF Sergipe, não vendas geográficas no estado. Validar com Amanda/Financeiro antes de tratar como mercado prioritário.
A55: TO | B55: Sem priorização definida | C55: — | G55: —
A57: Nota: SP e RJ são mercados maduros ("Colheita") — crescem no orgânico. Estados fora do roadmap de Mercados Foco seguem apenas crescimento orgânico (sem bônus).
A59: 6. Custo por Função — Organograma Comercial (Owners inbox/.../Organograma_Time_Comercial_SNomes.xlsx, aba Avaliação)
A60: Onde há múltiplas pessoas no mesmo cargo com salários diferentes, o valor abaixo é a MÉDIA simples dos salários encontrados (mensal, base — sem encargos/13º/férias). Cargos sem dado salarial no Organograma ficam sinalizados, não estimados.
A61: Função (simulador) | B61: Salário médio mensal (R$) | C61: Nº pessoas na amostra | D61: Cargo/Área no Organograma | E61: Observação
A62: Representante (Varejo terceiro) | B62: Não disponível | C62: 7 | D62: Representante — área "Varejo Indireto" | E62: ⚠ Sem salário — modelo comissionado/terceiro POR DESENHO, não é lacuna de dado. Representantes NÃO são funcionários Orfeu (CLT); custo real é comissão sobre vendas, a mapear com Comercial/Financeiro.
A63: Promotores/Abordadores (via agência) | B63: Não disponível | C63: 2 | D63: Promotores + Degustadores — área "Merchandising" | E63: ⚠ Sem salário — sempre contratados via agência externa POR DESENHO (todos os estados), não é lacuna de dado. Custo real é o contrato com a agência, a mapear com Trade/Financeiro.
A64: Comercial (B2B) | B64: 5162.89 | C64: 7 | D64: Vendedor — área "B2B" | E64: Média de 7 salários reais (R$3.483–R$7.907,50).
A65: Baristas (B2B) | B65: 4508.67 | C65: 6 | D65: Barista — área "B2B" | E65: Média de 6 salários reais (R$3.509–R$7.001).
A67: Vendedor Varejo Direto (SP/RJ) | B67: 5185.75 | C67: 4 | D67: Vendedor — área "Varejo" | E67: Média de 4 salários reais (R$3.871,50–R$7.000), apenas SP/RJ.
A68: Comercial — Gestão de Representantes (terceiro) | B68: 7500 | C68: 1 | D68: Vendedor — área "Varejo Indireto" | E68: 1 salário real. Papel dedicado a gerenciar a rede de representantes terceiro quando ultrapassa 12 (span do Gerente Varejo).
A69: Coordenadora Merchandising | B69: 4683 | C69: 1 | D69: Coordenadora — área "Merchandising" | E69: 1 salário real (RJ). Gerencia a relação com a agência de promotores/degustadores.
A70: Analista Merchandising | B70: 3878.95 | C70: 1 | D70: Analista — área "Merchandising" | E70: 1 salário real (SP). Apoia Gerente Varejo e Coordenadora de Merchandising.
A73: 7. Sinergia Geográfica — Estrutura Mais Enxuta (fora de SP/RJ)
A74: SP e RJ mantêm cobertura dedicada (mercados maduros, alta densidade). Nos demais 25 estados, 1 Representante/Comercial B2B cobre uma região multi-cidade em vez de 1 por estado — e os Promotores/Abordadores também ganham eficiência de cobertura. Objetivo: manter o Faturamento por QLP (headcount comercial) próximo ao patamar atual (~R$5M/pessoa/ano) ao longo de toda a projeção, em vez de diluir com o crescimento.
A75: Fator de sinergia — capacidade de Representante/Comercial B2B fora de SP/RJ (multiplica a capacidade-base B14) | B75: 3.5
A76: Fator de sinergia — Promotores/Abordadores fora de SP/RJ (divide a razão-base B15) | B76: 2.5
A77: Fator de escala 2026 (fechamento real ÷ total 2025 — aplicado ao mix por estado/canal de 2025) | B77: =B24/'Projeção Receita'!$D$59

Sheet Base Histórica 2025
A1: BASE HISTÓRICA 2025 — FONTE: Simulador Orfeu.xlsx (Base_Unitaria)
A3: VAREJO TOTAL (Varejo Direto + Representantes) por Estado
A4: UF | B4: Estado | C4: Fat. Bruto 2025 (R$) | D4: Margem Contrib. 2025 (R$) | E4: MC% | F4: Volume (un)
A5: SP | B5: São Paulo | C5: 21741345 | D5: 6947191.5 | E5: =IF(C5=0,0,D5/C5) | F5: 464121
A6: RJ | B6: Rio de Janeiro | C6: 5918211.7 | D6: 1508324 | E6: =IF(C6=0,0,D6/C6) | F6: 195051
A7: SC | B7: Santa Catarina | C7: 11585092 | D7: 2747793.1 | E7: =IF(C7=0,0,D7/C7) | F7: 335304
A8: DF | B8: Distrito Federal | C8: 869314.1 | D8: 275016.95 | E8: =IF(C8=0,0,D8/C8) | F8: 31939
A9: PR | B9: Paraná | C9: 2261077.4 | D9: 587959.2 | E9: =IF(C9=0,0,D9/C9) | F9: 66083
A10: RS | B10: Rio Grande do Sul | C10: 2591730.3 | D10: 442693.83 | E10: =IF(C10=0,0,D10/C10) | F10: 88288
A11: MG | B11: Minas Gerais | C11: 1450691.3 | D11: 430881.58 | E11: =IF(C11=0,0,D11/C11) | F11: 51018
A12: ES | B12: Espírito Santo | C12: 220220.52 | D12: 50170.084 | E12: =IF(C12=0,0,D12/C12) | F12: 8920
A13: BA | B13: Bahia | C13: 117607.08 | D13: 42422.252 | E13: =IF(C13=0,0,D13/C13) | F13: 3389
A14: CE | B14: Ceará | C14: 159336.2 | D14: 51733.247 | E14: =IF(C14=0,0,D14/C14) | F14: 5254
A15: PE | B15: Pernambuco | C15: 170354.16 | D15: 60386.823 | E15: =IF(C15=0,0,D15/C15) | F15: 5725
A16: MS | B16: Mato Grosso do Sul | C16: 132869.4 | D16: 41242.12 | E16: =IF(C16=0,0,D16/C16) | F16: 4744
... A31: TO | B31: Tocantins | C31: 33134.2 | D31: 13656.687 | E31: =IF(C31=0,0,D31/C31) | F31: 904
B32: TOTAL | C32: =SUM(C5:C31) | D32: =SUM(D5:D31)
A34: B2B por Estado
A35: UF | B35: Estado | C35: Fat. Bruto 2025 (R$) | D35: Margem Contrib. 2025 (R$) | E35: MC% | F35: Volume (un)
A36: SP | B36: São Paulo | C36: 15057942 | D36: 4887273.8 | E36: =IF(C36=0,0,D36/C36) | F36: 302681
A37: RJ | B37: Rio de Janeiro | C37: 4459529.1 | D37: 1346430.9 | E37: =IF(C37=0,0,D37/C37) | F37: 90536
A38: SC | B38: Santa Catarina | C38: 745367.96 | D38: 192714.7 | E38: =IF(C38=0,0,D38/C38) | F38: 10686
A39: DF | B39: Distrito Federal | C39: 593541.77 | D39: 241385.54 | E39: =IF(C39=0,0,D39/C39) | F39: 9922
A40: PR | B40: Paraná | C40: 812982.8 | D40: 203382.69 | E40: =IF(C40=0,0,D40/C40) | F40: 13768
A41: RS | B41: Rio Grande do Sul | C41: 315961.81 | D41: 105064.88 | E41: =IF(C41=0,0,D41/C41) | F41: 5283
A42: MG | B42: Minas Gerais | C42: 1414547.8 | D42: 368850.86 | E42: =IF(C42=0,0,D42/C42) | F42: 54910
A43: ES | B43: Espírito Santo | C43: 2700 | D43: 1071.7895 | E43: =IF(C43=0,0,D43/C43) | F43: 36
A44: BA | B44: Bahia | C44: 277487.2 | D44: 122033.24 | E44: =IF(C44=0,0,D44/C44) | F44: 6033
A45: CE | B45: Ceará | C45: 6693 | D45: 2658.4969 | E45: =IF(C45=0,0,D45/C45) | F45: 66
A46: PE | B46: Pernambuco | C46: 324873.15 | D46: 147392.15 | E46: =IF(C46=0,0,D46/C46) | F46: 5992
A47: MS | B47: Mato Grosso do Sul | C47: 50811.1 | D47: 22040.867 | E47: =IF(C47=0,0,D47/C47) | F47: 4649
... A62: TO | B62: Tocantins | C62: 10609.14 | D62: 4843.0873 | E62: =IF(C62=0,0,D62/C62) | F62: 267
B63: TOTAL | C63: =SUM(C36:C62) | D63: =SUM(D36:D62)
A65: B2B — Top 25 Cidades (2025, referência para cidades-foco)
A66: UF | B66: Cidade | C66: Fat. Bruto 2025 (R$)
A67: SP | B67: Sao Paulo | C67: 7342395
A68: RJ | B68: Rio De Janeiro | C68: 3201930
A69: SP | B69: Jundiai | C69: 955415.82
A70: SE | B70: Sao Paulo | C70: 706103.76
A71: MG | B71: Pocos De Caldas | C71: 635771.19
A72: DF | B72: Brasilia | C72: 593049.27
A73: PR | B73: Curitiba | C73: 558271.75
A74: GO | B74: Abadiania | C74: 537624.6
A75: SP | B75: Catanduva | C75: 521371.76
A76: SP | B76: Barueri | C76: 512216.01
A77: SP | B77: Santa Barbara D Oeste | C77: 389755.44
A78: SE | B78: Rio De Janeiro | C78: 356756.42
... A91: RJ | B91: Niteroi | C91: 200941.67

Sheet Projeção Receita
A1: PROJEÇÃO DE RECEITA — ESTADO x CANAL (2025 base → 2030)
A3: UF | B3: Estado | C3: Canal | D3: 2025 (base) | E3: 2026 | F3: 2027 | G3: 2028 | H3: 2029 | I3: 2030
A4: SP | B4: São Paulo | C4: Varejo | D4: ='Base Histórica 2025'!C5 | E4: =D4*Premissas!$B$77 | F4: =E4*(1+Premissas!$B$4+IF(ISNUMBER(Premissas!$C$29),IF(2027=Premissas!$C$29,Premissas!$B$6,IF(2027=Premissas!$C$29+1,Premissas!$B$7,IF(2027=Premissas!$C$29+2,Premissas!$B$8,0))),0)) | G4: =F4*(1+Premissas!$B$4+IF(ISNUMBER(Premissas!$C$29),IF(2028=Premissas!$C$29,Premissas!$B$6,IF(2028=Premissas!$C$29+1,Premissas!$B$7,IF(2028=Premissas!$C$29+2,Premissas!$B$8,0))),0)) | H4: =G4*(1+Premissas!$B$4+IF(ISNUMBER(Premissas!$C$29),IF(2029=Premissas!$C$29,Premissas!$B$6,IF(2029=Premissas!$C$29+1,Premissas!$B$7,IF(2029=Premissas!$C$29+2,Premissas!$B$8,0))),0)) | I4: =H4*(1+Premissas!$B$4+IF(ISNUMBER(Premissas!$C$29),IF(2030=Premissas!$C$29,Premissas!$B$6,IF(2030=Premissas!$C$29+1,Premissas!$B$7,IF(2030=Premissas!$C$29+2,Premissas!$B$8,0))),0))
A5: SP | B5: São Paulo | C5: B2B | D5: ='Base Histórica 2025'!C36 | E5: =D5*Premissas!$B$77 | F5: =E5*(1+Premissas!$B$5+IF(ISNUMBER(Premissas!$C$29),IF(2027=Premissas!$C$29,Premissas!$B$6,IF(2027=Premissas!$C$29+1,Premissas!$B$7,IF(2027=Premissas!$C$29+2,Premissas!$B$8,0))),0)) | G5: =F5*(1+Premissas!$B$5+IF(ISNUMBER(Premissas!$C$29),IF(2028=Premissas!$C$29,Premissas!$B$6,IF(2028=Premissas!$C$29+1,Premissas!$B$7,IF(2028=Premissas!$C$29+2,Premissas!$B$8,0))),0)) | H5: =G5*(1+Premissas!$B$5+IF(ISNUMBER(Premissas!$C$29),IF(2029=Premissas!$C$29,Premissas!$B$6,IF(2029=Premissas!$C$29+1,Premissas!$B$7,IF(2029=Premissas!$C$29+2,Premissas!$B$8,0))),0)) | I5: =H5*(1+Premissas!$B$5+IF(ISNUMBER(Premissas!$C$29),IF(2030=Premissas!$C$29,Premissas!$B$6,IF(2030=Premissas!$C$29+1,Premissas!$B$7,IF(2030=Premissas!$C$29+2,Premissas!$B$8,0))),0))
A6: RJ | B6: Rio de Janeiro | C6: Varejo | D6: ='Base Histórica 2025'!C6 | E6: =D6*Premissas!$B$77 | F6: =E6*(1+Premissas!$B$4+IF(ISNUMBER(Premissas!$C$30),IF(2027=Premissas!$C$30,Premissas!$B$6,IF(2027=Premissas!$C$30+1,Premissas!$B$7,IF(2027=Premissas!$C$30+2,Premissas!$B$8,0))),0)) | G6: =F6*(1+Premissas!$B$4+IF(ISNUMBER(Premissas!$C$30),IF(2028=Premissas!$C$30,Premissas!$B$6,IF(2028=Premissas!$C$30+1,Premissas!$B$7,IF(2028=Premissas!$C$30+2,Premissas!$B$8,0))),0)) | H6: =G6*(1+Premissas!$B$4+IF(ISNUMBER(Premissas!$C$30),IF(2029=Premissas!$C$30,Premissas!$B$6,IF(2029=Premissas!$C$30+1,Premissas!$B$7,IF(2029=Premissas!$C$30+2,Premissas!$B$8,0))),0)) | I6: =H6*(1+Premissas!$B$4+IF(ISNUMBER(Premissas!$C$30),IF(2030=Premissas!$C$30,Premissas!$B$6,IF(2030=Premissas!$C$30+1,Premissas!$B$7,IF(2030=Premissas!$C$30+2,Premissas!$B$8,0))),0))
A7: RJ | B7: Rio de Janeiro | C7: B2B | D7: ='Base Histórica 2025'!C37 | E7: =D7*Premissas!$B$77 | F7: =E7*(1+Premissas!$B$5+IF(ISNUMBER(Premissas!$C$30),IF(2027=Premissas!$C$30,Premissas!$B$6,IF(2027=Premissas!$C$30+1,Premissas!$B$7,IF(2027=Premissas!$C$30+2,Premissas!$B$8,0))),0)) | G7: =F7*(1+Premissas!$B$5+IF(ISNUMBER(Premissas!$C$30),IF(2028=Premissas!$C$30,Premissas!$B$6,IF(2028=Premissas!$C$30+1,Premissas!$B$7,IF(2028=Premissas!$C$30+2,Premissas!$B$8,0))),0)) | H7: =G7*(1+Premissas!$B$5+IF(ISNUMBER(Premissas!$C$30),IF(2029=Premissas!$C$30,Premissas!$B$6,IF(2029=Premissas!$C$30+1,Premissas!$B$7,IF(2029=Premissas!$C$30+2,Premissas!$B$8,0))),0)) | I7: =H7*(1+Premissas!$B$5+IF(ISNUMBER(Premissas!$C$30),IF(2030=Premissas!$C$30,Premissas!$B$6,IF(2030=Premissas!$C$30+1,Premissas!$B$7,IF(2030=Premissas!$C$30+2,Premissas!$B$8,0))),0))
A8: SC | B8: Santa Catarina | C8: Varejo | D8: ='Base Histórica 2025'!C7 | E8: =D8*Premissas!$B$77 | F8: =E8*(1+Premissas!$B$4+IF(ISNUMBER(Premissas!$C$31),IF(2027=Premissas!$C$31,Premissas!$B$6,IF(2027=Premissas!$C$31+1,Premissas!$B$7,IF(2027=Premissas!$C$31+2,Premissas!$B$8,0))),0)) | G8: =F8*(1+Premissas!$B$4+IF(ISNUMBER(Premissas!$C$31),IF(2028=Premissas!$C$31,Premissas!$B$6,IF(2028=Premissas!$C$31+1,Premissas!$B$7,IF(2028=Premissas!$C$31+2,Premissas!$B$8,0))),0)) | H8: =G8*(1+Premissas!$B$4+IF(ISNUMBER(Premissas!$C$31),IF(2029=Premissas!$C$31,Premissas!$B$6,IF(2029=Premissas!$C$31+1,Premissas!$B$7,IF(2029=Premissas!$C$31+2,Premissas!$B$8,0))),0)) | I8: =H8*(1+Premissas!$B$4+IF(ISNUMBER(Premissas!$C$31),IF(2030=Premissas!$C$31,Premissas!$B$6,IF(2030=Premissas!$C$31+1,Premissas!$B$7,IF(2030=Premissas!$C$31+2,Premissas!$B$8,0))),0))
A9: SC | B9: Santa Catarina | C9: B2B | D9: ='Base Histórica 2025'!C38 | E9: =D9*Premissas!$B$77 | F9: =E9*(1+Premissas!$B$5+IF(ISNUMBER(Premissas!$C$31),IF(2027=Premissas!$C$31,Premissas!$B$6,IF(2027=Premissas!$C$31+1,Premissas!$B$7,IF(2027=Premissas!$C$31+2,Premissas!$B$8,0))),0)) | G9: =F9*(1+Premissas!$B$5+IF(ISNUMBER(Premissas!$C$31),IF(2028=Premissas!$C$31,Premissas!$B$6,IF(2028=Premissas!$C$31+1,Premissas!$B$7,IF(2028=Premissas!$C$31+2,Premissas!$B$8,0))),0)) | H9: =G9*(1+Premissas!$B$5+IF(ISNUMBER(Premissas!$C$31),IF(2029=Premissas!$C$31,Premissas!$B$6,IF(2029=Premissas!$C$31+1,Premissas!$B$7,IF(2029=Premissas!$C$31+2,Premissas!$B$8,0))),0)) | I9: =H9*(1+Premissas!$B$5+IF(ISNUMBER(Premissas!$C$31),IF(2030=Premissas!$C$31,Premissas!$B$6,IF(2030=Premissas!$C$31+1,Premissas!$B$7,IF(2030=Premissas!$C$31+2,Premissas!$B$8,0))),0))
A10: DF | B10: Distrito Federal | C10: Varejo | D10: ='Base Histórica 2025'!C8 | E10: =D10*Premissas!$B$77 | F10: =E10*(1+Premissas!$B$4+IF(ISNUMBER(Premissas!$C$32),IF(2027=Premissas!$C$32,Premissas!$B$6,IF(2027=Premissas!$C$32+1,Premissas!$B$7,IF(2027=Premissas!$C$32+2,Premissas!$B$8,0))),0)) | G10: =F10*(1+Premissas!$B$4+IF(ISNUMBER(Premissas!$C$32),IF(2028=Premissas!$C$32,Premissas!$B$6,IF(2028=Premissas!$C$32+1,Premissas!$B$7,IF(2028=Premissas!$C$32+2,Premissas!$B$8,0))),0)) | H10: =G10*(1+Premissas!$B$4+IF(ISNUMBER(Premissas!$C$32),IF(2029=Premissas!$C$32,Premissas!$B$6,IF(2029=Premissas!$C$32+1,Premissas!$B$7,IF(2029=Premissas!$C$32+2,Premissas!$B$8,0))),0)) | I10: =H10*(1+Premissas!$B$4+IF(ISNUMBER(Premissas!$C$32),IF(2030=Premissas!$C$32,Premissas!$B$6,IF(2030=Premissas!$C$32+1,Premissas!$B$7,IF(2030=Premissas!$C$32+2,Premissas!$B$8,0))),0))
A11: DF | B11: Distrito Federal | C11: B2B | D11: ='Base Histórica 2025'!C39 | E11: =D11*Premissas!$B$77 | F11: =E11*(1+Premissas!$B$5+IF(ISNUMBER(Premissas!$C$32),IF(2027=Premissas!$C$32,Premissas!$B$6,IF(2027=Premissas!$C$32+1,Premissas!$B$7,IF(2027=Premissas!$C$32+2,Premissas!$B$8,0))),0)) | G11: =F11*(1+Premissas!$B$5+IF(ISNUMBER(Premissas!$C$32),IF(2028=Premissas!$C$32,Premissas!$B$6,IF(2028=Premissas!$C$32+1,Premissas!$B$7,IF(2028=Premissas!$C$32+2,Premissas!$B$8,0))),0)) | H11: =G11*(1+Premissas!$B$5+IF(ISNUMBER(Premissas!$C$32),IF(2029=Premissas!$C$32,Premissas!$B$6,IF(2029=Premissas!$C$32+1,Premissas!$B$7,IF(2029=Premissas!$C$32+2,Premissas!$B$8,0))),0)) | I11: =H11*(1+Premissas!$B$5+IF(ISNUMBER(Premissas!$C$32),IF(2030=Premissas!$C$32,Premissas!$B$6,IF(2030=Premissas!$C$32+1,Premissas!$B$7,IF(2030=Premissas!$C$32+2,Premissas!$B$8,0))),0))
A12: PR | B12: Paraná | C12: Varejo | D12: ='Base Histórica 2025'!C9 | E12: =D12*Premissas!$B$77 | F12: =E12*(1+Premissas!$B$4+IF(ISNUMBER(Premissas!$C$33),IF(2027=Premissas!$C$33,Premissas!$B$6,IF(2027=Premissas!$C$33+1,Premissas!$B$7,IF(2027=Premissas!$C$33+2,Premissas!$B$8,0))),0)) | G12: =F12*(1+Premissas!$B$4+IF(ISNUMBER(Premissas!$C$33),IF(2028=Premissas!$C$33,Premissas!$B$6,IF(2028=Premissas!$C$33+1,Premissas!$B$7,IF(2028=Premissas!$C$33+2,Premissas!$B$8,0))),0)) | H12: =G12*(1+Premissas!$B$4+IF(ISNUMBER(Premissas!$C$33),IF(2029=Premissas!$C$33,Premissas!$B$6,IF(2029=Premissas!$C$33+1,Premissas!$B$7,IF(2029=Premissas!$C$33+2,Premissas!$B$8,0))),0)) | I12: =H12*(1+Premissas!$B$4+IF(ISNUMBER(Premissas!$C$33),IF(2030=Premissas!$C$33,Premissas!$B$6,IF(2030=Premissas!$C$33+1,Premissas!$B$7,IF(2030=Premissas!$C$33+2,Premissas!$B$8,0))),0))
A13: PR | B13: Paraná | C13: B2B | D13: ='Base Histórica 2025'!C40 | E13: =D13*Premissas!$B$77 | F13: =E13*(1+Premissas!$B$5+IF(ISNUMBER(Premissas!$C$33),IF(2027=Premissas!$C$33,Premissas!$B$6,IF(2027=Premissas!$C$33+1,Premissas!$B$7,IF(2027=Premissas!$C$33+2,Premissas!$B$8,0))),0)) | G13: =F13*(1+Premissas!$B$5+IF(ISNUMBER(Premissas!$C$33),IF(2028=Premissas!$C$33,Premissas!$B$6,IF(2028=Premissas!$C$33+1,Premissas!$B$7,IF(2028=Premissas!$C$33+2,Premissas!$B$8,0))),0)) | H13: =G13*(1+Premissas!$B$5+IF(ISNUMBER(Premissas!$C$33),IF(2029=Premissas!$C$33,Premissas!$B$6,IF(2029=Premissas!$C$33+1,Premissas!$B$7,IF(2029=Premissas!$C$33+2,Premissas!$B$8,0))),0)) | I13: =H13*(1+Premissas!$B$5+IF(ISNUMBER(Premissas!$C$33),IF(2030=Premissas!$C$33,Premissas!$B$6,IF(2030=Premissas!$C$33+1,Premissas!$B$7,IF(2030=Premissas!$C$33+2,Premissas!$B$8,0))),0))
A14: RS | B14: Rio Grande do Sul | C14: Varejo | D14: ='Base Histórica 2025'!C10 | E14: =D14*Premissas!$B$77 | F14: =E14*(1+Premissas!$B$4+IF(ISNUMBER(Premissas!$C$34),IF(2027=Premissas!$C$34,Premissas!$B$6,IF(2027=Premissas!$C$34+1,Premissas!$B$7,IF(2027=Premissas!$C$34+2,Premissas!$B$8,0))),0)) | G14: =F14*(1+Premissas!$B$4+IF(ISNUMBER(Premissas!$C$34),IF(2028=Premissas!$C$34,Premissas!$B$6,IF(2028=Premissas!$C$34+1,Premissas!$B$7,IF(2028=Premissas!$C$34+2,Premissas!$B$8,0))),0)) | H14: =G14*(1+Premissas!$B$4+IF(ISNUMBER(Premissas!$C$34),IF(2029=Premissas!$C$34,Premissas!$B$6,IF(2029=Premissas!$C$34+1,Premissas!$B$7,IF(2029=Premissas!$C$34+2,Premissas!$B$8,0))),0)) | I14: =H14*(1+Premissas!$B$4+IF(ISNUMBER(Premissas!$C$34),IF(2030=Premissas!$C$34,Premissas!$B$6,IF(2030=Premissas!$C$34+1,Premissas!$B$7,IF(2030=Premissas!$C$34+2,Premissas!$B$8,0))),0))
A15: RS | B15: Rio Grande do Sul | C15: B2B | D15: ='Base Histórica 2025'!C41 | E15: =D15*Premissas!$B$77 | F15: =E15*(1+Premissas!$B$5+IF(ISNUMBER(Premissas!$C$34),IF(2027=Premissas!$C$34,Premissas!$B$6,IF(2027=Premissas!$C$34+1,Premissas!$B$7,IF(2027=Premissas!$C$34+2,Premissas!$B$8,0))),0)) | G15: =F15*(1+Premissas!$B$5+IF(ISNUMBER(Premissas!$C$34),IF(2028=Premissas!$C$34,Premissas!$B$6,IF(2028=Premissas!$C$34+1,Premissas!$B$7,IF(2028=Premissas!$C$34+2,Premissas!$B$8,0))),0)) | H15: =G15*(1+Premissas!$B$5+IF(ISNUMBER(Premissas!$C$34),IF(2029=Premissas!$C$34,Premissas!$B$6,IF(2029=Premissas!$C$34+1,Premissas!$B$7,IF(2029=Premissas!$C$34+2,Premissas!$B$8,0))),0)) | I15: =H15*(1+Premissas!$B$5+IF(ISNUMBER(Premissas!$C$34),IF(2030=Premissas!$C$34,Premissas!$B$6,IF(2030=Premissas!$C$34+1,Premissas!$B$7,IF(2030=Premissas!$C$34+2,Premissas!$B$8,0))),0))
A16: MG | B16: Minas Gerais | C16: Varejo | D16: ='Base Histórica 2025'!C11 | E16: =D16*Premissas!$B$77 | F16: =E16*(1+Premissas!$B$4+IF(ISNUMBER(Premissas!$C$35),IF(2027=Premissas!$C$35,Premissas!$B$6,IF(2027=Premissas!$C$35+1,Premissas!$B$7,IF(2027=Premissas!$C$35+2,Premissas!$B$8,0))),0)) | G16: =F16*(1+Premissas!$B$4+IF(ISNUMBER(Premissas!$C$35),IF(2028=Premissas!$C$35,Premissas!$B$6,IF(2028=Premissas!$C$35+1,Premissas!$B$7,IF(2028=Premissas!$C$35+2,Premissas!$B$8,0))),0)) | H16: =G16*(1+Premissas!$B$4+IF(ISNUMBER(Premissas!$C$35),IF(2029=Premissas!$C$35,Premissas!$B$6,IF(2029=Premissas!$C$35+1,Premissas!$B$7,IF(2029=Premissas!$C$35+2,Premissas!$B$8,0))),0)) | I16: =H16*(1+Premissas!$B$4+IF(ISNUMBER(Premissas!$C$35),IF(2030=Premissas!$C$35,Premissas!$B$6,IF(2030=Premissas!$C$35+1,Premissas!$B$7,IF(2030=Premissas!$C$35+2,Premissas!$B$8,0))),0))
A17: MG | B17: Minas Gerais | C17: B2B | D17: ='Base Histórica 2025'!C42 | E17: =D17*Premissas!$B$77 | F17: =E17*(1+Premissas!$B$5+IF(ISNUMBER(Premissas!$C$35),IF(2027=Premissas!$C$35,Premissas!$B$6,IF(2027=Premissas!$C$35+1,Premissas!$B$7,IF(2027=Premissas!$C$35+2,Premissas!$B$8,0))),0)) | G17: =F17*(1+Premissas!$B$5+IF(ISNUMBER(Premissas!$C$35),IF(2028=Premissas!$C$35,Premissas!$B$6,IF(2028=Premissas!$C$35+1,Premissas!$B$7,IF(2028=Premissas!$C$35+2,Premissas!$B$8,0))),0)) | H17: =G17*(1+Premissas!$B$5+IF(ISNUMBER(Premissas!$C$35),IF(2029=Premissas!$C$35,Premissas!$B$6,IF(2029=Premissas!$C$35+1,Premissas!$B$7,IF(2029=Premissas!$C$35+2,Premissas!$B$8,0))),0)) | I17: =H17*(1+Premissas!$B$5+IF(ISNUMBER(Premissas!$C$35),IF(2030=Premissas!$C$35,Premissas!$B$6,IF(2030=Premissas!$C$35+1,Premissas!$B$7,IF(2030=Premissas!$C$35+2,Premissas!$B$8,0))),0))
A18: ES | B18: Espírito Santo | C18: Varejo | D18: ='Base Histórica 2025'!C12 | E18: =D18*Premissas!$B$77 | F18: =E18*(1+Premissas!$B$4+IF(ISNUMBER(Premissas!$C$36),IF(2027=Premissas!$C$36,Premissas!$B$6,IF(2027=Premissas!$C$36+1,Premissas!$B$7,IF(2027=Premissas!$C$36+2,Premissas!$B$8,0))),0)) | G18: =F18*(1+Premissas!$B$4+IF(ISNUMBER(Premissas!$C$36),IF(2028=Premissas!$C$36,Premissas!$B$6,IF(2028=Premissas!$C$36+1,Premissas!$B$7,IF(2028=Premissas!$C$36+2,Premissas!$B$8,0))),0)) | H18: =G18*(1+Premissas!$B$4+IF(ISNUMBER(Premissas!$C$36),IF(2029=Premissas!$C$36,Premissas!$B$6,IF(2029=Premissas!$C$36+1,Premissas!$B$7,IF(2029=Premissas!$C$36+2,Premissas!$B$8,0))),0)) | I18: =H18*(1+Premissas!$B$4+IF(ISNUMBER(Premissas!$C$36),IF(2030=Premissas!$C$36,Premissas!$B$6,IF(2030=Premissas!$C$36+1,Premissas!$B$7,IF(2030=Premissas!$C$36+2,Premissas!$B$8,0))),0))
A19: ES | B19: Espírito Santo | C19: B2B | D19: ='Base Histórica 2025'!C43 | E19: =D19*Premissas!$B$77 | F19: =E19*(1+Premissas!$B$5+IF(ISNUMBER(Premissas!$C$36),IF(2027=Premissas!$C$36,Premissas!$B$6,IF(2027=Premissas!$C$36+1,Premissas!$B$7,IF(2027=Premissas!$C$36+2,Premissas!$B$8,0))),0)) | G19: =F19*(1+Premissas!$B$5+IF(ISNUMBER(Premissas!$C$36),IF(2028=Premissas!$C$36,Premissas!$B$6,IF(2028=Premissas!$C$36+1,Premissas!$B$7,IF(2028=Premissas!$C$36+2,Premissas!$B$8,0))),0)) | H19: =G19*(1+Premissas!$B$5+IF(ISNUMBER(Premissas!$C$36),IF(2029=Premissas!$C$36,Premissas!$B$6,IF(2029=Premissas!$C$36+1,Premissas!$B$7,IF(2029=Premissas!$C$36+2,Premissas!$B$8,0))),0)) | I19: =H19*(1+Premissas!$B$5+IF(ISNUMBER(Premissas!$C$36),IF(2030=Premissas!$C$36,Premissas!$B$6,IF(2030=Premissas!$C$36+1,Premissas!$B$7,IF(2030=Premissas!$C$36+2,Premissas!$B$8,0))),0))
A20: BA | B20: Bahia | C20: Varejo | D20: ='Base Histórica 2025'!C13 | E20: =D20*Premissas!$B$77 | F20: =E20*(1+Premissas!$B$4+IF(ISNUMBER(Premissas!$C$37),IF(2027=Premissas!$C$37,Premissas!$B$6,IF(2027=Premissas!$C$37+1,Premissas!$B$7,IF(2027=Premissas!$C$37+2,Premissas!$B$8,0))),0)) | G20: =F20*(1+Premissas!$B$4+IF(ISNUMBER(Premissas!$C$37),IF(2028=Premissas!$C$37,Premissas!$B$6,IF(2028=Premissas!$C$37+1,Premissas!$B$7,IF(2028=Premissas!$C$37+2,Premissas!$B$8,0))),0)) | H20: =G20*(1+Premissas!$B$4+IF(ISNUMBER(Premissas!$C$37),IF(2029=Premissas!$C$37,Premissas!$B$6,IF(2029=Premissas!$C$37+1,Premissas!$B$7,IF(2029=Premissas!$C$37+2,Premissas!$B$8,0))),0)) | I20: =H20*(1+Premissas!$B$4+IF(ISNUMBER(Premissas!$C$37),IF(2030=Premissas!$C$37,Premissas!$B$6,IF(2030=Premissas!$C$37+1,Premissas!$B$7,IF(2030=Premissas!$C$37+2,Premissas!$B$8,0))),0))
A21: BA | B21: Bahia | C21: B2B | D21: ='Base Histórica 2025'!C44 | E21: =D21*Premissas!$B$77 | F21: =E21*(1+Premissas!$B$5+IF(ISNUMBER(Premissas!$C$37),IF(2027=Premissas!$C$37,Premissas!$B$6,IF(2027=Premissas!$C$37+1,Premissas!$B$7,IF(2027=Premissas!$C$37+2,Premissas!$B$8,0))),0)) | G21: =F21*(1+Premissas!$B$5+IF(ISNUMBER(Premissas!$C$37),IF(2028=Premissas!$C$37,Premissas!$B$6,IF(2028=Premissas!$C$37+1,Premissas!$B$7,IF(2028=Premissas!$C$37+2,Premissas!$B$8,0))),0)) | H21: =G21*(1+Premissas!$B$5+IF(ISNUMBER(Premissas!$C$37),IF(2029=Premissas!$C$37,Premissas!$B$6,IF(2029=Premissas!$C$37+1,Premissas!$B$7,IF(2029=Premissas!$C$37+2,Premissas!$B$8,0))),0)) | I21: =H21*(1+Premissas!$B$5+IF(ISNUMBER(Premissas!$C$37),IF(2030=Premissas!$C$37,Premissas!$B$6,IF(2030=Premissas!$C$37+1,Premissas!$B$7,IF(2030=Premissas!$C$37+2,Premissas!$B$8,0))),0))
A22: CE | B22: Ceará | C22: Varejo | D22: ='Base Histórica 2025'!C14 | E22: =D22*Premissas!$B$77 | F22: =E22*(1+Premissas!$B$4+IF(ISNUMBER(Premissas!$C$38),IF(2027=Premissas!$C$38,Premissas!$B$6,IF(2027=Premissas!$C$38+1,Premissas!$B$7,IF(2027=Premissas!$C$38+2,Premissas!$B$8,0))),0)) | G22: =F22*(1+Premissas!$B$4+IF(ISNUMBER(Premissas!$C$38),IF(2028=Premissas!$C$38,Premissas!$B$6,IF(2028=Premissas!$C$38+1,Premissas!$B$7,IF(2028=Premissas!$C$38+2,Premissas!$B$8,0))),0)) | H22: =G22*(1+Premissas!$B$4+IF(ISNUMBER(Premissas!$C$38),IF(2029=Premissas!$C$38,Premissas!$B$6,IF(2029=Premissas!$C$38+1,Premissas!$B$7,IF(2029=Premissas!$C$38+2,Premissas!$B$8,0))),0)) | I22: =H22*(1+Premissas!$B$4+IF(ISNUMBER(Premissas!$C$38),IF(2030=Premissas!$C$38,Premissas!$B$6,IF(2030=Premissas!$C$38+1,Premissas!$B$7,IF(2030=Premissas!$C$38+2,Premissas!$B$8,0))),0))
A23: CE | B23: Ceará | C23: B2B | D23: ='Base Histórica 2025'!C45 | E23: =D23*Premissas!$B$77 | F23: =E23*(1+Premissas!$B$5+IF(ISNUMBER(Premissas!$C$38),IF(2027=Premissas!$C$38,Premissas!$B$6,IF(2027=Premissas!$C$38+1,Premissas!$B$7,IF(2027=Premissas!$C$38+2,Premissas!$B$8,0))),0)) | G23: =F23*(1+Premissas!$B$5+IF(ISNUMBER(Premissas!$C$38),IF(2028=Premissas!$C$38,Premissas!$B$6,IF(2028=Premissas!$C$38+1,Premissas!$B$7,IF(2028=Premissas!$C$38+2,Premissas!$B$8,0))),0)) | H23: =G23*(1+Premissas!$B$5+IF(ISNUMBER(Premissas!$C$38),IF(2029=Premissas!$C$38,Premissas!$B$6,IF(2029=Premissas!$C$38+1,Premissas!$B$7,IF(2029=Premissas!$C$38+2,Premissas!$B$8,0))),0)) | I23: =H23*(1+Premissas!$B$5+IF(ISNUMBER(Premissas!$C$38),IF(2030=Premissas!$C$38,Premissas!$B$6,IF(2030=Premissas!$C$38+1,Premissas!$B$7,IF(2030=Premissas!$C$38+2,Premissas!$B$8,0))),0))
A24: PE | B24: Pernambuco | C24: Varejo | D24: ='Base Histórica 2025'!C15 | E24: =D24*Premissas!$B$77 | F24: =E24*(1+Premissas!$B$4+IF(ISNUMBER(Premissas!$C$39),IF(2027=Premissas!$C$39,Premissas!$B$6,IF(2027=Premissas!$C$39+1,Premissas!$B$7,IF(2027=Premissas!$C$39+2,Premissas!$B$8,0))),0)) | G24: =F24*(1+Premissas!$B$4+IF(ISNUMBER(Premissas!$C$39),IF(2028=Premissas!$C$39,Premissas!$B$6,IF(2028=Premissas!$C$39+1,Premissas!$B$7,IF(2028=Premissas!$C$39+2,Premissas!$B$8,0))),0)) | H24: =G24*(1+Premissas!$B$4+IF(ISNUMBER(Premissas!$C$39),IF(2029=Premissas!$C$39,Premissas!$B$6,IF(2029=Premissas!$C$39+1,Premissas!$B$7,IF(2029=Premissas!$C$39+2,Premissas!$B$8,0))),0)) | I24: =H24*(1+Premissas!$B$4+IF(ISNUMBER(Premissas!$C$39),IF(2030=Premissas!$C$39,Premissas!$B$6,IF(2030=Premissas!$C$39+1,Premissas!$B$7,IF(2030=Premissas!$C$39+2,Premissas!$B$8,0))),0))
A25: PE | B25: Pernambuco | C25: B2B | D25: ='Base Histórica 2025'!C46 | E25: =D25*Premissas!$B$77 | F25: =E25*(1+Premissas!$B$5+IF(ISNUMBER(Premissas!$C$39),IF(2027=Premissas!$C$39,Premissas!$B$6,IF(2027=Premissas!$C$39+1,Premissas!$B$7,IF(2027=Premissas!$C$39+2,Premissas!$B$8,0))),0)) | G25: =F25*(1+Premissas!$B$5+IF(ISNUMBER(Premissas!$C$39),IF(2028=Premissas!$C$39,Premissas!$B$6,IF(2028=Premissas!$C$39+1,Premissas!$B$7,IF(2028=Premissas!$C$39+2,Premissas!$B$8,0))),0)) | H25: =G25*(1+Premissas!$B$5+IF(ISNUMBER(Premissas!$C$39),IF(2029=Premissas!$C$39,Premissas!$B$6,IF(2029=Premissas!$C$39+1,Premissas!$B$7,IF(2029=Premissas!$C$39+2,Premissas!$B$8,0))),0)) | I25: =H25*(1+Premissas!$B$5+IF(ISNUMBER(Premissas!$C$39),IF(2030=Premissas!$C$39,Premissas!$B$6,IF(2030=Premissas!$C$39+1,Premissas!$B$7,IF(2030=Premissas!$C$39+2,Premissas!$B$8,0))),0))
A26: MS | B26: Mato Grosso do Sul | C26: Varejo | D26: ='Base Histórica 2025'!C16 | E26: =D26*Premissas!$B$77 | F26: =E26*(1+Premissas!$B$4+IF(ISNUMBER(Premissas!$C$40),IF(2027=Premissas!$C$40,Premissas!$B$6,IF(2027=Premissas!$C$40+1,Premissas!$B$7,IF(2027=Premissas!$C$40+2,Premissas!$B$8,0))),0)) | G26: =F26*(1+Premissas!$B$4+IF(ISNUMBER(Premissas!$C$40),IF(2028=Premissas!$C$40,Premissas!$B$6,IF(2028=Premissas!$C$40+1,Premissas!$B$7,IF(2028=Premissas!$C$40+2,Premissas!$B$8,0))),0)) | H26: =G26*(1+Premissas!$B$4+IF(ISNUMBER(Premissas!$C$40),IF(2029=Premissas!$C$40,Premissas!$B$6,IF(2029=Premissas!$C$40+1,Premissas!$B$7,IF(2029=Premissas!$C$40+2,Premissas!$B$8,0))),0)) | I26: =H26*(1+Premissas!$B$4+IF(ISNUMBER(Premissas!$C$40),IF(2030=Premissas!$C$40,Premissas!$B$6,IF(2030=Premissas!$C$40+1,Premissas!$B$7,IF(2030=Premissas!$C$40+2,Premissas!$B$8,0))),0))
A27: MS | B27: Mato Grosso do Sul | C27: B2B | D27: ='Base Histórica 2025'!C47 | E27: =D27*Premissas!$B$77 | F27: =E27*(1+Premissas!$B$5+IF(ISNUMBER(Premissas!$C$40),IF(2027=Premissas!$C$40,Premissas!$B$6,IF(2027=Premissas!$C$40+1,Premissas!$B$7,IF(2027=Premissas!$C$40+2,Premissas!$B$8,0))),0)) | G27: =F27*(1+Premissas!$B$5+IF(ISNUMBER(Premissas!$C$40),IF(2028=Premissas!$C$40,Premissas!$B$6,IF(2028=Premissas!$C$40+1,Premissas!$B$7,IF(2028=Premissas!$C$40+2,Premissas!$B$8,0))),0)) | H27: =G27*(1+Premissas!$B$5+IF(ISNUMBER(Premissas!$C$40),IF(2029=Premissas!$C$40,Premissas!$B$6,IF(2029=Premissas!$C$40+1,Premissas!$B$7,IF(2029=Premissas!$C$40+2,Premissas!$B$8,0))),0)) | I27: =H27*(1+Premissas!$B$5+IF(ISNUMBER(Premissas!$C$40),IF(2030=Premissas!$C$40,Premissas!$B$6,IF(2030=Premissas!$C$40+1,Premissas!$B$7,IF(2030=Premissas!$C$40+2,Premissas!$B$8,0))),0))
A28: MT | B28: Mato Grosso | C28: Varejo | D28: ='Base Histórica 2025'!C17 | E28: =D28*Premissas!$B$77 | F28: =E28*(1+Premissas!$B$4+IF(ISNUMBER(Premissas!$C$41),IF(2027=Premissas!$C$41,Premissas!$B$6,IF(2027=Premissas!$C$41+1,Premissas!$B$7,IF(2027=Premissas!$C$41+2,Premissas!$B$8,0))),0)) | G28: =F28*(1+Premissas!$B$4+IF(ISNUMBER(Premissas!$C$41),IF(2028=Premissas!$C$41,Premissas!$B$6,IF(2028=Premissas!$C$41+1,Premissas!$B$7,IF(2028=Premissas!$C$41+2,Premissas!$B$8,0))),0)) | H28: =G28*(1+Premissas!$B$4+IF(ISNUMBER(Premissas!$C$41),IF(2029=Premissas!$C$41,Premissas!$B$6,IF(2029=Premissas!$C$41+1,Premissas!$B$7,IF(2029=Premissas!$C$41+2,Premissas!$B$8,0))),0)) | I28: =H28*(1+Premissas!$B$4+IF(ISNUMBER(Premissas!$C$41),IF(2030=Premissas!$C$41,Premissas!$B$6,IF(2030=Premissas!$C$41+1,Premissas!$B$7,IF(2030=Premissas!$C$41+2,Premissas!$B$8,0))),0))
A29: MT | B29: Mato Grosso | C29: B2B | D29: ='Base Histórica 2025'!C48 | E29: =D29*Premissas!$B$77 | F29: =E29*(1+Premissas!$B$5+IF(ISNUMBER(Premissas!$C$41),IF(2027=Premissas!$C$41,Premissas!$B$6,IF(2027=Premissas!$C$41+1,Premissas!$B$7,IF(2027=Premissas!$C$41+2,Premissas!$B$8,0))),0)) | G29: =F29*(1+Premissas!$B$5+IF(ISNUMBER(Premissas!$C$41),IF(2028=Premissas!$C$41,Premissas!$B$6,IF(2028=Premissas!$C$41+1,Premissas!$B$7,IF(2028=Premissas!$C$41+2,Premissas!$B$8,0))),0)) | H29: =G29*(1+Premissas!$B$5+IF(ISNUMBER(Premissas!$C$41),IF(2029=Premissas!$C$41,Premissas!$B$6,IF(2029=Premissas!$C$41+1,Premissas!$B$7,IF(2029=Premissas!$C$41+2,Premissas!$B$8,0))),0)) | I29: =H29*(1+Premissas!$B$5+IF(ISNUMBER(Premissas!$C$41),IF(2030=Premissas!$C$41,Premissas!$B$6,IF(2030=Premissas!$C$41+1,Premissas!$B$7,IF(2030=Premissas!$C$41+2,Premissas!$B$8,0))),0))
A30: AM | B30: Amazonas | C30: Varejo | D30: ='Base Histórica 2025'!C18 | E30: =D30*Premissas!$B$77 | F30: =E30*(1+Premissas!$B$4+IF(ISNUMBER(Premissas!$C$42),IF(2027=Premissas!$C$42,Premissas!$B$6,IF(2027=Premissas!$C$42+1,Premissas!$B$7,IF(2027=Premissas!$C$42+2,Premissas!$B$8,0))),0)) | G30: =F30*(1+Premissas!$B$4+IF(ISNUMBER(Premissas!$C$42),IF(2028=Premissas!$C$42,Premissas!$B$6,IF(2028=Premissas!$C$42+1,Premissas!$B$7,IF(2028=Premissas!$C$42+2,Premissas!$B$8,0))),0)) | H30: =G30*(1+Premissas!$B$4+IF(ISNUMBER(Premissas!$C$42),IF(2029=Premissas!$C$42,Premissas!$B$6,IF(2029=Premissas!$C$42+1,Premissas!$B$7,IF(2029=Premissas!$C$42+2,Premissas!$B$8,0))),0)) | I30: =H30*(1+Premissas!$B$4+IF(ISNUMBER(Premissas!$C$42),IF(2030=Premissas!$C$42,Premissas!$B$6,IF(2030=Premissas!$C$42+1,Premissas!$B$7,IF(2030=Premissas!$C$42+2,Premissas!$B$8,0))),0))
A31: AM | B31: Amazonas | C31: B2B | D31: ='Base Histórica 2025'!C49 | E31: =D31*Premissas!$B$77 | F31: =E31*(1+Premissas!$B$5+IF(ISNUMBER(Premissas!$C$42),IF(2027=Premissas!$C$42,Premissas!$B$6,IF(2027=Premissas!$C$42+1,Premissas!$B$7,IF(2027=Premissas!$C$42+2,Premissas!$B$8,0))),0)) | G31: =F31*(1+Premissas!$B$5+IF(ISNUMBER(Premissas!$C$42),IF(2028=Premissas!$C$42,Premissas!$B$6,IF(2028=Premissas!$C$42+1,Premissas!$B$7,IF(2028=Premissas!$C$42+2,Premissas!$B$8,0))),0)) | H31: =G31*(1+Premissas!$B$5+IF(ISNUMBER(Premissas!$C$42),IF(2029=Premissas!$C$42,Premissas!$B$6,IF(2029=Premissas!$C$42+1,Premissas!$B$7,IF(2029=Premissas!$C$42+2,Premissas!$B$8,0))),0)) | I31: =H31*(1+Premissas!$B$5+IF(ISNUMBER(Premissas!$C$42),IF(2030=Premissas!$C$42,Premissas!$B$6,IF(2030=Premissas!$C$42+1,Premissas!$B$7,IF(2030=Premissas!$C$42+2,Premissas!$B$8,0))),0))
A32: AC | B32: Acre | C32: Varejo | D32: ='Base Histórica 2025'!C19 | E32: =D32*Premissas!$B$77 | F32: =E32*(1+Premissas!$B$4+IF(ISNUMBER(Premissas!$C$43),IF(2027=Premissas!$C$43,Premissas!$B$6,IF(2027=Premissas!$C$43+1,Premissas!$B$7,IF(2027=Premissas!$C$43+2,Premissas!$B$8,0))),0)) | G32: =F32*(1+Premissas!$B$4+IF(ISNUMBER(Premissas!$C$43),IF(2028=Premissas!$C$43,Premissas!$B$6,IF(2028=Premissas!$C$43+1,Premissas!$B$7,IF(2028=Premissas!$C$43+2,Premissas!$B$8,0))),0)) | H32: =G32*(1+Premissas!$B$4+IF(ISNUMBER(Premissas!$C$43),IF(2029=Premissas!$C$43,Premissas!$B$6,IF(2029=Premissas!$C$43+1,Premissas!$B$7,IF(2029=Premissas!$C$43+2,Premissas!$B$8,0))),0)) | I32: =H32*(1+Premissas!$B$4+IF(ISNUMBER(Premissas!$C$43),IF(2030=Premissas!$C$43,Premissas!$B$6,IF(2030=Premissas!$C$43+1,Premissas!$B$7,IF(2030=Premissas!$C$43+2,Premissas!$B$8,0))),0))
A33: AC | B33: Acre | C33: B2B | D33: ='Base Histórica 2025'!C50 | E33: =D33*Premissas!$B$77 | F33: =E33*(1+Premissas!$B$5+IF(ISNUMBER(Premissas!$C$43),IF(2027=Premissas!$C$43,Premissas!$B$6,IF(2027=Premissas!$C$43+1,Premissas!$B$7,IF(2027=Premissas!$C$43+2,Premissas!$B$8,0))),0)) | G33: =F33*(1+Premissas!$B$5+IF(ISNUMBER(Premissas!$C$43),IF(2028=Premissas!$C$43,Premissas!$B$6,IF(2028=Premissas!$C$43+1,Premissas!$B$7,IF(2028=Premissas!$C$43+2,Premissas!$B$8,0))),0)) | H33: =G33*(1+Premissas!$B$5+IF(ISNUMBER(Premissas!$C$43),IF(2029=Premissas!$C$43,Premissas!$B$6,IF(2029=Premissas!$C$43+1,Premissas!$B$7,IF(2029=Premissas!$C$43+2,Premissas!$B$8,0))),0)) | I33: =H33*(1+Premissas!$B$5+IF(ISNUMBER(Premissas!$C$43),IF(2030=Premissas!$C$43,Premissas!$B$6,IF(2030=Premissas!$C$43+1,Premissas!$B$7,IF(2030=Premissas!$C$43+2,Premissas!$B$8,0))),0))
A34: AL | B34: Alagoas | C34: Varejo | D34: ='Base Histórica 2025'!C20 | E34: =D34*Premissas!$B$77 | F34: =E34*(1+Premissas!$B$4+IF(ISNUMBER(Premissas!$C$44),IF(2027=Premissas!$C$44,Premissas!$B$6,IF(2027=Premissas!$C$44+1,Premissas!$B$7,IF(2027=Premissas!$C$44+2,Premissas!$B$8,0))),0)) | G34: =F34*(1+Premissas!$B$4+IF(ISNUMBER(Premissas!$C$44),IF(2028=Premissas!$C$44,Premissas!$B$6,IF(2028=Premissas!$C$44+1,Premissas!$B$7,IF(2028=Premissas!$C$44+2,Premissas!$B$8,0))),0)) | H34: =G34*(1+Premissas!$B$4+IF(ISNUMBER(Premissas!$C$44),IF(2029=Premissas!$C$44,Premissas!$B$6,IF(2029=Premissas!$C$44+1,Premissas!$B$7,IF(2029=Premissas!$C$44+2,Premissas!$B$8,0))),0)) | I34: =H34*(1+Premissas!$B$4+IF(ISNUMBER(Premissas!$C$44),IF(2030=Premissas!$C$44,Premissas!$B$6,IF(2030=Premissas!$C$44+1,Premissas!$B$7,IF(2030=Premissas!$C$44+2,Premissas!$B$8,0))),0))
A35: AL | B35: Alagoas | C35: B2B | D35: ='Base Histórica 2025'!C51 | E35: =D35*Premissas!$B$77 | F35: =E35*(1+Premissas!$B$5+IF(ISNUMBER(Premissas!$C$44),IF(2027=Premissas!$C$44,Premissas!$B$6,IF(2027=Premissas!$C$44+1,Premissas!$B$7,IF(2027=Premissas!$C$44+2,Premissas!$B$8,0))),0)) | G35: =F35*(1+Premissas!$B$5+IF(ISNUMBER(Premissas!$C$44),IF(2028=Premissas!$C$44,Premissas!$B$6,IF(2028=Premissas!$C$44+1,Premissas!$B$7,IF(2028=Premissas!$C$44+2,Premissas!$B$8,0))),0)) | H35: =G35*(1+Premissas!$B$5+IF(ISNUMBER(Premissas!$C$44),IF(2029=Premissas!$C$44,Premissas!$B$6,IF(2029=Premissas!$C$44+1,Premissas!$B$7,IF(2029=Premissas!$C$44+2,Premissas!$B$8,0))),0)) | I35: =H35*(1+Premissas!$B$5+IF(ISNUMBER(Premissas!$C$44),IF(2030=Premissas!$C$44,Premissas!$B$6,IF(2030=Premissas!$C$44+1,Premissas!$B$7,IF(2030=Premissas!$C$44+2,Premissas!$B$8,0))),0))
A36: AP | B36: Amapá | C36: Varejo | D36: ='Base Histórica 2025'!C21 | E36: =D36*Premissas!$B$77 | F36: =E36*(1+Premissas!$B$4+IF(ISNUMBER(Premissas!$C$45),IF(2027=Premissas!$C$45,Premissas!$B$6,IF(2027=Premissas!$C$45+1,Premissas!$B$7,IF(2027=Premissas!$C$45+2,Premissas!$B$8,0))),0)) | G36: =F36*(1+Premissas!$B$4+IF(ISNUMBER(Premissas!$C$45),IF(2028=Premissas!$C$45,Premissas!$B$6,IF(2028=Premissas!$C$45+1,Premissas!$B$7,IF(2028=Premissas!$C$45+2,Premissas!$B$8,0))),0)) | H36: =G36*(1+Premissas!$B$4+IF(ISNUMBER(Premissas!$C$45),IF(2029=Premissas!$C$45,Premissas!$B$6,IF(2029=Premissas!$C$45+1,Premissas!$B$7,IF(2029=Premissas!$C$45+2,Premissas!$B$8,0))),0)) | I36: =H36*(1+Premissas!$B$4+IF(ISNUMBER(Premissas!$C$45),IF(2030=Premissas!$C$45,Premissas!$B$6,IF(2030=Premissas!$C$45+1,Premissas!$B$7,IF(2030=Premissas!$C$45+2,Premissas!$B$8,0))),0))
A37: AP | B37: Amapá | C37: B2B | D37: ='Base Histórica 2025'!C52 | E37: =D37*Premissas!$B$77 | F37: =E37*(1+Premissas!$B$5+IF(ISNUMBER(Premissas!$C$45),IF(2027=Premissas!$C$45,Premissas!$B$6,IF(2027=Premissas!$C$45+1,Premissas!$B$7,IF(2027=Premissas!$C$45+2,Premissas!$B$8,0))),0)) | G37: =F37*(1+Premissas!$B$5+IF(ISNUMBER(Premissas!$C$45),IF(2028=Premissas!$C$45,Premissas!$B$6,IF(2028=Premissas!$C$45+1,Premissas!$B$7,IF(2028=Premissas!$C$45+2,Premissas!$B$8,0))),0)) | H37: =G37*(1+Premissas!$B$5+IF(ISNUMBER(Premissas!$C$45),IF(2029=Premissas!$C$45,Premissas!$B$6,IF(2029=Premissas!$C$45+1,Premissas!$B$7,IF(2029=Premissas!$C$45+2,Premissas!$B$8,0))),0)) | I37: =H37*(1+Premissas!$B$5+IF(ISNUMBER(Premissas!$C$45),IF(2030=Premissas!$C$45,Premissas!$B$6,IF(2030=Premissas!$C$45+1,Premissas!$B$7,IF(2030=Premissas!$C$45+2,Premissas!$B$8,0))),0))
A38: GO | B38: Goiás | C38: Varejo | D38: ='Base Histórica 2025'!C22 | E38: =D38*Premissas!$B$77 | F38: =E38*(1+Premissas!$B$4+IF(ISNUMBER(Premissas!$C$46),IF(2027=Premissas!$C$46,Premissas!$B$6,IF(2027=Premissas!$C$46+1,Premissas!$B$7,IF(2027=Premissas!$C$46+2,Premissas!$B$8,0))),0)) | G38: =F38*(1+Premissas!$B$4+IF(ISNUMBER(Premissas!$C$46),IF(2028=Premissas!$C$46,Premissas!$B$6,IF(2028=Premissas!$C$46+1,Premissas!$B$7,IF(2028=Premissas!$C$46+2,Premissas!$B$8,0))),0)) | H38: =G38*(1+Premissas!$B$4+IF(ISNUMBER(Premissas!$C$46),IF(2029=Premissas!$C$46,Premissas!$B$6,IF(2029=Premissas!$C$46+1,Premissas!$B$7,IF(2029=Premissas!$C$46+2,Premissas!$B$8,0))),0)) | I38: =H38*(1+Premissas!$B$4+IF(ISNUMBER(Premissas!$C$46),IF(2030=Premissas!$C$46,Premissas!$B$6,IF(2030=Premissas!$C$46+1,Premissas!$B$7,IF(2030=Premissas!$C$46+2,Premissas!$B$8,0))),0))
A39: GO | B39: Goiás | C39: B2B | D39: ='Base Histórica 2025'!C53 | E39: =D39*Premissas!$B$77 | F39: =E39*(1+Premissas!$B$5+IF(ISNUMBER(Premissas!$C$46),IF(2027=Premissas!$C$46,Premissas!$B$6,IF(2027=Premissas!$C$46+1,Premissas!$B$7,IF(2027=Premissas!$C$46+2,Premissas!$B$8,0))),0)) | G39: =F39*(1+Premissas!$B$5+IF(ISNUMBER(Premissas!$C$46),IF(2028=Premissas!$C$46,Premissas!$B$6,IF(2028=Premissas!$C$46+1,Premissas!$B$7,IF(2028=Premissas!$C$46+2,Premissas!$B$8,0))),0)) | H39: =G39*(1+Premissas!$B$5+IF(ISNUMBER(Premissas!$C$46),IF(2029=Premissas!$C$46,Premissas!$B$6,IF(2029=Premissas!$C$46+1,Premissas!$B$7,IF(2029=Premissas!$C$46+2,Premissas!$B$8,0))),0)) | I39: =H39*(1+Premissas!$B$5+IF(ISNUMBER(Premissas!$C$46),IF(2030=Premissas!$C$46,Premissas!$B$6,IF(2030=Premissas!$C$46+1,Premissas!$B$7,IF(2030=Premissas!$C$46+2,Premissas!$B$8,0))),0))
A40: MA | B40: Maranhão | C40: Varejo | D40: ='Base Histórica 2025'!C23 | E40: =D40*Premissas!$B$77 | F40: =E40*(1+Premissas!$B$4+IF(ISNUMBER(Premissas!$C$47),IF(2027=Premissas!$C$47,Premissas!$B$6,IF(2027=Premissas!$C$47+1,Premissas!$B$7,IF(2027=Premissas!$C$47+2,Premissas!$B$8,0))),0)) | G40: =F40*(1+Premissas!$B$4+IF(ISNUMBER(Premissas!$C$47),IF(2028=Premissas!$C$47,Premissas!$B$6,IF(2028=Premissas!$C$47+1,Premissas!$B$7,IF(2028=Premissas!$C$47+2,Premissas!$B$8,0))),0)) | H40: =G40*(1+Premissas!$B$4+IF(ISNUMBER(Premissas!$C$47),IF(2029=Premissas!$C$47,Premissas!$B$6,IF(2029=Premissas!$C$47+1,Premissas!$B$7,IF(2029=Premissas!$C$47+2,Premissas!$B$8,0))),0)) | I40: =H40*(1+Premissas!$B$4+IF(ISNUMBER(Premissas!$C$47),IF(2030=Premissas!$C$47,Premissas!$B$6,IF(2030=Premissas!$C$47+1,Premissas!$B$7,IF(2030=Premissas!$C$47+2,Premissas!$B$8,0))),0))
A41: MA | B41: Maranhão | C41: B2B | D41: ='Base Histórica 2025'!C54 | E41: =D41*Premissas!$B$77 | F41: =E41*(1+Premissas!$B$5+IF(ISNUMBER(Premissas!$C$47),IF(2027=Premissas!$C$47,Premissas!$B$6,IF(2027=Premissas!$C$47+1,Premissas!$B$7,IF(2027=Premissas!$C$47+2,Premissas!$B$8,0))),0)) | G41: =F41*(1+Premissas!$B$5+IF(ISNUMBER(Premissas!$C$47),IF(2028=Premissas!$C$47,Premissas!$B$6,IF(2028=Premissas!$C$47+1,Premissas!$B$7,IF(2028=Premissas!$C$47+2,Premissas!$B$8,0))),0)) | H41: =G41*(1+Premissas!$B$5+IF(ISNUMBER(Premissas!$C$47),IF(2029=Premissas!$C$47,Premissas!$B$6,IF(2029=Premissas!$C$47+1,Premissas!$B$7,IF(2029=Premissas!$C$47+2,Premissas!$B$8,0))),0)) | I41: =H41*(1+Premissas!$B$5+IF(ISNUMBER(Premissas!$C$47),IF(2030=Premissas!$C$47,Premissas!$B$6,IF(2030=Premissas!$C$47+1,Premissas!$B$7,IF(2030=Premissas!$C$47+2,Premissas!$B$8,0))),0))
A42: PA | B42: Pará | C42: Varejo | D42: ='Base Histórica 2025'!C24 | E42: =D42*Premissas!$B$77 | F42: =E42*(1+Premissas!$B$4+IF(ISNUMBER(Premissas!$C$48),IF(2027=Premissas!$C$48,Premissas!$B$6,IF(2027=Premissas!$C$48+1,Premissas!$B$7,IF(2027=Premissas!$C$48+2,Premissas!$B$8,0))),0)) | G42: =F42*(1+Premissas!$B$4+IF(ISNUMBER(Premissas!$C$48),IF(2028=Premissas!$C$48,Premissas!$B$6,IF(2028=Premissas!$C$48+1,Premissas!$B$7,IF(2028=Premissas!$C$48+2,Premissas!$B$8,0))),0)) | H42: =G42*(1+Premissas!$B$4+IF(ISNUMBER(Premissas!$C$48),IF(2029=Premissas!$C$48,Premissas!$B$6,IF(2029=Premissas!$C$48+1,Premissas!$B$7,IF(2029=Premissas!$C$48+2,Premissas!$B$8,0))),0)) | I42: =H42*(1+Premissas!$B$4+IF(ISNUMBER(Premissas!$C$48),IF(2030=Premissas!$C$48,Premissas!$B$6,IF(2030=Premissas!$C$48+1,Premissas!$B$7,IF(2030=Premissas!$C$48+2,Premissas!$B$8,0))),0))
A43: PA | B43: Pará | C43: B2B | D43: ='Base Histórica 2025'!C55 | E43: =D43*Premissas!$B$77 | F43: =E43*(1+Premissas!$B$5+IF(ISNUMBER(Premissas!$C$48),IF(2027=Premissas!$C$48,Premissas!$B$6,IF(2027=Premissas!$C$48+1,Premissas!$B$7,IF(2027=Premissas!$C$48+2,Premissas!$B$8,0))),0)) | G43: =F43*(1+Premissas!$B$5+IF(ISNUMBER(Premissas!$C$48),IF(2028=Premissas!$C$48,Premissas!$B$6,IF(2028=Premissas!$C$48+1,Premissas!$B$7,IF(2028=Premissas!$C$48+2,Premissas!$B$8,0))),0)) | H43: =G43*(1+Premissas!$B$5+IF(ISNUMBER(Premissas!$C$48),IF(2029=Premissas!$C$48,Premissas!$B$6,IF(2029=Premissas!$C$48+1,Premissas!$B$7,IF(2029=Premissas!$C$48+2,Premissas!$B$8,0))),0)) | I43: =H43*(1+Premissas!$B$5+IF(ISNUMBER(Premissas!$C$48),IF(2030=Premissas!$C$48,Premissas!$B$6,IF(2030=Premissas!$C$48+1,Premissas!$B$7,IF(2030=Premissas!$C$48+2,Premissas!$B$8,0))),0))
A44: PB | B44: Paraíba | C44: Varejo | D44: ='Base Histórica 2025'!C25 | E44: =D44*Premissas!$B$77 | F44: =E44*(1+Premissas!$B$4+IF(ISNUMBER(Premissas!$C$49),IF(2027=Premissas!$C$49,Premissas!$B$6,IF(2027=Premissas!$C$49+1,Premissas!$B$7,IF(2027=Premissas!$C$49+2,Premissas!$B$8,0))),0)) | G44: =F44*(1+Premissas!$B$4+IF(ISNUMBER(Premissas!$C$49),IF(2028=Premissas!$C$49,Premissas!$B$6,IF(2028=Premissas!$C$49+1,Premissas!$B$7,IF(2028=Premissas!$C$49+2,Premissas!$B$8,0))),0)) | H44: =G44*(1+Premissas!$B$4+IF(ISNUMBER(Premissas!$C$49),IF(2029=Premissas!$C$49,Premissas!$B$6,IF(2029=Premissas!$C$49+1,Premissas!$B$7,IF(2029=Premissas!$C$49+2,Premissas!$B$8,0))),0)) | I44: =H44*(1+Premissas!$B$4+IF(ISNUMBER(Premissas!$C$49),IF(2030=Premissas!$C$49,Premissas!$B$6,IF(2030=Premissas!$C$49+1,Premissas!$B$7,IF(2030=Premissas!$C$49+2,Premissas!$B$8,0))),0))
A45: PB | B45: Paraíba | C45: B2B | D45: ='Base Histórica 2025'!C56 | E45: =D45*Premissas!$B$77 | F45: =E45*(1+Premissas!$B$5+IF(ISNUMBER(Premissas!$C$49),IF(2027=Premissas!$C$49,Premissas!$B$6,IF(2027=Premissas!$C$49+1,Premissas!$B$7,IF(2027=Premissas!$C$49+2,Premissas!$B$8,0))),0)) | G45: =F45*(1+Premissas!$B$5+IF(ISNUMBER(Premissas!$C$49),IF(2028=Premissas!$C$49,Premissas!$B$6,IF(2028=Premissas!$C$49+1,Premissas!$B$7,IF(2028=Premissas!$C$49+2,Premissas!$B$8,0))),0)) | H45: =G45*(1+Premissas!$B$5+IF(ISNUMBER(Premissas!$C$49),IF(2029=Premissas!$C$49,Premissas!$B$6,IF(2029=Premissas!$C$49+1,Premissas!$B$7,IF(2029=Premissas!$C$49+2,Premissas!$B$8,0))),0)) | I45: =H45*(1+Premissas!$B$5+IF(ISNUMBER(Premissas!$C$49),IF(2030=Premissas!$C$49,Premissas!$B$6,IF(2030=Premissas!$C$49+1,Premissas!$B$7,IF(2030=Premissas!$C$49+2,Premissas!$B$8,0))),0))
A46: PI | B46: Piauí | C46: Varejo | D46: ='Base Histórica 2025'!C26 | E46: =D46*Premissas!$B$77 | F46: =E46*(1+Premissas!$B$4+IF(ISNUMBER(Premissas!$C$50),IF(2027=Premissas!$C$50,Premissas!$B$6,IF(2027=Premissas!$C$50+1,Premissas!$B$7,IF(2027=Premissas!$C$50+2,Premissas!$B$8,0))),0)) | G46: =F46*(1+Premissas!$B$4+IF(ISNUMBER(Premissas!$C$50),IF(2028=Premissas!$C$50,Premissas!$B$6,IF(2028=Premissas!$C$50+1,Premissas!$B$7,IF(2028=Premissas!$C$50+2,Premissas!$B$8,0))),0)) | H46: =G46*(1+Premissas!$B$4+IF(ISNUMBER(Premissas!$C$50),IF(2029=Premissas!$C$50,Premissas!$B$6,IF(2029=Premissas!$C$50+1,Premissas!$B$7,IF(2029=Premissas!$C$50+2,Premissas!$B$8,0))),0)) | I46: =H46*(1+Premissas!$B$4+IF(ISNUMBER(Premissas!$C$50),IF(2030=Premissas!$C$50,Premissas!$B$6,IF(2030=Premissas!$C$50+1,Premissas!$B$7,IF(2030=Premissas!$C$50+2,Premissas!$B$8,0))),0))
A47: PI | B47: Piauí | C47: B2B | D47: ='Base Histórica 2025'!C57 | E47: =D47*Premissas!$B$77 | F47: =E47*(1+Premissas!$B$5+IF(ISNUMBER(Premissas!$C$50),IF(2027=Premissas!$C$50,Premissas!$B$6,IF(2027=Premissas!$C$50+1,Premissas!$B$7,IF(2027=Premissas!$C$50+2,Premissas!$B$8,0))),0)) | G47: =F47*(1+Premissas!$B$5+IF(ISNUMBER(Premissas!$C$50),IF(2028=Premissas!$C$50,Premissas!$B$6,IF(2028=Premissas!$C$50+1,Premissas!$B$7,IF(2028=Premissas!$C$50+2,Premissas!$B$8,0))),0)) | H47: =G47*(1+Premissas!$B$5+IF(ISNUMBER(Premissas!$C$50),IF(2029=Premissas!$C$50,Premissas!$B$6,IF(2029=Premissas!$C$50+1,Premissas!$B$7,IF(2029=Premissas!$C$50+2,Premissas!$B$8,0))),0)) | I47: =H47*(1+Premissas!$B$5+IF(ISNUMBER(Premissas!$C$50),IF(2030=Premissas!$C$50,Premissas!$B$6,IF(2030=Premissas!$C$50+1,Premissas!$B$7,IF(2030=Premissas!$C$50+2,Premissas!$B$8,0))),0))
A48: RN | B48: Rio Grande do Norte | C48: Varejo | D48: ='Base Histórica 2025'!C27 | E48: =D48*Premissas!$B$77 | F48: =E48*(1+Premissas!$B$4+IF(ISNUMBER(Premissas!$C$51),IF(2027=Premissas!$C$51,Premissas!$B$6,IF(2027=Premissas!$C$51+1,Premissas!$B$7,IF(2027=Premissas!$C$51+2,Premissas!$B$8,0))),0)) | G48: =F48*(1+Premissas!$B$4+IF(ISNUMBER(Premissas!$C$51),IF(2028=Premissas!$C$51,Premissas!$B$6,IF(2028=Premissas!$C$51+1,Premissas!$B$7,IF(2028=Premissas!$C$51+2,Premissas!$B$8,0))),0)) | H48: =G48*(1+Premissas!$B$4+IF(ISNUMBER(Premissas!$C$51),IF(2029=Premissas!$C$51,Premissas!$B$6,IF(2029=Premissas!$C$51+1,Premissas!$B$7,IF(2029=Premissas!$C$51+2,Premissas!$B$8,0))),0)) | I48: =H48*(1+Premissas!$B$4+IF(ISNUMBER(Premissas!$C$51),IF(2030=Premissas!$C$51,Premissas!$B$6,IF(2030=Premissas!$C$51+1,Premissas!$B$7,IF(2030=Premissas!$C$51+2,Premissas!$B$8,0))),0))
A49: RN | B49: Rio Grande do Norte | C49: B2B | D49: ='Base Histórica 2025'!C58 | E49: =D49*Premissas!$B$77 | F49: =E49*(1+Premissas!$B$5+IF(ISNUMBER(Premissas!$C$51),IF(2027=Premissas!$C$51,Premissas!$B$6,IF(2027=Premissas!$C$51+1,Premissas!$B$7,IF(2027=Premissas!$C$51+2,Premissas!$B$8,0))),0)) | G49: =F49*(1+Premissas!$B$5+IF(ISNUMBER(Premissas!$C$51),IF(2028=Premissas!$C$51,Premissas!$B$6,IF(2028=Premissas!$C$51+1,Premissas!$B$7,IF(2028=Premissas!$C$51+2,Premissas!$B$8,0))),0)) | H49: =G49*(1+Premissas!$B$5+IF(ISNUMBER(Premissas!$C$51),IF(2029=Premissas!$C$51,Premissas!$B$6,IF(2029=Premissas!$C$51+1,Premissas!$B$7,IF(2029=Premissas!$C$51+2,Premissas!$B$8,0))),0)) | I49: =H49*(1+Premissas!$B$5+IF(ISNUMBER(Premissas!$C$51),IF(2030=Premissas!$C$51,Premissas!$B$6,IF(2030=Premissas!$C$51+1,Premissas!$B$7,IF(2030=Premissas!$C$51+2,Premissas!$B$8,0))),0))
A50: RO | B50: Rondônia | C50: Varejo | D50: ='Base Histórica 2025'!C28 | E50: =D50*Premissas!$B$77 | F50: =E50*(1+Premissas!$B$4+IF(ISNUMBER(Premissas!$C$52),IF(2027=Premissas!$C$52,Premissas!$B$6,IF(2027=Premissas!$C$52+1,Premissas!$B$7,IF(2027=Premissas!$C$52+2,Premissas!$B$8,0))),0)) | G50: =F50*(1+Premissas!$B$4+IF(ISNUMBER(Premissas!$C$52),IF(2028=Premissas!$C$52,Premissas!$B$6,IF(2028=Premissas!$C$52+1,Premissas!$B$7,IF(2028=Premissas!$C$52+2,Premissas!$B$8,0))),0)) | H50: =G50*(1+Premissas!$B$4+IF(ISNUMBER(Premissas!$C$52),IF(2029=Premissas!$C$52,Premissas!$B$6,IF(2029=Premissas!$C$52+1,Premissas!$B$7,IF(2029=Premissas!$C$52+2,Premissas!$B$8,0))),0)) | I50: =H50*(1+Premissas!$B$4+IF(ISNUMBER(Premissas!$C$52),IF(2030=Premissas!$C$52,Premissas!$B$6,IF(2030=Premissas!$C$52+1,Premissas!$B$7,IF(2030=Premissas!$C$52+2,Premissas!$B$8,0))),0))
A51: RO | B51: Rondônia | C51: B2B | D51: ='Base Histórica 2025'!C59 | E51: =D51*Premissas!$B$77 | F51: =E51*(1+Premissas!$B$5+IF(ISNUMBER(Premissas!$C$52),IF(2027=Premissas!$C$52,Premissas!$B$6,IF(2027=Premissas!$C$52+1,Premissas!$B$7,IF(2027=Premissas!$C$52+2,Premissas!$B$8,0))),0)) | G51: =F51*(1+Premissas!$B$5+IF(ISNUMBER(Premissas!$C$52),IF(2028=Premissas!$C$52,Premissas!$B$6,IF(2028=Premissas!$C$52+1,Premissas!$B$7,IF(2028=Premissas!$C$52+2,Premissas!$B$8,0))),0)) | H51: =G51*(1+Premissas!$B$5+IF(ISNUMBER(Premissas!$C$52),IF(2029=Premissas!$C$52,Premissas!$B$6,IF(2029=Premissas!$C$52+1,Premissas!$B$7,IF(2029=Premissas!$C$52+2,Premissas!$B$8,0))),0)) | I51: =H51*(1+Premissas!$B$5+IF(ISNUMBER(Premissas!$C$52),IF(2030=Premissas!$C$52,Premissas!$B$6,IF(2030=Premissas!$C$52+1,Premissas!$B$7,IF(2030=Premissas!$C$52+2,Premissas!$B$8,0))),0))
A52: RR | B52: Roraima | C52: Varejo | D52: ='Base Histórica 2025'!C29 | E52: =D52*Premissas!$B$77 | F52: =E52*(1+Premissas!$B$4+IF(ISNUMBER(Premissas!$C$53),IF(2027=Premissas!$C$53,Premissas!$B$6,IF(2027=Premissas!$C$53+1,Premissas!$B$7,IF(2027=Premissas!$C$53+2,Premissas!$B$8,0))),0)) | G52: =F52*(1+Premissas!$B$4+IF(ISNUMBER(Premissas!$C$53),IF(2028=Premissas!$C$53,Premissas!$B$6,IF(2028=Premissas!$C$53+1,Premissas!$B$7,IF(2028=Premissas!$C$53+2,Premissas!$B$8,0))),0)) | H52: =G52*(1+Premissas!$B$4+IF(ISNUMBER(Premissas!$C$53),IF(2029=Premissas!$C$53,Premissas!$B$6,IF(2029=Premissas!$C$53+1,Premissas!$B$7,IF(2029=Premissas!$C$53+2,Premissas!$B$8,0))),0)) | I52: =H52*(1+Premissas!$B$4+IF(ISNUMBER(Premissas!$C$53),IF(2030=Premissas!$C$53,Premissas!$B$6,IF(2030=Premissas!$C$53+1,Premissas!$B$7,IF(2030=Premissas!$C$53+2,Premissas!$B$8,0))),0))
A53: RR | B53: Roraima | C53: B2B | D53: ='Base Histórica 2025'!C60 | E53: =D53*Premissas!$B$77 | F53: =E53*(1+Premissas!$B$5+IF(ISNUMBER(Premissas!$C$53),IF(2027=Premissas!$C$53,Premissas!$B$6,IF(2027=Premissas!$C$53+1,Premissas!$B$7,IF(2027=Premissas!$C$53+2,Premissas!$B$8,0))),0)) | G53: =F53*(1+Premissas!$B$5+IF(ISNUMBER(Premissas!$C$53),IF(2028=Premissas!$C$53,Premissas!$B$6,IF(2028=Premissas!$C$53+1,Premissas!$B$7,IF(2028=Premissas!$C$53+2,Premissas!$B$8,0))),0)) | H53: =G53*(1+Premissas!$B$5+IF(ISNUMBER(Premissas!$C$53),IF(2029=Premissas!$C$53,Premissas!$B$6,IF(2029=Premissas!$C$53+1,Premissas!$B$7,IF(2029=Premissas!$C$53+2,Premissas!$B$8,0))),0)) | I53: =H53*(1+Premissas!$B$5+IF(ISNUMBER(Premissas!$C$53),IF(2030=Premissas!$C$53,Premissas!$B$6,IF(2030=Premissas!$C$53+1,Premissas!$B$7,IF(2030=Premissas!$C$53+2,Premissas!$B$8,0))),0))
A54: SE | B54: Sergipe | C54: Varejo | D54: ='Base Histórica 2025'!C30 | E54: =D54*Premissas!$B$77 | F54: =E54*(1+Premissas!$B$4+IF(ISNUMBER(Premissas!$C$54),IF(2027=Premissas!$C$54,Premissas!$B$6,IF(2027=Premissas!$C$54+1,Premissas!$B$7,IF(2027=Premissas!$C$54+2,Premissas!$B$8,0))),0)) | G54: =F54*(1+Premissas!$B$4+IF(ISNUMBER(Premissas!$C$54),IF(2028=Premissas!$C$54,Premissas!$B$6,IF(2028=Premissas!$C$54+1,Premissas!$B$7,IF(2028=Premissas!$C$54+2,Premissas!$B$8,0))),0)) | H54: =G54*(1+Premissas!$B$4+IF(ISNUMBER(Premissas!$C$54),IF(2029=Premissas!$C$54,Premissas!$B$6,IF(2029=Premissas!$C$54+1,Premissas!$B$7,IF(2029=Premissas!$C$54+2,Premissas!$B$8,0))),0)) | I54: =H54*(1+Premissas!$B$4+IF(ISNUMBER(Premissas!$C$54),IF(2030=Premissas!$C$54,Premissas!$B$6,IF(2030=Premissas!$C$54+1,Premissas!$B$7,IF(2030=Premissas!$C$54+2,Premissas!$B$8,0))),0))
A55: SE | B55: Sergipe | C55: B2B | D55: ='Base Histórica 2025'!C61 | E55: =D55*Premissas!$B$77 | F55: =E55*(1+Premissas!$B$5+IF(ISNUMBER(Premissas!$C$54),IF(2027=Premissas!$C$54,Premissas!$B$6,IF(2027=Premissas!$C$54+1,Premissas!$B$7,IF(2027=Premissas!$C$54+2,Premissas!$B$8,0))),0)) | G55: =F55*(1+Premissas!$B$5+IF(ISNUMBER(Premissas!$C$54),IF(2028=Premissas!$C$54,Premissas!$B$6,IF(2028=Premissas!$C$54+1,Premissas!$B$7,IF(2028=Premissas!$C$54+2,Premissas!$B$8,0))),0)) | H55: =G55*(1+Premissas!$B$5+IF(ISNUMBER(Premissas!$C$54),IF(2029=Premissas!$C$54,Premissas!$B$6,IF(2029=Premissas!$C$54+1,Premissas!$B$7,IF(2029=Premissas!$C$54+2,Premissas!$B$8,0))),0)) | I55: =H55*(1+Premissas!$B$5+IF(ISNUMBER(Premissas!$C$54),IF(2030=Premissas!$C$54,Premissas!$B$6,IF(2030=Premissas!$C$54+1,Premissas!$B$7,IF(2030=Premissas!$C$54+2,Premissas!$B$8,0))),0))
A56: TO | B56: Tocantins | C56: Varejo | D56: ='Base Histórica 2025'!C31 | E56: =D56*Premissas!$B$77 | F56: =E56*(1+Premissas!$B$4+IF(ISNUMBER(Premissas!$C$55),IF(2027=Premissas!$C$55,Premissas!$B$6,IF(2027=Premissas!$C$55+1,Premissas!$B$7,IF(2027=Premissas!$C$55+2,Premissas!$B$8,0))),0)) | G56: =F56*(1+Premissas!$B$4+IF(ISNUMBER(Premissas!$C$55),IF(2028=Premissas!$C$55,Premissas!$B$6,IF(2028=Premissas!$C$55+1,Premissas!$B$7,IF(2028=Premissas!$C$55+2,Premissas!$B$8,0))),0)) | H56: =G56*(1+Premissas!$B$4+IF(ISNUMBER(Premissas!$C$55),IF(2029=Premissas!$C$55,Premissas!$B$6,IF(2029=Premissas!$C$55+1,Premissas!$B$7,IF(2029=Premissas!$C$55+2,Premissas!$B$8,0))),0)) | I56: =H56*(1+Premissas!$B$4+IF(ISNUMBER(Premissas!$C$55),IF(2030=Premissas!$C$55,Premissas!$B$6,IF(2030=Premissas!$C$55+1,Premissas!$B$7,IF(2030=Premissas!$C$55+2,Premissas!$B$8,0))),0))
A57: TO | B57: Tocantins | C57: B2B | D57: ='Base Histórica 2025'!C62 | E57: =D57*Premissas!$B$77 | F57: =E57*(1+Premissas!$B$5+IF(ISNUMBER(Premissas!$C$55),IF(2027=Premissas!$C$55,Premissas!$B$6,IF(2027=Premissas!$C$55+1,Premissas!$B$7,IF(2027=Premissas!$C$55+2,Premissas!$B$8,0))),0)) | G57: =F57*(1+Premissas!$B$5+IF(ISNUMBER(Premissas!$C$55),IF(2028=Premissas!$C$55,Premissas!$B$6,IF(2028=Premissas!$C$55+1,Premissas!$B$7,IF(2028=Premissas!$C$55+2,Premissas!$B$8,0))),0)) | H57: =G57*(1+Premissas!$B$5+IF(ISNUMBER(Premissas!$C$55),IF(2029=Premissas!$C$55,Premissas!$B$6,IF(2029=Premissas!$C$55+1,Premissas!$B$7,IF(2029=Premissas!$C$55+2,Premissas!$B$8,0))),0)) | I57: =H57*(1+Premissas!$B$5+IF(ISNUMBER(Premissas!$C$55),IF(2030=Premissas!$C$55,Premissas!$B$6,IF(2030=Premissas!$C$55+1,Premissas!$B$7,IF(2030=Premissas!$C$55+2,Premissas!$B$8,0))),0))
A58: — | B58: — | C58: Online (site próprio + Mercado Livre + Amazon) | D58: 35000000 | E58: =D58*Premissas!$B$77 | F58: =E58*(1+Premissas!$B$9) | G58: =F58*(1+Premissas!$B$9) | H58: =G58*(1+Premissas!$B$9) | I58: =H58*(1+Premissas!$B$9)
C59: TOTAL VAREJO + B2B + ONLINE | D59: =SUM(D4:D58) | E59: =SUM(E4:E58) | F59: =SUM(F4:F58) | G59: =SUM(G4:G58) | H59: =SUM(H4:H58) | I59: =SUM(I4:I58)

Sheet Oportunidade GAP Mix
A1: OPORTUNIDADE DE RECEITA — GAP DE DISTRIBUIÇÃO (MIX)
A2: Simulação de receita incremental a partir do fechamento do GAP de SKUs distribuídos (mix atual x meta), por estado — fonte: mix_oportunidade_redes_prioritarias.xlsx, 18/ago/2026. Análise separada da linha de crescimento orgânico de Varejo já modelada em 'Projeção Receita' — para comparação lado a lado antes de decidir se e como incorporar à linha de Varejo do simulador.
A4: 1. Premissas desta análise
A5: Giro incremental por SKU novo (% do faturamento médio por SKU atual) | E5: 0.5
A6: Anos para fechar o GAP de distribuição (ramp linear a partir de 2026) | E6: 3
A8: Nota de escopo: SKUs atuais e GAP vêm do arquivo de redes prioritárias mapeadas — não cobre necessariamente 100% do faturamento Varejo do estado. Em estados onde essas redes são uma fatia pequena do total, o faturamento médio por SKU abaixo pode estar SUPERESTIMADO. Validar escopo antes de uso operacional.
A10: 2. Cálculo por Estado
A11: Estado | B11: Fat. Bruto Varejo 2025 (R$) | C11: SKUs Atuais (mix) | D11: GAP SKUs (piso 0) | E11: Fat. médio por SKU atual (R$) | F11: Giro incremental / SKU novo (R$) | G11: Receita incremental potencial (R$)
A12: SP | B12: ='Base Histórica 2025'!C5 | C12: 12269 | D12: 4277 | E12: =IF(C12=0,0,B12/C12) | F12: =E12*$E$5 | G12: =D12*F12
A13: RJ | B13: ='Base Histórica 2025'!C6 | C13: 774 | D13: 4281 | E13: =IF(C13=0,0,B13/C13) | F13: =E13*$E$5 | G13: =D13*F13
A14: SC | B14: ='Base Histórica 2025'!C7 | C14: 731 | D14: 2126 | E14: =IF(C14=0,0,B14/C14) | F14: =E14*$E$5 | G14: =D14*F14
A15: PR | B15: ='Base Histórica 2025'!C9 | C15: 1889 | D15: 2930 | E15: =IF(C15=0,0,B15/C15) | F15: =E15*$E$5 | G15: =D15*F15
A16: RS | B16: ='Base Histórica 2025'!C10 | C16: 126 | D16: 450 | E16: =IF(C16=0,0,B16/C16) | F16: =E16*$E$5 | G16: =D16*F16
A17: TOTAL | B17: =SUM(B12:B16) | C17: =SUM(C12:C16) | D17: =SUM(D12:D16) | G17: =SUM(G12:G16)
A19: 3. Ramp Anual — Receita Incremental (fechamento gradual do GAP)
A20: Cada estado fecha seu GAP linearmente ao longo do número de anos definido na premissa acima (início em 2026). Receita incremental do ano = Receita incremental potencial total × MIN(1, (ano-2025)/anos_fechar).
A21: Estado | B21: 2026 | C21: 2027 | D21: 2028 | E21: 2029 | F21: 2030
A22: SP | B22: =$G$12*MIN(1,(2026-2025)/$E$6) | C22: =$G$12*MIN(1,(2027-2025)/$E$6) | D22: =$G$12*MIN(1,(2028-2025)/$E$6) | E22: =$G$12*MIN(1,(2029-2025)/$E$6) | F22: =$G$12*MIN(1,(2030-2025)/$E$6)
A23: RJ | B23: =$G$13*MIN(1,(2026-2025)/$E$6) | C23: =$G$13*MIN(1,(2027-2025)/$E$6) | D23: =$G$13*MIN(1,(2028-2025)/$E$6) | E23: =$G$13*MIN(1,(2029-2025)/$E$6) | F23: =$G$13*MIN(1,(2030-2025)/$E$6)
A24: SC | B24: =$G$14*MIN(1,(2026-2025)/$E$6) | C24: =$G$14*MIN(1,(2027-2025)/$E$6) | D24: =$G$14*MIN(1,(2028-2025)/$E$6) | E24: =$G$14*MIN(1,(2029-2025)/$E$6) | F24: =$G$14*MIN(1,(2030-2025)/$E$6)
A25: PR | B25: =$G$15*MIN(1,(2026-2025)/$E$6) | C25: =$G$15*MIN(1,(2027-2025)/$E$6) | D25: =$G$15*MIN(1,(2028-2025)/$E$6) | E25: =$G$15*MIN(1,(2029-2025)/$E$6) | F25: =$G$15*MIN(1,(2030-2025)/$E$6)
A26: RS | B26: =$G$16*MIN(1,(2026-2025)/$E$6) | C26: =$G$16*MIN(1,(2027-2025)/$E$6) | D26: =$G$16*MIN(1,(2028-2025)/$E$6) | E26: =$G$16*MIN(1,(2029-2025)/$E$6) | F26: =$G$16*MIN(1,(2030-2025)/$E$6)
A27: TOTAL | B27: =SUM(B22:B26) | C27: =SUM(C22:C26) | D27: =SUM(D22:D26) | E27: =SUM(E22:E26) | F27: =SUM(F22:F26)
A29: 4. Comparação — Varejo Orgânico vs. Varejo + Oportunidade GAP Mix
A30: Para inclusão futura na linha de Varejo (se aprovado): soma do crescimento orgânico já modelado em 'Projeção Receita' com a receita incremental do fechamento de GAP (seção 3 acima).
B31: 2026 | C31: 2027 | D31: 2028 | E31: 2029 | F31: 2030
A32: Varejo orgânico (Projeção Receita, SP+RJ+SC+PR+RS) | B32: ='Projeção Receita'!E4+'Projeção Receita'!E6+'Projeção Receita'!E8+'Projeção Receita'!E12+'Projeção Receita'!E14 | C32: ='Projeção Receita'!F4+'Projeção Receita'!F6+'Projeção Receita'!F8+'Projeção Receita'!F12+'Projeção Receita'!F14 | D32: ='Projeção Receita'!G4+'Projeção Receita'!G6+'Projeção Receita'!G8+'Projeção Receita'!G12+'Projeção Receita'!G14 | E32: ='Projeção Receita'!H4+'Projeção Receita'!H6+'Projeção Receita'!H8+'Projeção Receita'!H12+'Projeção Receita'!H14 | F32: ='Projeção Receita'!I4+'Projeção Receita'!I6+'Projeção Receita'!I8+'Projeção Receita'!I12+'Projeção Receita'!I14
A33: + Oportunidade GAP Mix (ramp, seção 3) | B33: =B27 | C33: =C27 | D33: =D27 | E33: =E27 | F33: =F27
A34: Varejo Total (orgânico + GAP mix) | B34: =B32+B33 | C34: =C32+C33 | D34: =D32+D33 | E34: =E32+E33 | F34: =F32+F33
A35: Uplift % vs. Varejo orgânico | B35: =B33/B32 | C35: =C33/C32 | D35: =D33/D32 | E35: =E33/E32 | F35: =F33/F32
A37: Leitura
A38: • Este cálculo trata a oportunidade de GAP como incremental E ADICIONAL ao crescimento orgânico já modelado — não substitui as premissas de Premissas!B4 (25,5% a.a.), que já embutem alguma expansão de mix implícita. Antes de somar as duas linhas na Projeção Receita oficial, vale checar se não há dupla contagem.
A39: • O giro incremental de 50% é uma premissa de arranque conservadora — SKU novo tipicamente gira abaixo da média madura da loja. Ajustável na célula A5.
A40: • O ramp de 3 anos (padrão) é uma primeira hipótese de execução — pode ser encurtado se o time comercial priorizar ativação rápida das lojas 'Sem mix' (ver análise em slides, seção de recomendações).
A41: • Fat. médio por SKU está sujeito à limitação de escopo descrita acima (nota de seção 1) — mais confiável em termos relativos (comparação entre estados) do que em valor absoluto.

Sheet B2B por Estado e Cidade
A1: B2B — FATURAMENTO POR ESTADO E CIDADE (2025-2030)
A2: Base real: transações B2B 2025 por cidade (Simulador Orfeu.xlsx, aba Base_Unitaria). Cada cidade cresce na MESMA taxa do seu estado em 'Projeção Receita' (mix de cidade dentro do estado mantido constante de 2025 — premissa a validar com dado real de 2026+ quando disponível). Cidades com faturamento 2025 abaixo de R$30k ficam agrupadas em 'Outras cidades do estado'.
A4: UF | B4: Cidade | C4: 2025 | D4: 2026 | E4: 2027 | F4: 2028 | G4: 2029 | H4: 2030 | I4: Mult. 2030/2025
A5: SP | B5: TOTAL SP (B2B) | C5: ='Projeção Receita'!D5 | D5: ='Projeção Receita'!E5 | E5: ='Projeção Receita'!F5 | F5: ='Projeção Receita'!G5 | G5: ='Projeção Receita'!H5 | H5: ='Projeção Receita'!I5 | I5: =I5/C5
A6: SP | B6: Sao Paulo | C6: 7342395 | D6: =$C6*('Projeção Receita'!E5/'Projeção Receita'!$D$5) | E6: =$C6*('Projeção Receita'!F5/'Projeção Receita'!$D$5) | F6: =$C6*('Projeção Receita'!G5/'Projeção Receita'!$D$5) | G6: =$C6*('Projeção Receita'!H5/'Projeção Receita'!$D$5) | H6: =$C6*('Projeção Receita'!I5/'Projeção Receita'!$D$5) | I6: =I6/C6
A7: SP | B7: Jundiai | C7: 955415.82 | D7: =$C7*('Projeção Receita'!E5/'Projeção Receita'!$D$5) | E7: =$C7*('Projeção Receita'!F5/'Projeção Receita'!$D$5) | F7: =$C7*('Projeção Receita'!G5/'Projeção Receita'!$D$5) | G7: =$C7*('Projeção Receita'!H5/'Projeção Receita'!$D$5) | H7: =$C7*('Projeção Receita'!I5/'Projeção Receita'!$D$5) | I7: =I7/C7
A8: SP | B8: Catanduva | C8: 521371.76 | D8: =$C8*('Projeção Receita'!E5/'Projeção Receita'!$D$5) | E8: =$C8*('Projeção Receita'!F5/'Projeção Receita'!$D$5) | F8: =$C8*('Projeção Receita'!G5/'Projeção Receita'!$D$5) | G8: =$C8*('Projeção Receita'!H5/'Projeção Receita'!$D$5) | H8: =$C8*('Projeção Receita'!I5/'Projeção Receita'!$D$5) | I8: =I8/C8
A9: SP | B9: Barueri | C9: 512216.01 | D9: =$C9*('Projeção Receita'!E5/'Projeção Receita'!$D$5) | E9: =$C9*('Projeção Receita'!F5/'Projeção Receita'!$D$5) | F9: =$C9*('Projeção Receita'!G5/'Projeção Receita'!$D$5) | G9: =$C9*('Projeção Receita'!H5/'Projeção Receita'!$D$5) | H9: =$C9*('Projeção Receita'!I5/'Projeção Receita'!$D$5) | I9: =I9/C9
A10: SP | B10: Santa Barbara D Oeste | C10: 389755.44 | D10: =$C10*('Projeção Receita'!E5/'Projeção Receita'!$D$5) | E10: =$C10*('Projeção Receita'!F5/'Projeção Receita'!$D$5) | F10: =$C10*('Projeção Receita'!G5/'Projeção Receita'!$D$5) | G10: =$C10*('Projeção Receita'!H5/'Projeção Receita'!$D$5) | H10: =$C10*('Projeção Receita'!I5/'Projeção Receita'!$D$5) | I10: =I10/C10
A11: SP | B11: Sao Carlos | C11: 328493.52 | D11: =$C11*('Projeção Receita'!E5/'Projeção Receita'!$D$5) | E11: =$C11*('Projeção Receita'!F5/'Projeção Receita'!$D$5) | F11: =$C11*('Projeção Receita'!G5/'Projeção Receita'!$D$5) | G11: =$C11*('Projeção Receita'!H5/'Projeção Receita'!$D$5) | H11: =$C11*('Projeção Receita'!I5/'Projeção Receita'!$D$5) | I11: =I11/C11
A12: SP | B12: Guararema | C12: 320997.92 | D12: =$C12*('Projeção Receita'!E5/'Projeção Receita'!$D$5) | E12: =$C12*('Projeção Receita'!F5/'Projeção Receita'!$D$5) | F12: =$C12*('Projeção Receita'!G5/'Projeção Receita'!$D$5) | G12: =$C12*('Projeção Receita'!H5/'Projeção Receita'!$D$5) | H12: =$C12*('Projeção Receita'!I5/'Projeção Receita'!$D$5) | I12: =I12/C12
A13: SP | B13: Campinas | C13: 303816.18 | D13: =$C13*('Projeção Receita'!E5/'Projeção Receita'!$D$5) | E13: =$C13*('Projeção Receita'!F5/'Projeção Receita'!$D$5) | F13: =$C13*('Projeção Receita'!G5/'Projeção Receita'!$D$5) | G13: =$C13*('Projeção Receita'!H5/'Projeção Receita'!$D$5) | H13: =$C13*('Projeção Receita'!I5/'Projeção Receita'!$D$5) | I13: =I13/C13
A14: SP | B14: Santa Cruz Do Rio Pardo | C14: 299135.64 | D14: =$C14*('Projeção Receita'!E5/'Projeção Receita'!$D$5) | E14: =$C14*('Projeção Receita'!F5/'Projeção Receita'!$D$5) | F14: =$C14*('Projeção Receita'!G5/'Projeção Receita'!$D$5) | G14: =$C14*('Projeção Receita'!H5/'Projeção Receita'!$D$5) | H14: =$C14*('Projeção Receita'!I5/'Projeção Receita'!$D$5) | I14: =I14/C14
A15: SP | B15: Limeira | C15: 281583 | D15: =$C15*('Projeção Receita'!E5/'Projeção Receita'!$D$5) | E15: =$C15*('Projeção Receita'!F5/'Projeção Receita'!$D$5) | F15: =$C15*('Projeção Receita'!G5/'Projeção Receita'!$D$5) | G15: =$C15*('Projeção Receita'!H5/'Projeção Receita'!$D$5) | H15: =$C15*('Projeção Receita'!I5/'Projeção Receita'!$D$5) | I15: =I15/C15
A16: SP | B16: Queluz | C16: 269053.01 | D16: =$C16*('Projeção Receita'!E5/'Projeção Receita'!$D$5) | E16: =$C16*('Projeção Receita'!F5/'Projeção Receita'!$D$5) | F16: =$C16*('Projeção Receita'!G5/'Projeção Receita'!$D$5) | G16: =$C16*('Projeção Receita'!H5/'Projeção Receita'!$D$5) | H16: =$C16*('Projeção Receita'!I5/'Projeção Receita'!$D$5) | I16: =I16/C16
A17: SP | B17: Guaratingueta | C17: 233422.16 | D17: =$C17*('Projeção Receita'!E5/'Projeção Receita'!$D$5) | E17: =$C17*('Projeção Receita'!F5/'Projeção Receita'!$D$5) | F17: =$C17*('Projeção Receita'!G5/'Projeção Receita'!$D$5) | G17: =$C17*('Projeção Receita'!H5/'Projeção Receita'!$D$5) | H17: =$C17*('Projeção Receita'!I5/'Projeção Receita'!$D$5) | I17: =I17/C17
A18: SP | B18: Mairipora | C18: 188796.31 | D18: =$C18*('Projeção Receita'!E5/'Projeção Receita'!$D$5) | E18: =$C18*('Projeção Receita'!F5/'Projeção Receita'!$D$5) | F18: =$C18*('Projeção Receita'!G5/'Projeção Receita'!$D$5) | G18: =$C18*('Projeção Receita'!H5/'Projeção Receita'!$D$5) | H18: =$C18*('Projeção Receita'!I5/'Projeção Receita'!$D$5) | I18: =I18/C18
A19: SP | B19: Registro | C19: 183827.05 | D19: =$C19*('Projeção Receita'!E5/'Projeção Receita'!$D$5) | E19: =$C19*('Projeção Receita'!F5/'Projeção Receita'!$D$5) | F19: =$C19*('Projeção Receita'!G5/'Projeção Receita'!$D$5) | G19: =$C19*('Projeção Receita'!H5/'Projeção Receita'!$D$5) | H19: =$C19*('Projeção Receita'!I5/'Projeção Receita'!$D$5) | I19: =I19/C19
A20: SP | B20: Pindamonhangaba | C20: 176328.01 | D20: =$C20*('Projeção Receita'!E5/'Projeção Receita'!$D$5) | E20: =$C20*('Projeção Receita'!F5/'Projeção Receita'!$D$5) | F20: =$C20*('Projeção Receita'!G5/'Projeção Receita'!$D$5) | G20: =$C20*('Projeção Receita'!H5/'Projeção Receita'!$D$5) | H20: =$C20*('Projeção Receita'!I5/'Projeção Receita'!$D$5) | I20: =I20/C20
A21: SP | B21: Pariquera-Acu | C21: 176318.36 | D21: =$C21*('Projeção Receita'!E5/'Projeção Receita'!$D$5) | E21: =$C21*('Projeção Receita'!F5/'Projeção Receita'!$D$5) | F21: =$C21*('Projeção Receita'!G5/'Projeção Receita'!$D$5) | G21: =$C21*('Projeção Receita'!H5/'Projeção Receita'!$D$5) | H21: =$C21*('Projeção Receita'!I5/'Projeção Receita'!$D$5) | I21: =I21/C21
A22: SP | B22: Jandira | C22: 166213.13 | D22: =$C22*('Projeção Receita'!E5/'Projeção Receita'!$D$5) | E22: =$C22*('Projeção Receita'!F5/'Projeção Receita'!$D$5) | F22: =$C22*('Projeção Receita'!G5/'Projeção Receita'!$D$5) | G22: =$C22*('Projeção Receita'!H5/'Projeção Receita'!$D$5) | H22: =$C22*('Projeção Receita'!I5/'Projeção Receita'!$D$5) | I22: =I22/C22
A23: SP | B23: Ribeirao Preto | C23: 158227.72 | D23: =$C23*('Projeção Receita'!E5/'Projeção Receita'!$D$5) | E23: =$C23*('Projeção Receita'!F5/'Projeção Receita'!$D$5) | F23: =$C23*('Projeção Receita'!G5/'Projeção Receita'!$D$5) | G23: =$C23*('Projeção Receita'!H5/'Projeção Receita'!$D$5) | H23: =$C23*('Projeção Receita'!I5/'Projeção Receita'!$D$5) | I23: =I23/C23
A24: SP | B24: Pirassununga | C24: 154951.38 | D24: =$C24*('Projeção Receita'!E5/'Projeção Receita'!$D$5) | E24: =$C24*('Projeção Receita'!F5/'Projeção Receita'!$D$5) | F24: =$C24*('Projeção Receita'!G5/'Projeção Receita'!$D$5) | G24: =$C24*('Projeção Receita'!H5/'Projeção Receita'!$D$5) | H24: =$C24*('Projeção Receita'!I5/'Projeção Receita'!$D$5) | I24: =I24/C24
A25: SP | B25: Cordeiropolis | C25: 152347.68 | D25: =$C25*('Projeção Receita'!E5/'Projeção Receita'!$D$5) | E25: =$C25*('Projeção Receita'!F5/'Projeção Receita'!$D$5) | F25: =$C25*('Projeção Receita'!G5/'Projeção Receita'!$D$5) | G25: =$C25*('Projeção Receita'!H5/'Projeção Receita'!$D$5) | H25: =$C25*('Projeção Receita'!I5/'Projeção Receita'!$D$5) | I25: =I25/C25
A26: SP | B26: Pardinho | C26: 146586.38 | D26: =$C26*('Projeção Receita'!E5/'Projeção Receita'!$D$5) | E26: =$C26*('Projeção Receita'!F5/'Projeção Receita'!$D$5) | F26: =$C26*('Projeção Receita'!G5/'Projeção Receita'!$D$5) | G26: =$C26*('Projeção Receita'!H5/'Projeção Receita'!$D$5) | H26: =$C26*('Projeção Receita'!I5/'Projeção Receita'!$D$5) | I26: =I26/C26
A27: SP | B27: Guarulhos | C27: 140336.53 | D27: =$C27*('Projeção Receita'!E5/'Projeção Receita'!$D$5) | E27: =$C27*('Projeção Receita'!F5/'Projeção Receita'!$D$5) | F27: =$C27*('Projeção Receita'!G5/'Projeção Receita'!$D$5) | G27: =$C27*('Projeção Receita'!H5/'Projeção Receita'!$D$5) | H27: =$C27*('Projeção Receita'!I5/'Projeção Receita'!$D$5) | I27: =I27/C27
A28: SP | B28: Miracatu | C28: 131830.06 | D28: =$C28*('Projeção Receita'!E5/'Projeção Receita'!$D$5) | E28: =$C28*('Projeção Receita'!F5/'Projeção Receita'!$D$5) | F28: =$C28*('Projeção Receita'!G5/'Projeção Receita'!$D$5) | G28: =$C28*('Projeção Receita'!H5/'Projeção Receita'!$D$5) | H28: =$C28*('Projeção Receita'!I5/'Projeção Receita'!$D$5) | I28: =I28/C28
A29: SP | B29: Jarinu | C29: 130292.6 | D29: =$C29*('Projeção Receita'!E5/'Projeção Receita'!$D$5) | E29: =$C29*('Projeção Receita'!F5/'Projeção Receita'!$D$5) | F29: =$C29*('Projeção Receita'!G5/'Projeção Receita'!$D$5) | G29: =$C29*('Projeção Receita'!H5/'Projeção Receita'!$D$5) | H29: =$C29*('Projeção Receita'!I5/'Projeção Receita'!$D$5) | I29: =I29/C29
A30: SP | B30: Aracariguama | C30: 113363.56 | D30: =$C30*('Projeção Receita'!E5/'Projeção Receita'!$D$5) | E30: =$C30*('Projeção Receita'!F5/'Projeção Receita'!$D$5) | F30: =$C30*('Projeção Receita'!G5/'Projeção Receita'!$D$5) | G30: =$C30*('Projeção Receita'!H5/'Projeção Receita'!$D$5) | H30: =$C30*('Projeção Receita'!I5/'Projeção Receita'!$D$5) | I30: =I30/C30
A31: SP | B31: Bauru | C31: 96658.13 | D31: =$C31*('Projeção Receita'!E5/'Projeção Receita'!$D$5) | E31: =$C31*('Projeção Receita'!F5/'Projeção Receita'!$D$5) | F31: =$C31*('Projeção Receita'!G5/'Projeção Receita'!$D$5) | G31: =$C31*('Projeção Receita'!H5/'Projeção Receita'!$D$5) | H31: =$C31*('Projeção Receita'!I5/'Projeção Receita'!$D$5) | I31: =I31/C31
A32: SP | B32: Itatiba | C32: 87081.6 | D32: =$C32*('Projeção Receita'!E5/'Projeção Receita'!$D$5) | E32: =$C32*('Projeção Receita'!F5/'Projeção Receita'!$D$5) | F32: =$C32*('Projeção Receita'!G5/'Projeção Receita'!$D$5) | G32: =$C32*('Projeção Receita'!H5/'Projeção Receita'!$D$5) | H32: =$C32*('Projeção Receita'!I5/'Projeção Receita'!$D$5) | I32: =I32/C32
A33: SP | B33: Itupeva | C33: 86643.7 | D33: =$C33*('Projeção Receita'!E5/'Projeção Receita'!$D$5) | E33: =$C33*('Projeção Receita'!F5/'Projeção Receita'!$D$5) | F33: =$C33*('Projeção Receita'!G5/'Projeção Receita'!$D$5) | G33: =$C33*('Projeção Receita'!H5/'Projeção Receita'!$D$5) | H33: =$C33*('Projeção Receita'!I5/'Projeção Receita'!$D$5) | I33: =I33/C33
A34: SP | B34: Santo Andre | C34: 83026.06 | D34: =$C34*('Projeção Receita'!E5/'Projeção Receita'!$D$5) | E34: =$C34*('Projeção Receita'!F5/'Projeção Receita'!$D$5) | F34: =$C34*('Projeção Receita'!G5/'Projeção Receita'!$D$5) | G34: =$C34*('Projeção Receita'!H5/'Projeção Receita'!$D$5) | H34: =$C34*('Projeção Receita'!I5/'Projeção Receita'!$D$5) | I34: =I34/C34
A35: SP | B35: Iaras | C35: 64796.89 | D35: =$C35*('Projeção Receita'!E5/'Projeção Receita'!$D$5) | E35: =$C35*('Projeção Receita'!F5/'Projeção Receita'!$D$5) | F35: =$C35*('Projeção Receita'!G5/'Projeção Receita'!$D$5) | G35: =$C35*('Projeção Receita'!H5/'Projeção Receita'!$D$5) | H35: =$C35*('Projeção Receita'!I5/'Projeção Receita'!$D$5) | I35: =I35/C35
A36: SP | B36: Guaruja | C36: 55019.8 | D36: =$C36*('Projeção Receita'!E5/'Projeção Receita'!$D$5) | E36: =$C36*('Projeção Receita'!F5/'Projeção Receita'!$D$5) | F36: =$C36*('Projeção Receita'!G5/'Projeção Receita'!$D$5) | G36: =$C36*('Projeção Receita'!H5/'Projeção Receita'!$D$5) | H36: =$C36*('Projeção Receita'!I5/'Projeção Receita'!$D$5) | I36: =I36/C36
A37: SP | B37: Osasco | C37: 54495.86 | D37: =$C37*('Projeção Receita'!E5/'Projeção Receita'!$D$5) | E37: =$C37*('Projeção Receita'!F5/'Projeção Receita'!$D$5) | F37: =$C37*('Projeção Receita'!G5/'Projeção Receita'!$D$5) | G37: =$C37*('Projeção Receita'!H5/'Projeção Receita'!$D$5) | H37: =$C37*('Projeção Receita'!I5/'Projeção Receita'!$D$5) | I37: =I37/C37
A38: SP | B38: Ilhabela | C38: 46931.9 | D38: =$C38*('Projeção Receita'!E5/'Projeção Receita'!$D$5) | E38: =$C38*('Projeção Receita'!F5/'Projeção Receita'!$D$5) | F38: =$C38*('Projeção Receita'!G5/'Projeção Receita'!$D$5) | G38: =$C38*('Projeção Receita'!H5/'Projeção Receita'!$D$5) | H38: =$C38*('Projeção Receita'!I5/'Projeção Receita'!$D$5) | I38: =I38/C38
A39: SP | B39: Cotia | C39: 45658.32 | D39: =$C39*('Projeção Receita'!E5/'Projeção Receita'!$D$5) | E39: =$C39*('Projeção Receita'!F5/'Projeção Receita'!$D$5) | F39: =$C39*('Projeção Receita'!G5/'Projeção Receita'!$D$5) | G39: =$C39*('Projeção Receita'!H5/'Projeção Receita'!$D$5) | H39: =$C39*('Projeção Receita'!I5/'Projeção Receita'!$D$5) | I39: =I39/C39
A40: SP | B40: Ourinhos | C40: 44680.2 | D40: =$C40*('Projeção Receita'!E5/'Projeção Receita'!$D$5) | E40: =$C40*('Projeção Receita'!F5/'Projeção Receita'!$D$5) | F40: =$C40*('Projeção Receita'!G5/'Projeção Receita'!$D$5) | G40: =$C40*('Projeção Receita'!H5/'Projeção Receita'!$D$5) | H40: =$C40*('Projeção Receita'!I5/'Projeção Receita'!$D$5) | I40: =I40/C40
A41: SP | B41: Braganca Paulista | C41: 40841.12 | D41: =$C41*('Projeção Receita'!E5/'Projeção Receita'!$D$5) | E41: =$C41*('Projeção Receita'!F5/'Projeção Receita'!$D$5) | F41: =$C41*('Projeção Receita'!G5/'Projeção Receita'!$D$5) | G41: =$C41*('Projeção Receita'!H5/'Projeção Receita'!$D$5) | H41: =$C41*('Projeção Receita'!I5/'Projeção Receita'!$D$5) | I41: =I41/C41
A42: SP | B42: Aparecida | C42: 38814 | D42: =$C42*('Projeção Receita'!E5/'Projeção Receita'!$D$5) | E42: =$C42*('Projeção Receita'!F5/'Projeção Receita'!$D$5) | F42: =$C42*('Projeção Receita'!G5/'Projeção Receita'!$D$5) | G42: =$C42*('Projeção Receita'!H5/'Projeção Receita'!$D$5) | H42: =$C42*('Projeção Receita'!I5/'Projeção Receita'!$D$5) | I42: =I42/C42
A43: SP | B43: Paranapanema | C43: 31800.02 | D43: =$C43*('Projeção Receita'!E5/'Projeção Receita'!$D$5) | E43: =$C43*('Projeção Receita'!F5/'Projeção Receita'!$D$5) | F43: =$C43*('Projeção Receita'!G5/'Projeção Receita'!$D$5) | G43: =$C43*('Projeção Receita'!H5/'Projeção Receita'!$D$5) | H43: =$C43*('Projeção Receita'!I5/'Projeção Receita'!$D$5) | I43: =I43/C43
A44: SP | B44: Santana De Parnaiba | C44: 30699.9 | D44: =$C44*('Projeção Receita'!E5/'Projeção Receita'!$D$5) | E44: =$C44*('Projeção Receita'!F5/'Projeção Receita'!$D$5) | F44: =$C44*('Projeção Receita'!G5/'Projeção Receita'!$D$5) | G44: =$C44*('Projeção Receita'!H5/'Projeção Receita'!$D$5) | H44: =$C44*('Projeção Receita'!I5/'Projeção Receita'!$D$5) | I44: =I44/C44
A45: SP | B45: Outras cidades do estado (residual) | C45: =C5-SUM(C6:C44) | D45: =D5-SUM(D6:D44) | E45: =E5-SUM(E6:E44) | F45: =F5-SUM(F6:F44) | G45: =G5-SUM(G6:G44) | H45: =H5-SUM(H6:H44)
A47: RJ | B47: TOTAL RJ (B2B) | C47: ='Projeção Receita'!D7 | D47: ='Projeção Receita'!E7 | E47: ='Projeção Receita'!F7 | F47: ='Projeção Receita'!G7 | G47: ='Projeção Receita'!H7 | H47: ='Projeção Receita'!I7 | I47: =I47/C47
A48: RJ | B48: Rio De Janeiro | C48: 3201930 | D48: =$C48*('Projeção Receita'!E7/'Projeção Receita'!$D$7) | E48: =$C48*('Projeção Receita'!F7/'Projeção Receita'!$D$7) | F48: =$C48*('Projeção Receita'!G7/'Projeção Receita'!$D$7) | G48: =$C48*('Projeção Receita'!H7/'Projeção Receita'!$D$7) | H48: =$C48*('Projeção Receita'!I7/'Projeção Receita'!$D$7) | I48: =I48/C48
A49: RJ | B49: Resende | C49: 231562.22 | D49: =$C49*('Projeção Receita'!E7/'Projeção Receita'!$D$7) | E49: =$C49*('Projeção Receita'!F7/'Projeção Receita'!$D$7) | F49: =$C49*('Projeção Receita'!G7/'Projeção Receita'!$D$7) | G49: =$C49*('Projeção Receita'!H7/'Projeção Receita'!$D$7) | H49: =$C49*('Projeção Receita'!I7/'Projeção Receita'!$D$7) | I49: =I49/C49
A50: RJ | B50: Niteroi | C50: 200941.67 | D50: =$C50*('Projeção Receita'!E7/'Projeção Receita'!$D$7) | E50: =$C50*('Projeção Receita'!F7/'Projeção Receita'!$D$7) | F50: =$C50*('Projeção Receita'!G7/'Projeção Receita'!$D$7) | G50: =$C50*('Projeção Receita'!H7/'Projeção Receita'!$D$7) | H50: =$C50*('Projeção Receita'!I7/'Projeção Receita'!$D$7) | I50: =I50/C50
A51: RJ | B51: Itatiaia | C51: 166658.64 | D51: =$C51*('Projeção Receita'!E7/'Projeção Receita'!$D$7) | E51: =$C51*('Projeção Receita'!F7/'Projeção Receita'!$D$7) | F51: =$C51*('Projeção Receita'!G7/'Projeção Receita'!$D$7) | G51: =$C51*('Projeção Receita'!H7/'Projeção Receita'!$D$7) | H51: =$C51*('Projeção Receita'!I7/'Projeção Receita'!$D$7) | I51: =I51/C51
A52: RJ | B52: Rio Bonito | C52: 141086.34 | D52: =$C52*('Projeção Receita'!E7/'Projeção Receita'!$D$7) | E52: =$C52*('Projeção Receita'!F7/'Projeção Receita'!$D$7) | F52: =$C52*('Projeção Receita'!G7/'Projeção Receita'!$D$7) | G52: =$C52*('Projeção Receita'!H7/'Projeção Receita'!$D$7) | H52: =$C52*('Projeção Receita'!I7/'Projeção Receita'!$D$7) | I52: =I52/C52
A53: RJ | B53: Nova Iguacu | C53: 96736.57 | D53: =$C53*('Projeção Receita'!E7/'Projeção Receita'!$D$7) | E53: =$C53*('Projeção Receita'!F7/'Projeção Receita'!$D$7) | F53: =$C53*('Projeção Receita'!G7/'Projeção Receita'!$D$7) | G53: =$C53*('Projeção Receita'!H7/'Projeção Receita'!$D$7) | H53: =$C53*('Projeção Receita'!I7/'Projeção Receita'!$D$7) | I53: =I53/C53
A54: RJ | B54: Paraty | C54: 88561.54 | D54: =$C54*('Projeção Receita'!E7/'Projeção Receita'!$D$7) | E54: =$C54*('Projeção Receita'!F7/'Projeção Receita'!$D$7) | F54: =$C54*('Projeção Receita'!G7/'Projeção Receita'!$D$7) | G54: =$C54*('Projeção Receita'!H7/'Projeção Receita'!$D$7) | H54: =$C54*('Projeção Receita'!I7/'Projeção Receita'!$D$7) | I54: =I54/C54
A55: RJ | B55: Campos Dos Goytacazes | C55: 73796.64 | D55: =$C55*('Projeção Receita'!E7/'Projeção Receita'!$D$7) | E55: =$C55*('Projeção Receita'!F7/'Projeção Receita'!$D$7) | F55: =$C55*('Projeção Receita'!G7/'Projeção Receita'!$D$7) | G55: =$C55*('Projeção Receita'!H7/'Projeção Receita'!$D$7) | H55: =$C55*('Projeção Receita'!I7/'Projeção Receita'!$D$7) | I55: =I55/C55
A56: RJ | B56: Barra Do Pirai | C56: 40006.1 | D56: =$C56*('Projeção Receita'!E7/'Projeção Receita'!$D$7) | E56: =$C56*('Projeção Receita'!F7/'Projeção Receita'!$D$7) | F56: =$C56*('Projeção Receita'!G7/'Projeção Receita'!$D$7) | G56: =$C56*('Projeção Receita'!H7/'Projeção Receita'!$D$7) | H56: =$C56*('Projeção Receita'!I7/'Projeção Receita'!$D$7) | I56: =I56/C56
A57: RJ | B57: Outras cidades do estado (residual) | C57: =C47-SUM(C48:C56) | D57: =D47-SUM(D48:D56) | E57: =E47-SUM(E48:E56) | F57: =F47-SUM(F48:F56) | G57: =G47-SUM(G48:G56) | H57: =H47-SUM(H48:H56)
A59: MG | B59: TOTAL MG (B2B) | C59: ='Projeção Receita'!D17 | D59: ='Projeção Receita'!E17 | E59: ='Projeção Receita'!F17 | F59: ='Projeção Receita'!G17 | G59: ='Projeção Receita'!H17 | H59: ='Projeção Receita'!I17 | I59: =I59/C59
A60: MG | B60: Pocos De Caldas | C60: 635771.19 | D60: =$C60*('Projeção Receita'!E17/'Projeção Receita'!$D$17) | E60: =$C60*('Projeção Receita'!F17/'Projeção Receita'!$D$17) | F60: =$C60*('Projeção Receita'!G17/'Projeção Receita'!$D$17) | G60: =$C60*('Projeção Receita'!H17/'Projeção Receita'!$D$17) | H60: =$C60*('Projeção Receita'!I17/'Projeção Receita'!$D$17) | I60: =I60/C60
A61: MG | B61: Belo Horizonte | C61: 128351.91 | D61: =$C61*('Projeção Receita'!E17/'Projeção Receita'!$D$17) | E61: =$C61*('Projeção Receita'!F17/'Projeção Receita'!$D$17) | F61: =$C61*('Projeção Receita'!G17/'Projeção Receita'!$D$17) | G61: =$C61*('Projeção Receita'!H17/'Projeção Receita'!$D$17) | H61: =$C61*('Projeção Receita'!I17/'Projeção Receita'!$D$17) | I61: =I61/C61
A62: MG | B62: Juiz De Fora | C62: 115683.52 | D62: =$C62*('Projeção Receita'!E17/'Projeção Receita'!$D$17) | E62: =$C62*('Projeção Receita'!F17/'Projeção Receita'!$D$17) | F62: =$C62*('Projeção Receita'!G17/'Projeção Receita'!$D$17) | G62: =$C62*('Projeção Receita'!H17/'Projeção Receita'!$D$17) | H62: =$C62*('Projeção Receita'!I17/'Projeção Receita'!$D$17) | I62: =I62/C62
A63: MG | B63: Uberaba | C63: 100228.6 | D63: =$C63*('Projeção Receita'!E17/'Projeção Receita'!$D$17) | E63: =$C63*('Projeção Receita'!F17/'Projeção Receita'!$D$17) | F63: =$C63*('Projeção Receita'!G17/'Projeção Receita'!$D$17) | G63: =$C63*('Projeção Receita'!H17/'Projeção Receita'!$D$17) | H63: =$C63*('Projeção Receita'!I17/'Projeção Receita'!$D$17) | I63: =I63/C63
A64: MG | B64: Estiva | C64: 72592.2 | D64: =$C64*('Projeção Receita'!E17/'Projeção Receita'!$D$17) | E64: =$C64*('Projeção Receita'!F17/'Projeção Receita'!$D$17) | F64: =$C64*('Projeção Receita'!G17/'Projeção Receita'!$D$17) | G64: =$C64*('Projeção Receita'!H17/'Projeção Receita'!$D$17) | H64: =$C64*('Projeção Receita'!I17/'Projeção Receita'!$D$17) | I64: =I64/C64
A65: MG | B65: Ribeirao Vermelho | C65: 56428.24 | D65: =$C65*('Projeção Receita'!E17/'Projeção Receita'!$D$17) | E65: =$C65*('Projeção Receita'!F17/'Projeção Receita'!$D$17) | F65: =$C65*('Projeção Receita'!G17/'Projeção Receita'!$D$17) | G65: =$C65*('Projeção Receita'!H17/'Projeção Receita'!$D$17) | H65: =$C65*('Projeção Receita'!I17/'Projeção Receita'!$D$17) | I65: =I65/C65
A66: MG | B66: Botelhos | C66: 49382.29 | D66: =$C66*('Projeção Receita'!E17/'Projeção Receita'!$D$17) | E66: =$C66*('Projeção Receita'!F17/'Projeção Receita'!$D$17) | F66: =$C66*('Projeção Receita'!G17/'Projeção Receita'!$D$17) | G66: =$C66*('Projeção Receita'!H17/'Projeção Receita'!$D$17) | H66: =$C66*('Projeção Receita'!I17/'Projeção Receita'!$D$17) | I66: =I66/C66
A67: MG | B67: Sao Sebastiao Da Bela Vista | C67: 44695 | D67: =$C67*('Projeção Receita'!E17/'Projeção Receita'!$D$17) | E67: =$C67*('Projeção Receita'!F17/'Projeção Receita'!$D$17) | F67: =$C67*('Projeção Receita'!G17/'Projeção Receita'!$D$17) | G67: =$C67*('Projeção Receita'!H17/'Projeção Receita'!$D$17) | H67: =$C67*('Projeção Receita'!I17/'Projeção Receita'!$D$17) | I67: =I67/C67
A68: MG | B68: Uberlandia | C68: 37635.75 | D68: =$C68*('Projeção Receita'!E17/'Projeção Receita'!$D$17) | E68: =$C68*('Projeção Receita'!F17/'Projeção Receita'!$D$17) | F68: =$C68*('Projeção Receita'!G17/'Projeção Receita'!$D$17) | G68: =$C68*('Projeção Receita'!H17/'Projeção Receita'!$D$17) | H68: =$C68*('Projeção Receita'!I17/'Projeção Receita'!$D$17) | I68: =I68/C68
A69: MG | B69: Oliveira | C69: 37324.5 | D69: =$C69*('Projeção Receita'!E17/'Projeção Receita'!$D$17) | E69: =$C69*('Projeção Receita'!F17/'Projeção Receita'!$D$17) | F69: =$C69*('Projeção Receita'!G17/'Projeção Receita'!$D$17) | G69: =$C69*('Projeção Receita'!H17/'Projeção Receita'!$D$17) | H69: =$C69*('Projeção Receita'!I17/'Projeção Receita'!$D$17) | I69: =I69/C69
A70: MG | B70: Confins | C70: 31474.4 | D70: =$C70*('Projeção Receita'!E17/'Projeção Receita'!$D$17) | E70: =$C70*('Projeção Receita'!F17/'Projeção Receita'!$D$17) | F70: =$C70*('Projeção Receita'!G17/'Projeção Receita'!$D$17) | G70: =$C70*('Projeção Receita'!H17/'Projeção Receita'!$D$17) | H70: =$C70*('Projeção Receita'!I17/'Projeção Receita'!$D$17) | I70: =I70/C70
A71: MG | B71: Outras cidades do estado (residual) | C71: =C59-SUM(C60:C70) | D71: =D59-SUM(D60:D70) | E71: =E59-SUM(E60:E70) | F71: =F59-SUM(F60:F70) | G71: =G59-SUM(G60:G70) | H71: =H59-SUM(H60:H70)
A73: SC | B73: TOTAL SC (B2B) | C73: ='Projeção Receita'!D9 | D73: ='Projeção Receita'!E9 | E73: ='Projeção Receita'!F9 | F73: ='Projeção Receita'!G9 | G73: ='Projeção Receita'!H9 | H73: ='Projeção Receita'!I9 | I73: =I73/C73
A74: SC | B74: Balneario Picarras | C74: 203891.5 | D74: =$C74*('Projeção Receita'!E9/'Projeção Receita'!$D$9) | E74: =$C74*('Projeção Receita'!F9/'Projeção Receita'!$D$9) | F74: =$C74*('Projeção Receita'!G9/'Projeção Receita'!$D$9) | G74: =$C74*('Projeção Receita'!H9/'Projeção Receita'!$D$9) | H74: =$C74*('Projeção Receita'!I9/'Projeção Receita'!$D$9) | I74: =I74/C74
A75: SC | B75: Cacador | C75: 91789.2 | D75: =$C75*('Projeção Receita'!E9/'Projeção Receita'!$D$9) | E75: =$C75*('Projeção Receita'!F9/'Projeção Receita'!$D$9) | F75: =$C75*('Projeção Receita'!G9/'Projeção Receita'!$D$9) | G75: =$C75*('Projeção Receita'!H9/'Projeção Receita'!$D$9) | H75: =$C75*('Projeção Receita'!I9/'Projeção Receita'!$D$9) | I75: =I75/C75
A76: SC | B76: Florianopolis | C76: 87996.61 | D76: =$C76*('Projeção Receita'!E9/'Projeção Receita'!$D$9) | E76: =$C76*('Projeção Receita'!F9/'Projeção Receita'!$D$9) | F76: =$C76*('Projeção Receita'!G9/'Projeção Receita'!$D$9) | G76: =$C76*('Projeção Receita'!H9/'Projeção Receita'!$D$9) | H76: =$C76*('Projeção Receita'!I9/'Projeção Receita'!$D$9) | I76: =I76/C76
A77: SC | B77: Imbituba | C77: 84773.01 | D77: =$C77*('Projeção Receita'!E9/'Projeção Receita'!$D$9) | E77: =$C77*('Projeção Receita'!F9/'Projeção Receita'!$D$9) | F77: =$C77*('Projeção Receita'!G9/'Projeção Receita'!$D$9) | G77: =$C77*('Projeção Receita'!H9/'Projeção Receita'!$D$9) | H77: =$C77*('Projeção Receita'!I9/'Projeção Receita'!$D$9) | I77: =I77/C77
A78: SC | B78: Itajai | C78: 41598.79 | D78: =$C78*('Projeção Receita'!E9/'Projeção Receita'!$D$9) | E78: =$C78*('Projeção Receita'!F9/'Projeção Receita'!$D$9) | F78: =$C78*('Projeção Receita'!G9/'Projeção Receita'!$D$9) | G78: =$C78*('Projeção Receita'!H9/'Projeção Receita'!$D$9) | H78: =$C78*('Projeção Receita'!I9/'Projeção Receita'!$D$9) | I78: =I78/C78
A79: SC | B79: Joinville | C79: 33601.71 | D79: =$C79*('Projeção Receita'!E9/'Projeção Receita'!$D$9) | E79: =$C79*('Projeção Receita'!F9/'Projeção Receita'!$D$9) | F79: =$C79*('Projeção Receita'!G9/'Projeção Receita'!$D$9) | G79: =$C79*('Projeção Receita'!H9/'Projeção Receita'!$D$9) | H79: =$C79*('Projeção Receita'!I9/'Projeção Receita'!$D$9) | I79: =I79/C79
A80: SC | B80: Outras cidades do estado (residual) | C80: =C73-SUM(C74:C79) | D80: =D73-SUM(D74:D79) | E80: =E73-SUM(E74:E79) | F80: =F73-SUM(F74:F79) | G80: =G73-SUM(G74:G79) | H80: =H73-SUM(H74:H79)
A82: PR | B82: TOTAL PR (B2B) | C82: ='Projeção Receita'!D13 | D82: ='Projeção Receita'!E13 | E82: ='Projeção Receita'!F13 | F82: ='Projeção Receita'!G13 | G82: ='Projeção Receita'!H13 | H82: ='Projeção Receita'!I13 | I82: =I82/C82
A83: PR | B83: Curitiba | C83: 558271.75 | D83: =$C83*('Projeção Receita'!E13/'Projeção Receita'!$D$13) | E83: =$C83*('Projeção Receita'!F13/'Projeção Receita'!$D$13) | F83: =$C83*('Projeção Receita'!G13/'Projeção Receita'!$D$13) | G83: =$C83*('Projeção Receita'!H13/'Projeção Receita'!$D$13) | H83: =$C83*('Projeção Receita'!I13/'Projeção Receita'!$D$13) | I83: =I83/C83
A84: PR | B84: Toledo | C84: 49304.97 | D84: =$C84*('Projeção Receita'!E13/'Projeção Receita'!$D$13) | E84: =$C84*('Projeção Receita'!F13/'Projeção Receita'!$D$13) | F84: =$C84*('Projeção Receita'!G13/'Projeção Receita'!$D$13) | G84: =$C84*('Projeção Receita'!H13/'Projeção Receita'!$D$13) | H84: =$C84*('Projeção Receita'!I13/'Projeção Receita'!$D$13) | I84: =I84/C84
A85: PR | B85: Londrina | C85: 47164.34 | D85: =$C85*('Projeção Receita'!E13/'Projeção Receita'!$D$13) | E85: =$C85*('Projeção Receita'!F13/'Projeção Receita'!$D$13) | F85: =$C85*('Projeção Receita'!G13/'Projeção Receita'!$D$13) | G85: =$C85*('Projeção Receita'!H13/'Projeção Receita'!$D$13) | H85: =$C85*('Projeção Receita'!I13/'Projeção Receita'!$D$13) | I85: =I85/C85
A86: PR | B86: Maringa | C86: 31176 | D86: =$C86*('Projeção Receita'!E13/'Projeção Receita'!$D$13) | E86: =$C86*('Projeção Receita'!F13/'Projeção Receita'!$D$13) | F86: =$C86*('Projeção Receita'!G13/'Projeção Receita'!$D$13) | G86: =$C86*('Projeção Receita'!H13/'Projeção Receita'!$D$13) | H86: =$C86*('Projeção Receita'!I13/'Projeção Receita'!$D$13) | I86: =I86/C86
A87: PR | B87: Outras cidades do estado (residual) | C87: =C82-SUM(C83:C86) | D87: =D82-SUM(D83:D86) | E87: =E82-SUM(E83:E86) | F87: =F82-SUM(F83:F86) | G87: =G82-SUM(G83:G86) | H87: =H82-SUM(H83:H86)
A89: GO | B89: TOTAL GO (B2B) | C89: ='Projeção Receita'!D39 | D89: ='Projeção Receita'!E39 | E89: ='Projeção Receita'!F39 | F89: ='Projeção Receita'!G39 | G89: ='Projeção Receita'!H39 | H89: ='Projeção Receita'!I39 | I89: =I89/C89
A90: GO | B90: Abadiania | C90: 537624.6 | D90: =$C90*('Projeção Receita'!E39/'Projeção Receita'!$D$39) | E90: =$C90*('Projeção Receita'!F39/'Projeção Receita'!$D$39) | F90: =$C90*('Projeção Receita'!G39/'Projeção Receita'!$D$39) | G90: =$C90*('Projeção Receita'!H39/'Projeção Receita'!$D$39) | H90: =$C90*('Projeção Receita'!I39/'Projeção Receita'!$D$39) | I90: =I90/C90
A91: GO | B91: Goiania | C91: 327013.29 | D91: =$C91*('Projeção Receita'!E39/'Projeção Receita'!$D$39) | E91: =$C91*('Projeção Receita'!F39/'Projeção Receita'!$D$39) | F91: =$C91*('Projeção Receita'!G39/'Projeção Receita'!$D$39) | G91: =$C91*('Projeção Receita'!H39/'Projeção Receita'!$D$39) | H91: =$C91*('Projeção Receita'!I39/'Projeção Receita'!$D$39) | I91: =I91/C91
A92: GO | B92: Outras cidades do estado (residual) | C92: =C89-SUM(C90:C91) | D92: =D89-SUM(D90:D91) | E92: =E89-SUM(E90:E91) | F92: =F89-SUM(F90:F91) | G92: =G89-SUM(G90:G91) | H92: =H89-SUM(H90:H91)
A94: RS | B94: TOTAL RS (B2B) | C94: ='Projeção Receita'!D15 | D94: ='Projeção Receita'!E15 | E94: ='Projeção Receita'!F15 | F94: ='Projeção Receita'!G15 | G94: ='Projeção Receita'!H15 | H94: ='Projeção Receita'!I15 | I94: =I94/C94
A95: RS | B95: Gravatai | C95: 99231.66 | D95: =$C95*('Projeção Receita'!E15/'Projeção Receita'!$D$15) | E95: =$C95*('Projeção Receita'!F15/'Projeção Receita'!$D$15) | F95: =$C95*('Projeção Receita'!G15/'Projeção Receita'!$D$15) | G95: =$C95*('Projeção Receita'!H15/'Projeção Receita'!$D$15) | H95: =$C95*('Projeção Receita'!I15/'Projeção Receita'!$D$15) | I95: =I95/C95
A96: RS | B96: Bento Goncalves | C96: 62839.98 | D96: =$C96*('Projeção Receita'!E15/'Projeção Receita'!$D$15) | E96: =$C96*('Projeção Receita'!F15/'Projeção Receita'!$D$15) | F96: =$C96*('Projeção Receita'!G15/'Projeção Receita'!$D$15) | G96: =$C96*('Projeção Receita'!H15/'Projeção Receita'!$D$15) | H96: =$C96*('Projeção Receita'!I15/'Projeção Receita'!$D$15) | I96: =I96/C96
A97: RS | B97: Outras cidades do estado (residual) | C97: =C94-SUM(C95:C96) | D97: =D94-SUM(D95:D96) | E97: =E94-SUM(E95:E96) | F97: =F94-SUM(F95:F96) | G97: =G94-SUM(G95:G96) | H97: =H94-SUM(H95:H96)
A99: PE | B99: TOTAL PE (B2B) | C99: ='Projeção Receita'!D25 | D99: ='Projeção Receita'!E25 | E99: ='Projeção Receita'!F25 | F99: ='Projeção Receita'!G25 | G99: ='Projeção Receita'!H25 | H99: ='Projeção Receita'!I25 | I99: =I99/C99
A100: PE | B100: Ipojuca | C100: 257954.23 | D100: =$C100*('Projeção Receita'!E25/'Projeção Receita'!$D$25) | E100: =$C100*('Projeção Receita'!F25/'Projeção Receita'!$D$25) | F100: =$C100*('Projeção Receita'!G25/'Projeção Receita'!$D$25) | G100: =$C100*('Projeção Receita'!H25/'Projeção Receita'!$D$25) | H100: =$C100*('Projeção Receita'!I25/'Projeção Receita'!$D$25) | I100: =I100/C100
A101: PE | B101: Recife | C101: 57641.35 | D101: =$C101*('Projeção Receita'!E25/'Projeção Receita'!$D$25) | E101: =$C101*('Projeção Receita'!F25/'Projeção Receita'!$D$25) | F101: =$C101*('Projeção Receita'!G25/'Projeção Receita'!$D$25) | G101: =$C101*('Projeção Receita'!H25/'Projeção Receita'!$D$25) | H101: =$C101*('Projeção Receita'!I25/'Projeção Receita'!$D$25) | I101: =I101/C101
A102: PE | B102: Outras cidades do estado (residual) | C102: =C99-SUM(C100:C101) | D102: =D99-SUM(D100:D101) | E102: =E99-SUM(E100:E101) | F102: =F99-SUM(F100:F101) | G102: =G99-SUM(G100:G101) | H102: =H99-SUM(H100:H101)
A104: BA | B104: TOTAL BA (B2B) | C104: ='Projeção Receita'!D21 | D104: ='Projeção Receita'!E21 | E104: ='Projeção Receita'!F21 | F104: ='Projeção Receita'!G21 | G104: ='Projeção Receita'!H21 | H104: ='Projeção Receita'!I21 | I104: =I104/C104
A105: BA | B105: Salvador | C105: 224676.4 | D105: =$C105*('Projeção Receita'!E21/'Projeção Receita'!$D$21) | E105: =$C105*('Projeção Receita'!F21/'Projeção Receita'!$D$21) | F105: =$C105*('Projeção Receita'!G21/'Projeção Receita'!$D$21) | G105: =$C105*('Projeção Receita'!H21/'Projeção Receita'!$D$21) | H105: =$C105*('Projeção Receita'!I21/'Projeção Receita'!$D$21) | I105: =I105/C105
A106: BA | B106: Porto Seguro | C106: 49280 | D106: =$C106*('Projeção Receita'!E21/'Projeção Receita'!$D$21) | E106: =$C106*('Projeção Receita'!F21/'Projeção Receita'!$D$21) | F106: =$C106*('Projeção Receita'!G21/'Projeção Receita'!$D$21) | G106: =$C106*('Projeção Receita'!H21/'Projeção Receita'!$D$21) | H106: =$C106*('Projeção Receita'!I21/'Projeção Receita'!$D$21) | I106: =I106/C106
A107: BA | B107: Outras cidades do estado (residual) | C107: =C104-SUM(C105:C106) | D107: =D104-SUM(D105:D106) | E107: =E104-SUM(E105:E106) | F107: =F104-SUM(F105:F106) | G107: =G104-SUM(G105:G106) | H107: =H104-SUM(H105:H106)
A109: DF | B109: TOTAL DF (B2B) | C109: ='Projeção Receita'!D11 | D109: ='Projeção Receita'!E11 | E109: ='Projeção Receita'!F11 | F109: ='Projeção Receita'!G11 | G109: ='Projeção Receita'!H11 | H109: ='Projeção Receita'!I11 | I109: =I109/C109
A110: DF | B110: Brasilia | C110: 593049.27 | D110: =$C110*('Projeção Receita'!E11/'Projeção Receita'!$D$11) | E110: =$C110*('Projeção Receita'!F11/'Projeção Receita'!$D$11) | F110: =$C110*('Projeção Receita'!G11/'Projeção Receita'!$D$11) | G110: =$C110*('Projeção Receita'!H11/'Projeção Receita'!$D$11) | H110: =$C110*('Projeção Receita'!I11/'Projeção Receita'!$D$11) | I110: =I110/C110
...

Sheet Funcionários
A1: PROJEÇÃO DE FUNCIONÁRIOS — POR ESTADO E FUNÇÃO
A2: Regra: Varejo Direto (payroll Orfeu) apenas em SP/RJ — inclui Vendedor e Promotor/Abordador próprios. Demais estados = Representante terceiro (comissionado) e Promotores/Abordadores via agência externa — ambos fora da folha. Cidades-foco B2B → Comercial primeiro, depois Barista.
A3: Nota: baseline 2025 de Vendedor Varejo Direto (SP=3, RJ=1) corrigido para bater com o headcount real no Organograma_Time_Comercial_SNomes.xlsx, aba Avaliação (Funcionários 4, 5, 6 em SP; Funcionário 8 no RJ).
A4: UF | B4: Estado | C4: Função | D4: 2025 (atual) | E4: 2026 | F4: 2027 | G4: 2028 | H4: 2029 | I4: 2030
A5: SP | B5: São Paulo | C5: Vendedor Varejo Direto (SP/RJ) | D5: 3 | E5: =$D$5+ROUNDDOWN(MAX(0,'Projeção Receita'!E4-'Projeção Receita'!$D$4)/Premissas!$B$14,0) | F5: =$D$5+ROUNDDOWN(MAX(0,'Projeção Receita'!F4-'Projeção Receita'!$D$4)/Premissas!$B$14,0) | G5: =$D$5+ROUNDDOWN(MAX(0,'Projeção Receita'!G4-'Projeção Receita'!$D$4)/Premissas!$B$14,0) | H5: =$D$5+ROUNDDOWN(MAX(0,'Projeção Receita'!H4-'Projeção Receita'!$D$4)/Premissas!$B$14,0) | I5: =$D$5+ROUNDDOWN(MAX(0,'Projeção Receita'!I4-'Projeção Receita'!$D$4)/Premissas!$B$14,0)
A6: SP | B6: São Paulo | C6: Promotor/Abordador Próprio (SP/RJ) | D6: 0 | E6: =ROUNDDOWN(MAX(0,('Projeção Receita'!E4-'Projeção Receita'!$D$4))/1000000*Premissas!$B$15,0) | F6: =ROUNDDOWN(MAX(0,('Projeção Receita'!F4-'Projeção Receita'!$D$4))/1000000*Premissas!$B$15,0) | G6: =ROUNDDOWN(MAX(0,('Projeção Receita'!G4-'Projeção Receita'!$D$4))/1000000*Premissas!$B$15,0) | H6: =ROUNDDOWN(MAX(0,('Projeção Receita'!H4-'Projeção Receita'!$D$4))/1000000*Premissas!$B$15,0) | I6: =ROUNDDOWN(MAX(0,('Projeção Receita'!I4-'Projeção Receita'!$D$4))/1000000*Premissas!$B$15,0)
A7: SP | B7: São Paulo | C7: Comercial (B2B) | D7: 3 | E7: =$D$7+ROUNDDOWN(MAX(0,'Projeção Receita'!E5-'Projeção Receita'!$D$5)/Premissas!$B$14,0) | F7: =$D$7+ROUNDDOWN(MAX(0,'Projeção Receita'!F5-'Projeção Receita'!$D$5)/Premissas!$B$14,0) | G7: =$D$7+ROUNDDOWN(MAX(0,'Projeção Receita'!G5-'Projeção Receita'!$D$5)/Premissas!$B$14,0) | H7: =$D$7+ROUNDDOWN(MAX(0,'Projeção Receita'!H5-'Projeção Receita'!$D$5)/Premissas!$B$14,0) | I7: =$D$7+ROUNDDOWN(MAX(0,'Projeção Receita'!I5-'Projeção Receita'!$D$5)/Premissas!$B$14,0)
A8: SP | B8: São Paulo | C8: Baristas (B2B) | D8: 4 | E8: =ROUNDUP(E7*Premissas!$B$16,0) | F8: =ROUNDUP(F7*Premissas!$B$16,0) | G8: =ROUNDUP(G7*Premissas!$B$16,0) | H8: =ROUNDUP(H7*Premissas!$B$16,0) | I8: =ROUNDUP(I7*Premissas!$B$16,0)
A9: RJ | B9: Rio de Janeiro | C9: Vendedor Varejo Direto (SP/RJ) | D9: 1 | E9: =$D$9+ROUNDDOWN(MAX(0,'Projeção Receita'!E6-'Projeção Receita'!$D$6)/Premissas!$B$14,0) | F9: =$D$9+ROUNDDOWN(MAX(0,'Projeção Receita'!F6-'Projeção Receita'!$D$6)/Premissas!$B$14,0) | G9: =$D$9+ROUNDDOWN(MAX(0,'Projeção Receita'!G6-'Projeção Receita'!$D$6)/Premissas!$B$14,0) | H9: =$D$9+ROUNDDOWN(MAX(0,'Projeção Receita'!H6-'Projeção Receita'!$D$6)/Premissas!$B$14,0) | I9: =$D$9+ROUNDDOWN(MAX(0,'Projeção Receita'!I6-'Projeção Receita'!$D$6)/Premissas!$B$14,0)
A10: RJ | B10: Rio de Janeiro | C10: Promotor/Abordador Próprio (SP/RJ) | D10: 0 | E10: =ROUNDDOWN(MAX(0,('Projeção Receita'!E6-'Projeção Receita'!$D$6))/1000000*Premissas!$B$15,0) | F10: =ROUNDDOWN(MAX(0,('Projeção Receita'!F6-'Projeção Receita'!$D$6))/1000000*Premissas!$B$15,0) | G10: =ROUNDDOWN(MAX(0,('Projeção Receita'!G6-'Projeção Receita'!$D$6))/1000000*Premissas!$B$15,0) | H10: =ROUNDDOWN(MAX(0,('Projeção Receita'!H6-'Projeção Receita'!$D$6))/1000000*Premissas!$B$15,0) | I10: =ROUNDDOWN(MAX(0,('Projeção Receita'!I6-'Projeção Receita'!$D$6))/1000000*Premissas!$B$15,0)
A11: RJ | B11: Rio de Janeiro | C11: Comercial (B2B) | D11: 2 | E11: =$D$11+ROUNDDOWN(MAX(0,'Projeção Receita'!E7-'Projeção Receita'!$D$7)/Premissas!$B$14,0) | F11: =$D$11+ROUNDDOWN(MAX(0,'Projeção Receita'!F7-'Projeção Receita'!$D$7)/Premissas!$B$14,0) | G11: =$D$11+ROUNDDOWN(MAX(0,'Projeção Receita'!G7-'Projeção Receita'!$D$7)/Premissas!$B$14,0) | H11: =$D$11+ROUNDDOWN(MAX(0,'Projeção Receita'!H7-'Projeção Receita'!$D$7)/Premissas!$B$14,0) | I11: =$D$11+ROUNDDOWN(MAX(0,'Projeção Receita'!I7-'Projeção Receita'!$D$7)/Premissas!$B$14,0)
A12: RJ | B12: Rio de Janeiro | C12: Baristas (B2B) | D12: 2 | E12: =ROUNDUP(E11*Premissas!$B$16,0) | F12: =ROUNDUP(F11*Premissas!$B$16,0) | G12: =ROUNDUP(G11*Premissas!$B$16,0) | H12: =ROUNDUP(H11*Premissas!$B$16,0) | I12: =ROUNDUP(I11*Premissas!$B$16,0)
A13: SC | B13: Santa Catarina | C13: Representante (Varejo terceiro) | D13: 1 | E13: =$D$13+ROUNDDOWN(MAX(0,'Projeção Receita'!E8-'Projeção Receita'!$D$8)/(Premissas!$B$14*Premissas!$B$75),0) | F13: =$D$13+ROUNDDOWN(MAX(0,'Projeção Receita'!F8-'Projeção Receita'!$D$8)/(Premissas!$B$14*Premissas!$B$75),0) | G13: =$D$13+ROUNDDOWN(MAX(0,'Projeção Receita'!G8-'Projeção Receita'!$D$8)/(Premissas!$B$14*Premissas!$B$75),0) | H13: =$D$13+ROUNDDOWN(MAX(0,'Projeção Receita'!H8-'Projeção Receita'!$D$8)/(Premissas!$B$14*Premissas!$B$75),0) | I13: =$D$13+ROUNDDOWN(MAX(0,'Projeção Receita'!I8-'Projeção Receita'!$D$8)/(Premissas!$B$14*Premissas!$B$75),0)
A14: SC | B14: Santa Catarina | C14: Promotores/Abordadores (via agência) | D14: 0 | E14: =ROUNDDOWN(MAX(0,('Projeção Receita'!E8-'Projeção Receita'!$D$8))/1000000*(Premissas!$B$15/Premissas!$B$76),0) | F14: =ROUNDDOWN(MAX(0,('Projeção Receita'!F8-'Projeção Receita'!$D$8))/1000000*(Premissas!$B$15/Premissas!$B$76),0) | G14: =ROUNDDOWN(MAX(0,('Projeção Receita'!G8-'Projeção Receita'!$D$8))/1000000*(Premissas!$B$15/Premissas!$B$76),0) | H14: =ROUNDDOWN(MAX(0,('Projeção Receita'!H8-'Projeção Receita'!$D$8))/1000000*(Premissas!$B$15/Premissas!$B$76),0) | I14: =ROUNDDOWN(MAX(0,('Projeção Receita'!I8-'Projeção Receita'!$D$8))/1000000*(Premissas!$B$15/Premissas!$B$76),0)
A15: SC | B15: Santa Catarina | C15: Comercial (B2B) | D15: 0 | E15: =$D$15+ROUNDDOWN(MAX(0,'Projeção Receita'!E9-'Projeção Receita'!$D$9)/(Premissas!$B$14*Premissas!$B$75),0) | F15: =$D$15+ROUNDDOWN(MAX(0,'Projeção Receita'!F9-'Projeção Receita'!$D$9)/(Premissas!$B$14*Premissas!$B$75),0) | G15: =$D$15+ROUNDDOWN(MAX(0,'Projeção Receita'!G9-'Projeção Receita'!$D$9)/(Premissas!$B$14*Premissas!$B$75),0) | H15: =$D$15+ROUNDDOWN(MAX(0,'Projeção Receita'!H9-'Projeção Receita'!$D$9)/(Premissas!$B$14*Premissas!$B$75),0) | I15: =$D$15+ROUNDDOWN(MAX(0,'Projeção Receita'!I9-'Projeção Receita'!$D$9)/(Premissas!$B$14*Premissas!$B$75),0)
A16: SC | B16: Santa Catarina | C16: Baristas (B2B) | D16: 0 | E16: =ROUNDUP(E15*Premissas!$B$16,0) | F16: =ROUNDUP(F15*Premissas!$B$16,0) | G16: =ROUNDUP(G15*Premissas!$B$16,0) | H16: =ROUNDUP(H15*Premissas!$B$16,0) | I16: =ROUNDUP(I15*Premissas!$B$16,0)
A17: DF | B17: Distrito Federal | C17: Representante (Varejo terceiro) | D17: 0 | E17: =$D$17+ROUNDDOWN(MAX(0,'Projeção Receita'!E10-'Projeção Receita'!$D$10)/(Premissas!$B$14*Premissas!$B$75),0) | F17: =$D$17+ROUNDDOWN(MAX(0,'Projeção Receita'!F10-'Projeção Receita'!$D$10)/(Premissas!$B$14*Premissas!$B$75),0) | G17: =$D$17+ROUNDDOWN(MAX(0,'Projeção Receita'!G10-'Projeção Receita'!$D$10)/(Premissas!$B$14*Premissas!$B$75),0) | H17: =$D$17+ROUNDDOWN(MAX(0,'Projeção Receita'!H10-'Projeção Receita'!$D$10)/(Premissas!$B$14*Premissas!$B$75),0) | I17: =$D$17+ROUNDDOWN(MAX(0,'Projeção Receita'!I10-'Projeção Receita'!$D$10)/(Premissas!$B$14*Premissas!$B$75),0)
A18: DF | B18: Distrito Federal | C18: Promotores/Abordadores (via agência) | D18: 0 | E18: =ROUNDDOWN(MAX(0,('Projeção Receita'!E10-'Projeção Receita'!$D$10))/1000000*(Premissas!$B$15/Premissas!$B$76),0) | F18: =ROUNDDOWN(MAX(0,('Projeção Receita'!F10-'Projeção Receita'!$D$10))/1000000*(Premissas!$B$15/Premissas!$B$76),0) | G18: =ROUNDDOWN(MAX(0,('Projeção Receita'!G10-'Projeção Receita'!$D$10))/1000000*(Premissas!$B$15/Premissas!$B$76),0) | H18: =ROUNDDOWN(MAX(0,('Projeção Receita'!H10-'Projeção Receita'!$D$10))/1000000*(Premissas!$B$15/Premissas!$B$76),0) | I18: =ROUNDDOWN(MAX(0,('Projeção Receita'!I10-'Projeção Receita'!$D$10))/1000000*(Premissas!$B$15/Premissas!$B$76),0)
A19: DF | B19: Distrito Federal | C19: Comercial (B2B) | D19: 1 | E19: =$D$19+ROUNDDOWN(MAX(0,'Projeção Receita'!E11-'Projeção Receita'!$D$11)/(Premissas!$B$14*Premissas!$B$75),0) | F19: =$D$19+ROUNDDOWN(MAX(0,'Projeção Receita'!F11-'Projeção Receita'!$D$11)/(Premissas!$B$14*Premissas!$B$75),0) | G19: =$D$19+ROUNDDOWN(MAX(0,'Projeção Receita'!G11-'Projeção Receita'!$D$11)/(Premissas!$B$14*Premissas!$B$75),0) | H19: =$D$19+ROUNDDOWN(MAX(0,'Projeção Receita'!H11-'Projeção Receita'!$D$11)/(Premissas!$B$14*Premissas!$B$75),0) | I19: =$D$19+ROUNDDOWN(MAX(0,'Projeção Receita'!I11-'Projeção Receita'!$D$11)/(Premissas!$B$14*Premissas!$B$75),0)
A20: DF | B20: Distrito Federal | C20: Baristas (B2B) | D20: 0 | E20: =ROUNDUP(E19*Premissas!$B$16,0) | F20: =ROUNDUP(F19*Premissas!$B$16,0) | G20: =ROUNDUP(G19*Premissas!$B$16,0) | H20: =ROUNDUP(H19*Premissas!$B$16,0) | I20: =ROUNDUP(I19*Premissas!$B$16,0)
A21: PR | B21: Paraná | C21: Representante (Varejo terceiro) | D21: 2 | E21: =$D$21+ROUNDDOWN(MAX(0,'Projeção Receita'!E12-'Projeção Receita'!$D$12)/(Premissas!$B$14*Premissas!$B$75),0) | F21: =$D$21+ROUNDDOWN(MAX(0,'Projeção Receita'!F12-'Projeção Receita'!$D$12)/(Premissas!$B$14*Premissas!$B$75),0) | G21: =$D$21+ROUNDDOWN(MAX(0,'Projeção Receita'!G12-'Projeção Receita'!$D$12)/(Premissas!$B$14*Premissas!$B$75),0) | H21: =$D$21+ROUNDDOWN(MAX(0,'Projeção Receita'!H12-'Projeção Receita'!$D$12)/(Premissas!$B$14*Premissas!$B$75),0) | I21: =$D$21+ROUNDDOWN(MAX(0,'Projeção Receita'!I12-'Projeção Receita'!$D$12)/(Premissas!$B$14*Premissas!$B$75),0)
A22: PR | B22: Paraná | C22: Promotores/Abordadores (via agência) | D22: 0 | E22: =ROUNDDOWN(MAX(0,('Projeção Receita'!E12-'Projeção Receita'!$D$12))/1000000*(Premissas!$B$15/Premissas!$B$76),0) | F22: =ROUNDDOWN(MAX(0,('Projeção Receita'!F12-'Projeção Receita'!$D$12))/1000000*(Premissas!$B$15/Premissas!$B$76),0) | G22: =ROUNDDOWN(MAX(0,('Projeção Receita'!G12-'Projeção Receita'!$D$12))/1000000*(Premissas!$B$15/Premissas!$B$76),0) | H22: =ROUNDDOWN(MAX(0,('Projeção Receita'!H12-'Projeção Receita'!$D$12))/1000000*(Premissas!$B$15/Premissas!$B$76),0) | I22: =ROUNDDOWN(MAX(0,('Projeção Receita'!I12-'Projeção Receita'!$D$12))/1000000*(Premissas!$B$15/Premissas!$B$76),0)
A23: PR | B23: Paraná | C23: Comercial (B2B) | D23: 0 | E23: =$D$23+ROUNDDOWN(MAX(0,'Projeção Receita'!E13-'Projeção Receita'!$D$13)/(Premissas!$B$14*Premissas!$B$75),0) | F23: =$D$23+ROUNDDOWN(MAX(0,'Projeção Receita'!F13-'Projeção Receita'!$D$13)/(Premissas!$B$14*Premissas!$B$75),0) | G23: =$D$23+ROUNDDOWN(MAX(0,'Projeção Receita'!G13-'Projeção Receita'!$D$13)/(Premissas!$B$14*Premissas!$B$75),0) | H23: =$D$23+ROUNDDOWN(MAX(0,'Projeção Receita'!H13-'Projeção Receita'!$D$13)/(Premissas!$B$14*Premissas!$B$75),0) | I23: =$D$23+ROUNDDOWN(MAX(0,'Projeção Receita'!I13-'Projeção Receita'!$D$13)/(Premissas!$B$14*Premissas!$B$75),0)
A24: PR | B24: Paraná | C24: Baristas (B2B) | D24: 0 | E24: =ROUNDUP(E23*Premissas!$B$16,0) | F24: =ROUNDUP(F23*Premissas!$B$16,0) | G24: =ROUNDUP(G23*Premissas!$B$16,0) | H24: =ROUNDUP(H23*Premissas!$B$16,0) | I24: =ROUNDUP(I23*Premissas!$B$16,0)
A25: RS | B25: Rio Grande do Sul | C25: Representante (Varejo terceiro) | D25: 1 | E25: =$D$25+ROUNDDOWN(MAX(0,'Projeção Receita'!E14-'Projeção Receita'!$D$14)/(Premissas!$B$14*Premissas!$B$75),0) | F25: =$D$25+ROUNDDOWN(MAX(0,'Projeção Receita'!F14-'Projeção Receita'!$D$14)/(Premissas!$B$14*Premissas!$B$75),0) | G25: =$D$25+ROUNDDOWN(MAX(0,'Projeção Receita'!G14-'Projeção Receita'!$D$14)/(Premissas!$B$14*Premissas!$B$75),0) | H25: =$D$25+ROUNDDOWN(MAX(0,'Projeção Receita'!H14-'Projeção Receita'!$D$14)/(Premissas!$B$14*Premissas!$B$75),0) | I25: =$D$25+ROUNDDOWN(MAX(0,'Projeção Receita'!I14-'Projeção Receita'!$D$14)/(Premissas!$B$14*Premissas!$B$75),0)
A26: RS | B26: Rio Grande do Sul | C26: Promotores/Abordadores (via agência) | D26: 0 | E26: =ROUNDDOWN(MAX(0,('Projeção Receita'!E14-'Projeção Receita'!$D$14))/1000000*(Premissas!$B$15/Premissas!$B$76),0) | F26: =ROUNDDOWN(MAX(0,('Projeção Receita'!F14-'Projeção Receita'!$D$14))/1000000*(Premissas!$B$15/Premissas!$B$76),0) | G26: =ROUNDDOWN(MAX(0,('Projeção Receita'!G14-'Projeção Receita'!$D$14))/1000000*(Premissas!$B$15/Premissas!$B$76),0) | H26: =ROUNDDOWN(MAX(0,('Projeção Receita'!H14-'Projeção Receita'!$D$14))/1000000*(Premissas!$B$15/Premissas!$B$76),0) | I26: =ROUNDDOWN(MAX(0,('Projeção Receita'!I14-'Projeção Receita'!$D$14))/1000000*(Premissas!$B$15/Premissas!$B$76),0)
A27: RS | B27: Rio Grande do Sul | C27: Comercial (B2B) | D27: 0 | E27: =$D$27+ROUNDDOWN(MAX(0,'Projeção Receita'!E15-'Projeção Receita'!$D$15)/(Premissas!$B$14*Premissas!$B$75),0) | F27: =$D$27+ROUNDDOWN(MAX(0,'Projeção Receita'!F15-'Projeção Receita'!$D$15)/(Premissas!$B$14*Premissas!$B$75),0) | G27: =$D$27+ROUNDDOWN(MAX(0,'Projeção Receita'!G15-'Projeção Receita'!$D$15)/(Premissas!$B$14*Premissas!$B$75),0) | H27: =$D$27+ROUNDDOWN(MAX(0,'Projeção Receita'!H15-'Projeção Receita'!$D$15)/(Premissas!$B$14*Premissas!$B$75),0) | I27: =$D$27+ROUNDDOWN(MAX(0,'Projeção Receita'!I15-'Projeção Receita'!$D$15)/(Premissas!$B$14*Premissas!$B$75),0)
A28: RS | B28: Rio Grande do Sul | C28: Baristas (B2B) | D28: 0 | E28: =ROUNDUP(E27*Premissas!$B$16,0) | F28: =ROUNDUP(F27*Premissas!$B$16,0) | G28: =ROUNDUP(G27*Premissas!$B$16,0) | H28: =ROUNDUP(H27*Premissas!$B$16,0) | I28: =ROUNDUP(I27*Premissas!$B$16,0)
A29: MG | B29: Minas Gerais | C29: Representante (Varejo terceiro) | D29: 0 | E29: =$D$29+ROUNDDOWN(MAX(0,'Projeção Receita'!E16-'Projeção Receita'!$D$16)/(Premissas!$B$14*Premissas!$B$75),0) | F29: =$D$29+ROUNDDOWN(MAX(0,'Projeção Receita'!F16-'Projeção Receita'!$D$16)/(Premissas!$B$14*Premissas!$B$75),0) | G29: =$D$29+ROUNDDOWN(MAX(0,'Projeção Receita'!G16-'Projeção Receita'!$D$16)/(Premissas!$B$14*Premissas!$B$75),0) | H29: =$D$29+ROUNDDOWN(MAX(0,'Projeção Receita'!H16-'Projeção Receita'!$D$16)/(Premissas!$B$14*Premissas!$B$75),0) | I29: =$D$29+ROUNDDOWN(MAX(0,'Projeção Receita'!I16-'Projeção Receita'!$D$16)/(Premissas!$B$14*Premissas!$B$75),0)
A30: MG | B30: Minas Gerais | C30: Promotores/Abordadores (via agência) | D30: 0 | E30: =ROUNDDOWN(MAX(0,('Projeção Receita'!E16-'Projeção Receita'!$D$16))/1000000*(Premissas!$B$15/Premissas!$B$76),0) | F30: =ROUNDDOWN(MAX(0,('Projeção Receita'!F16-'Projeção Receita'!$D$16))/1000000*(Premissas!$B$15/Premissas!$B$76),0) | G30: =ROUNDDOWN(MAX(0,('Projeção Receita'!G16-'Projeção Receita'!$D$16))/1000000*(Premissas!$B$15/Premissas!$B$76),0) | H30: =ROUNDDOWN(MAX(0,('Projeção Receita'!H16-'Projeção Receita'!$D$16))/1000000*(Premissas!$B$15/Premissas!$B$76),0) | I30: =ROUNDDOWN(MAX(0,('Projeção Receita'!I16-'Projeção Receita'!$D$16))/1000000*(Premissas!$B$15/Premissas!$B$76),0)
A31: MG | B31: Minas Gerais | C31: Comercial (B2B) | D31: 1 | E31: =$D$31+ROUNDDOWN(MAX(0,'Projeção Receita'!E17-'Projeção Receita'!$D$17)/(Premissas!$B$14*Premissas!$B$75),0) | F31: =$D$31+ROUNDDOWN(MAX(0,'Projeção Receita'!F17-'Projeção Receita'!$D$17)/(Premissas!$B$14*Premissas!$B$75),0) | G31: =$D$31+ROUNDDOWN(MAX(0,'Projeção Receita'!G17-'Projeção Receita'!$D$17)/(Premissas!$B$14*Premissas!$B$75),0) | H31: =$D$31+ROUNDDOWN(MAX(0,'Projeção Receita'!H17-'Projeção Receita'!$D$17)/(Premissas!$B$14*Premissas!$B$75),0) | I31: =$D$31+ROUNDDOWN(MAX(0,'Projeção Receita'!I17-'Projeção Receita'!$D$17)/(Premissas!$B$14*Premissas!$B$75),0)
A32: MG | B32: Minas Gerais | C32: Baristas (B2B) | D32: 0 | E32: =ROUNDUP(E31*Premissas!$B$16,0) | F32: =ROUNDUP(F31*Premissas!$B$16,0) | G32: =ROUNDUP(G31*Premissas!$B$16,0) | H32: =ROUNDUP(H31*Premissas!$B$16,0) | I32: =ROUNDUP(I31*Premissas!$B$16,0)
A33: ES | B33: Espírito Santo | C33: Representante (Varejo terceiro) | D33: 0 | E33: =$D$33+ROUNDDOWN(MAX(0,'Projeção Receita'!E18-'Projeção Receita'!$D$18)/(Premissas!$B$14*Premissas!$B$75),0) | F33: =$D$33+ROUNDDOWN(MAX(0,'Projeção Receita'!F18-'Projeção Receita'!$D$18)/(Premissas!$B$14*Premissas!$B$75),0) | G33: =$D$33+ROUNDDOWN(MAX(0,'Projeção Receita'!G18-'Projeção Receita'!$D$18)/(Premissas!$B$14*Premissas!$B$75),0) | H33: =$D$33+ROUNDDOWN(MAX(0,'Projeção Receita'!H18-'Projeção Receita'!$D$18)/(Premissas!$B$14*Premissas!$B$75),0) | I33: =$D$33+ROUNDDOWN(MAX(0,'Projeção Receita'!I18-'Projeção Receita'!$D$18)/(Premissas!$B$14*Premissas!$B$75),0)
A34: ES | B34: Espírito Santo | C34: Promotores/Abordadores (via agência) | D34: 0 | E34: =ROUNDDOWN(MAX(0,('Projeção Receita'!E18-'Projeção Receita'!$D$18))/1000000*(Premissas!$B$15/Premissas!$B$76),0) | F34: =ROUNDDOWN(MAX(0,('Projeção Receita'!F18-'Projeção Receita'!$D$18))/1000000*(Premissas!$B$15/Premissas!$B$76),0) | G34: =ROUNDDOWN(MAX(0,('Projeção Receita'!G18-'Projeção Receita'!$D$18))/1000000*(Premissas!$B$15/Premissas!$B$76),0) | H34: =ROUNDDOWN(MAX(0,('Projeção Receita'!H18-'Projeção Receita'!$D$18))/1000000*(Premissas!$B$15/Premissas!$B$76),0) | I34: =ROUNDDOWN(MAX(0,('Projeção Receita'!I18-'Projeção Receita'!$D$18))/1000000*(Premissas!$B$15/Premissas!$B$76),0)
A35: ES | B35: Espírito Santo | C35: Comercial (B2B) | D35: 0 | E35: =$D$35+ROUNDDOWN(MAX(0,'Projeção Receita'!E19-'Projeção Receita'!$D$19)/(Premissas!$B$14*Premissas!$B$75),0) | F35: =$D$35+ROUNDDOWN(MAX(0,'Projeção Receita'!F19-'Projeção Receita'!$D$19)/(Premissas!$B$14*Premissas!$B$75),0) | G35: =$D$35+ROUNDDOWN(MAX(0,'Projeção Receita'!G19-'Projeção Receita'!$D$19)/(Premissas!$B$14*Premissas!$B$75),0) | H35: =$D$35+ROUNDDOWN(MAX(0,'Projeção Receita'!H19-'Projeção Receita'!$D$19)/(Premissas!$B$14*Premissas!$B$75),0) | I35: =$D$35+ROUNDDOWN(MAX(0,'Projeção Receita'!I19-'Projeção Receita'!$D$19)/(Premissas!$B$14*Premissas!$B$75),0)
A36: ES | B36: Espírito Santo | C36: Baristas (B2B) | D36: 0 | E36: =ROUNDUP(E35*Premissas!$B$16,0) | F36: =ROUNDUP(F35*Premissas!$B$16,0) | G36: =ROUNDUP(G35*Premissas!$B$16,0) | H36: =ROUNDUP(H35*Premissas!$B$16,0) | I36: =ROUNDUP(I35*Premissas!$B$16,0)
A37: BA | B37: Bahia | C37: Representante (Varejo terceiro) | D37: 1 | E37: =$D$37+ROUNDDOWN(MAX(0,'Projeção Receita'!E20-'Projeção Receita'!$D$20)/(Premissas!$B$14*Premissas!$B$75),0) | F37: =$D$37+ROUNDDOWN(MAX(0,'Projeção Receita'!F20-'Projeção Receita'!$D$20)/(Premissas!$B$14*Premissas!$B$75),0) | G37: =$D$37+ROUNDDOWN(MAX(0,'Projeção Receita'!G20-'Projeção Receita'!$D$20)/(Premissas!$B$14*Premissas!$B$75),0) | H37: =$D$37+ROUNDDOWN(MAX(0,'Projeção Receita'!H20-'Projeção Receita'!$D$20)/(Premissas!$B$14*Premissas!$B$75),0) | I37: =$D$37+ROUNDDOWN(MAX(0,'Projeção Receita'!I20-'Projeção Receita'!$D$20)/(Premissas!$B$14*Premissas!$B$75),0)
A38: BA | B38: Bahia | C38: Promotores/Abordadores (via agência) | D38: 0 | E38: =ROUNDDOWN(MAX(0,('Projeção Receita'!E20-'Projeção Receita'!$D$20))/1000000*(Premissas!$B$15/Premissas!$B$76),0) | F38: =ROUNDDOWN(MAX(0,('Projeção Receita'!F20-'Projeção Receita'!$D$20))/1000000*(Premissas!$B$15/Premissas!$B$76),0) | G38: =ROUNDDOWN(MAX(0,('Projeção Receita'!G20-'Projeção Receita'!$D$20))/1000000*(Premissas!$B$15/Premissas!$B$76),0) | H38: =ROUNDDOWN(MAX(0,('Projeção Receita'!H20-'Projeção Receita'!$D$20))/1000000*(Premissas!$B$15/Premissas!$B$76),0) | I38: =ROUNDDOWN(MAX(0,('Projeção Receita'!I20-'Projeção Receita'!$D$20))/1000000*(Premissas!$B$15/Premissas!$B$76),0)
A39: BA | B39: Bahia | C39: Comercial (B2B) | D39: 0 | E39: =$D$39+ROUNDDOWN(MAX(0,'Projeção Receita'!E21-'Projeção Receita'!$D$21)/(Premissas!$B$14*Premissas!$B$75),0) | F39: =$D$39+ROUNDDOWN(MAX(0,'Projeção Receita'!F21-'Projeção Receita'!$D$21)/(Premissas!$B$14*Premissas!$B$75),0) | G39: =$D$39+ROUNDDOWN(MAX(0,'Projeção Receita'!G21-'Projeção Receita'!$D$21)/(Premissas!$B$14*Premissas!$B$75),0) | H39: =$D$39+ROUNDDOWN(MAX(0,'Projeção Receita'!H21-'Projeção Receita'!$D$21)/(Premissas!$B$14*Premissas!$B$75),0) | I39: =$D$39+ROUNDDOWN(MAX(0,'Projeção Receita'!I21-'Projeção Receita'!$D$21)/(Premissas!$B$14*Premissas!$B$75),0)
A40: BA | B40: Bahia | C40: Baristas (B2B) | D40: 0 | E40: =ROUNDUP(E39*Premissas!$B$16,0) | F40: =ROUNDUP(F39*Premissas!$B$16,0) | G40: =ROUNDUP(G39*Premissas!$B$16,0) | H40: =ROUNDUP(H39*Premissas!$B$16,0) | I40: =ROUNDUP(I39*Premissas!$B$16,0)
A41: CE | B41: Ceará | C41: Representante (Varejo terceiro) | D41: 0 | E41: =$D$41+ROUNDDOWN(MAX(0,'Projeção Receita'!E22-'Projeção Receita'!$D$22)/(Premissas!$B$14*Premissas!$B$75),0) | F41: =$D$41+ROUNDDOWN(MAX(0,'Projeção Receita'!F22-'Projeção Receita'!$D$22)/(Premissas!$B$14*Premissas!$B$75),0) | G41: =$D$41+ROUNDDOWN(MAX(0,'Projeção Receita'!G22-'Projeção Receita'!$D$22)/(Premissas!$B$14*Premissas!$B$75),0) | H41: =$D$41+ROUNDDOWN(MAX(0,'Projeção Receita'!H22-'Projeção Receita'!$D$22)/(Premissas!$B$14*Premissas!$B$75),0) | I41: =$D$41+ROUNDDOWN(MAX(0,'Projeção Receita'!I22-'Projeção Receita'!$D$22)/(Premissas!$B$14*Premissas!$B$75),0)
A42: CE | B42: Ceará | C42: Promotores/Abordadores (via agência) | D42: 0 | E42: =ROUNDDOWN(MAX(0,('Projeção Receita'!E22-'Projeção Receita'!$D$22))/1000000*(Premissas!$B$15/Premissas!$B$76),0) | F42: =ROUNDDOWN(MAX(0,('Projeção Receita'!F22-'Projeção Receita'!$D$22))/1000000*(Premissas!$B$15/Premissas!$B$76),0) | G42: =ROUNDDOWN(MAX(0,('Projeção Receita'!G22-'Projeção Receita'!$D$22))/1000000*(Premissas!$B$15/Premissas!$B$76),0) | H42: =ROUNDDOWN(MAX(0,('Projeção Receita'!H22-'Projeção Receita'!$D$22))/1000000*(Premissas!$B$15/Premissas!$B$76),0) | I42: =ROUNDDOWN(MAX(0,('Projeção Receita'!I22-'Projeção Receita'!$D$22))/1000000*(Premissas!$B$15/Premissas!$B$76),0)
A43: CE | B43: Ceará | C43: Comercial (B2B) | D43: 0 | E43: =$D$43+ROUNDDOWN(MAX(0,'Projeção Receita'!E23-'Projeção Receita'!$D$23)/(Premissas!$B$14*Premissas!$B$75),0) | F43: =$D$43+ROUNDDOWN(MAX(0,'Projeção Receita'!F23-'Projeção Receita'!$D$23)/(Premissas!$B$14*Premissas!$B$75),0) | G43: =$D$43+ROUNDDOWN(MAX(0,'Projeção Receita'!G23-'Projeção Receita'!$D$23)/(Premissas!$B$14*Premissas!$B$75),0) | H43: =$D$43+ROUNDDOWN(MAX(0,'Projeção Receita'!H23-'Projeção Receita'!$D$23)/(Premissas!$B$14*Premissas!$B$75),0) | I43: =$D$43+ROUNDDOWN(MAX(0,'Projeção Receita'!I23-'Projeção Receita'!$D$23)/(Premissas!$B$14*Premissas!$B$75),0)
A44: CE | B44: Ceará | C44: Baristas (B2B) | D44: 0 | E44: =ROUNDUP(E43*Premissas!$B$16,0) | F44: =ROUNDUP(F43*Premissas!$B$16,0) | G44: =ROUNDUP(G43*Premissas!$B$16,0) | H44: =ROUNDUP(H43*Premissas!$B$16,0) | I44: =ROUNDUP(I43*Premissas!$B$16,0)
A45: PE | B45: Pernambuco | C45: Representante (Varejo terceiro) | D45: 0 | E45: =$D$45+ROUNDDOWN(MAX(0,'Projeção Receita'!E24-'Projeção Receita'!$D$24)/(Premissas!$B$14*Premissas!$B$75),0) | F45: =$D$45+ROUNDDOWN(MAX(0,'Projeção Receita'!F24-'Projeção Receita'!$D$24)/(Premissas!$B$14*Premissas!$B$75),0) | G45: =$D$45+ROUNDDOWN(MAX(0,'Projeção Receita'!G24-'Projeção Receita'!$D$24)/(Premissas!$B$14*Premissas!$B$75),0) | H45: =$D$45+ROUNDDOWN(MAX(0,'Projeção Receita'!H24-'Projeção Receita'!$D$24)/(Premissas!$B$14*Premissas!$B$75),0) | I45: =$D$45+ROUNDDOWN(MAX(0,'Projeção Receita'!I24-'Projeção Receita'!$D$24)/(Premissas!$B$14*Premissas!$B$75),0)
A46: PE | B46: Pernambuco | C46: Promotores/Abordadores (via agência) | D46: 0 | E46: =ROUNDDOWN(MAX(0,('Projeção Receita'!E24-'Projeção Receita'!$D$24))/1000000*(Premissas!$B$15/Premissas!$B$76),0) | F46: =ROUNDDOWN(MAX(0,('Projeção Receita'!F24-'Projeção Receita'!$D$24))/1000000*(Premissas!$B$15/Premissas!$B$76),0) | G46: =ROUNDDOWN(MAX(0,('Projeção Receita'!G24-'Projeção Receita'!$D$24))/1000000*(Premissas!$B$15/Premissas!$B$76),0) | H46: =ROUNDDOWN(MAX(0,('Projeção Receita'!H24-'Projeção Receita'!$D$24))/1000000*(Premissas!$B$15/Premissas!$B$76),0) | I46: =ROUNDDOWN(MAX(0,('Projeção Receita'!I24-'Projeção Receita'!$D$24))/1000000*(Premissas!$B$15/Premissas!$B$76),0)
A47: PE | B47: Pernambuco | C47: Comercial (B2B) | D47: 0 | E47: =$D$47+ROUNDDOWN(MAX(0,'Projeção Receita'!E25-'Projeção Receita'!$D$25)/(Premissas!$B$14*Premissas!$B$75),0) | F47: =$D$47+ROUNDDOWN(MAX(0,'Projeção Receita'!F25-'Projeção Receita'!$D$25)/(Premissas!$B$14*Premissas!$B$75),0) | G47: =$D$47+ROUNDDOWN(MAX(0,'Projeção Receita'!G25-'Projeção Receita'!$D$25)/(Premissas!$B$14*Premissas!$B$75),0) | H47: =$D$47+ROUNDDOWN(MAX(0,'Projeção Receita'!H25-'Projeção Receita'!$D$25)/(Premissas!$B$14*Premissas!$B$75),0) | I47: =$D$47+ROUNDDOWN(MAX(0,'Projeção Receita'!I25-'Projeção Receita'!$D$25)/(Premissas!$B$14*Premissas!$B$75),0)
A48: PE | B48: Pernambuco | C48: Baristas (B2B) | D48: 0 | E48: =ROUNDUP(E47*Premissas!$B$16,0) | F48: =ROUNDUP(F47*Premissas!$B$16,0) | G48: =ROUNDUP(G47*Premissas!$B$16,0) | H48: =ROUNDUP(H47*Premissas!$B$16,0) | I48: =ROUNDUP(I47*Premissas!$B$16,0)
A49: MS | B49: Mato Grosso do Sul | C49: Representante (Varejo terceiro) | D49: 0 | E49: =$D$49+ROUNDDOWN(MAX(0,'Projeção Receita'!E26-'Projeção Receita'!$D$26)/(Premissas!$B$14*Premissas!$B$75),0) | F49: =$D$49+ROUNDDOWN(MAX(0,'Projeção Receita'!F26-'Projeção Receita'!$D$26)/(Premissas!$B$14*Premissas!$B$75),0) | G49: =$D$49+ROUNDDOWN(MAX(0,'Projeção Receita'!G26-'Projeção Receita'!$D$26)/(Premissas!$B$14*Premissas!$B$75),0) | H49: =$D$49+ROUNDDOWN(MAX(0,'Projeção Receita'!H26-'Projeção Receita'!$D$26)/(Premissas!$B$14*Premissas!$B$75),0) | I49: =$D$49+ROUNDDOWN(MAX(0,'Projeção Receita'!I26-'Projeção Receita'!$D$26)/(Premissas!$B$14*Premissas!$B$75),0)
A50: MS | B50: Mato Grosso do Sul | C50: Promotores/Abordadores (via agência) | D50: 0 | E50: =ROUNDDOWN(MAX(0,('Projeção Receita'!E26-'Projeção Receita'!$D$26))/1000000*(Premissas!$B$15/Premissas!$B$76),0) | F50: =ROUNDDOWN(MAX(0,('Projeção Receita'!F26-'Projeção Receita'!$D$26))/1000000*(Premissas!$B$15/Premissas!$B$76),0) | G50: =ROUNDDOWN(MAX(0,('Projeção Receita'!G26-'Projeção Receita'!$D$26))/1000000*(Premissas!$B$15/Premissas!$B$76),0) | H50: =ROUNDDOWN(MAX(0,('Projeção Receita'!H26-'Projeção Receita'!$D$26))/1000000*(Premissas!$B$15/Premissas!$B$76),0) | I50: =ROUNDDOWN(MAX(0,('Projeção Receita'!I26-'Projeção Receita'!$D$26))/1000000*(Premissas!$B$15/Premissas!$B$76),0)
A51: MS | B51: Mato Grosso do Sul | C51: Comercial (B2B) | D51: 0 | E51: =$D$51+ROUNDDOWN(MAX(0,'Projeção Receita'!E27-'Projeção Receita'!$D$27)/(Premissas!$B$14*Premissas!$B$75),0) | F51: =$D$51+ROUNDDOWN(MAX(0,'Projeção Receita'!F27-'Projeção Receita'!$D$27)/(Premissas!$B$14*Premissas!$B$75),0) | G51: =$D$51+ROUNDDOWN(MAX(0,'Projeção Receita'!G27-'Projeção Receita'!$D$27)/(Premissas!$B$14*Premissas!$B$75),0) | H51: =$D$51+ROUNDDOWN(MAX(0,'Projeção Receita'!H27-'Projeção Receita'!$D$27)/(Premissas!$B$14*Premissas!$B$75),0) | I51: =$D$51+ROUNDDOWN(MAX(0,'Projeção Receita'!I27-'Projeção Receita'!$D$27)/(Premissas!$B$14*Premissas!$B$75),0)
A52: MS | B52: Mato Grosso do Sul | C52: Baristas (B2B) | D52: 0 | E52: =ROUNDUP(E51*Premissas!$B$16,0) | F52: =ROUNDUP(F51*Premissas!$B$16,0) | G52: =ROUNDUP(G51*Premissas!$B$16,0) | H52: =ROUNDUP(H51*Premissas!$B$16,0) | I52: =ROUNDUP(I51*Premissas!$B$16,0)
A53: MT | B53: Mato Grosso | C53: Representante (Varejo terceiro) | D53: 0 | E53: =$D$53+ROUNDDOWN(MAX(0,'Projeção Receita'!E28-'Projeção Receita'!$D$28)/(Premissas!$B$14*Premissas!$B$75),0) | F53: =$D$53+ROUNDDOWN(MAX(0,'Projeção Receita'!F28-'Projeção Receita'!$D$28)/(Premissas!$B$14*Premissas!$B$75),0) | G53: =$D$53+ROUNDDOWN(MAX(0,'Projeção Receita'!G28-'Projeção Receita'!$D$28)/(Premissas!$B$14*Premissas!$B$75),0) | H53: =$D$53+ROUNDDOWN(MAX(0,'Projeção Receita'!H28-'Projeção Receita'!$D$28)/(Premissas!$B$14*Premissas!$B$75),0) | I53: =$D$53+ROUNDDOWN(MAX(0,'Projeção Receita'!I28-'Projeção Receita'!$D$28)/(Premissas!$B$14*Premissas!$B$75),0)
A54: MT | B54: Mato Grosso | C54: Promotores/Abordadores (via agência) | D54: 0 | E54: =ROUNDDOWN(MAX(0,('Projeção Receita'!E28-'Projeção Receita'!$D$28))/1000000*(Premissas!$B$15/Premissas!$B$76),0) | F54: =ROUNDDOWN(MAX(0,('Projeção Receita'!F28-'Projeção Receita'!$D$28))/1000000*(Premissas!$B$15/Premissas!$B$76),0) | G54: =ROUNDDOWN(MAX(0,('Projeção Receita'!G28-'Projeção Receita'!$D$28))/1000000*(Premissas!$B$15/Premissas!$B$76),0) | H54: =ROUNDDOWN(MAX(0,('Projeção Receita'!H28-'Projeção Receita'!$D$28))/1000000*(Premissas!$B$15/Premissas!$B$76),0) | I54: =ROUNDDOWN(MAX(0,('Projeção Receita'!I28-'Projeção Receita'!$D$28))/1000000*(Premissas!$B$15/Premissas!$B$76),0)
A55: MT | B55: Mato Grosso | C55: Comercial (B2B) | D55: 0 | E55: =$D$55+ROUNDDOWN(MAX(0,'Projeção Receita'!E29-'Projeção Receita'!$D$29)/(Premissas!$B$14*Premissas!$B$75),0) | F55: =$D$55+ROUNDDOWN(MAX(0,'Projeção Receita'!F29-'Projeção Receita'!$D$29)/(Premissas!$B$14*Premissas!$B$75),0) | G55: =$D$55+ROUNDDOWN(MAX(0,'Projeção Receita'!G29-'Projeção Receita'!$D$29)/(Premissas!$B$14*Premissas!$B$75),0) | H55: =$D$55+ROUNDDOWN(MAX(0,'Projeção Receita'!H29-'Projeção Receita'!$D$29)/(Premissas!$B$14*Premissas!$B$75),0) | I55: =$D$55+ROUNDDOWN(MAX(0,'Projeção Receita'!I29-'Projeção Receita'!$D$29)/(Premissas!$B$14*Premissas!$B$75),0)
A56: MT | B56: Mato Grosso | C56: Baristas (B2B) | D56: 0 | E56: =ROUNDUP(E55*Premissas!$B$16,0) | F56: =ROUNDUP(F55*Premissas!$B$16,0) | G56: =ROUNDUP(G55*Premissas!$B$16,0) | H56: =ROUNDUP(H55*Premissas!$B$16,0) | I56: =ROUNDUP(I55*Premissas!$B$16,0)
A57: AM | B57: Amazonas | C57: Representante (Varejo terceiro) | D57: 1 | E57: =$D$57+ROUNDDOWN(MAX(0,'Projeção Receita'!E30-'Projeção Receita'!$D$30)/(Premissas!$B$14*Premissas!$B$75),0) | F57: =$D$57+ROUNDDOWN(MAX(0,'Projeção Receita'!F30-'Projeção Receita'!$D$30)/(Premissas!$B$14*Premissas!$B$75),0) | G57: =$D$57+ROUNDDOWN(MAX(0,'Projeção Receita'!G30-'Projeção Receita'!$D$30)/(Premissas!$B$14*Premissas!$B$75),0) | H57: =$D$57+ROUNDDOWN(MAX(0,'Projeção Receita'!H30-'Projeção Receita'!$D$30)/(Premissas!$B$14*Premissas!$B$75),0) | I57: =$D$57+ROUNDDOWN(MAX(0,'Projeção Receita'!I30-'Projeção Receita'!$D$30)/(Premissas!$B$14*Premissas!$B$75),0)
A58: AM | B58: Amazonas | C58: Promotores/Abordadores (via agência) | D58: 0 | E58: =ROUNDDOWN(MAX(0,('Projeção Receita'!E30-'Projeção Receita'!$D$30))/1000000*(Premissas!$B$15/Premissas!$B$76),0) | F58: =ROUNDDOWN(MAX(0,('Projeção Receita'!F30-'Projeção Receita'!$D$30))/1000000*(Premissas!$B$15/Premissas!$B$76),0) | G58: =ROUNDDOWN(MAX(0,('Projeção Receita'!G30-'Projeção Receita'!$D$30))/1000000*(Premissas!$B$15/Premissas!$B$76),0) | H58: =ROUNDDOWN(MAX(0,('Projeção Receita'!H30-'Projeção Receita'!$D$30))/1000000*(Premissas!$B$15/Premissas!$B$76),0) | I58: =ROUNDDOWN(MAX(0,('Projeção Receita'!I30-'Projeção Receita'!$D$30))/1000000*(Premissas!$B$15/Premissas!$B$76),0)
A59: AM | B59: Amazonas | C59: Comercial (B2B) | D59: 0 | E59: =$D$59+ROUNDDOWN(MAX(0,'Projeção Receita'!E31-'Projeção Receita'!$D$31)/(Premissas!$B$14*Premissas!$B$75),0) | F59: =$D$59+ROUNDDOWN(MAX(0,'Projeção Receita'!F31-'Projeção Receita'!$D$31)/(Premissas!$B$14*Premissas!$B$75),0) | G59: =$D$59+ROUNDDOWN(MAX(0,'Projeção Receita'!G31-'Projeção Receita'!$D$31)/(Premissas!$B$14*Premissas!$B$75),0) | H59: =$D$59+ROUNDDOWN(MAX(0,'Projeção Receita'!H31-'Projeção Receita'!$D$31)/(Premissas!$B$14*Premissas!$B$75),0) | I59: =$D$59+ROUNDDOWN(MAX(0,'Projeção Receita'!I31-'Projeção Receita'!$D$31)/(Premissas!$B$14*Premissas!$B$75),0)
A60: AM | B60: Amazonas | C60: Baristas (B2B) | D60: 0 | E60: =ROUNDUP(E59*Premissas!$B$16,0) | F60: =ROUNDUP(F59*Premissas!$B$16,0) | G60: =ROUNDUP(G59*Premissas!$B$16,0) | H60: =ROUNDUP(H59*Premissas!$B$16,0) | I60: =ROUNDUP(I59*Premissas!$B$16,0)
A61: AC | B61: Acre | C61: Representante (Varejo terceiro) | D61: 0 | E61: =$D$61+ROUNDDOWN(MAX(0,'Projeção Receita'!E32-'Projeção Receita'!$D$32)/(Premissas!$B$14*Premissas!$B$75),0) | F61: =$D$61+ROUNDDOWN(MAX(0,'Projeção Receita'!F32-'Projeção Receita'!$D$32)/(Premissas!$B$14*Premissas!$B$75),0) | G61: =$D$61+ROUNDDOWN(MAX(0,'Projeção Receita'!G32-'Projeção Receita'!$D$32)/(Premissas!$B$14*Premissas!$B$75),0) | H61: =$D$61+ROUNDDOWN(MAX(0,'Projeção Receita'!H32-'Projeção Receita'!$D$32)/(Premissas!$B$14*Premissas!$B$75),0) | I61: =$D$61+ROUNDDOWN(MAX(0,'Projeção Receita'!I32-'Projeção Receita'!$D$32)/(Premissas!$B$14*Premissas!$B$75),0)
A62: AC | B62: Acre | C62: Promotores/Abordadores (via agência) | D62: 0 | E62: =ROUNDDOWN(MAX(0,('Projeção Receita'!E32-'Projeção Receita'!$D$32))/1000000*(Premissas!$B$15/Premissas!$B$76),0) | F62: =ROUNDDOWN(MAX(0,('Projeção Receita'!F32-'Projeção Receita'!$D$32))/1000000*(Premissas!$B$15/Premissas!$B$76),0) | G62: =ROUNDDOWN(MAX(0,('Projeção Receita'!G32-'Projeção Receita'!$D$32))/1000000*(Premissas!$B$15/Premissas!$B$76),0) | H62: =ROUNDDOWN(MAX(0,('Projeção Receita'!H32-'Projeção Receita'!$D$32))/1000000*(Premissas!$B$15/Premissas!$B$76),0) | I62: =ROUNDDOWN(MAX(0,('Projeção Receita'!I32-'Projeção Receita'!$D$32))/1000000*(Premissas!$B$15/Premissas!$B$76),0)
A63: AC | B63: Acre | C63: Comercial (B2B) | D63: 0 | E63: =$D$63+ROUNDDOWN(MAX(0,'Projeção Receita'!E33-'Projeção Receita'!$D$33)/(Premissas!$B$14*Premissas!$B$75),0) | F63: =$D$63+ROUNDDOWN(MAX(0,'Projeção Receita'!F33-'Projeção Receita'!$D$33)/(Premissas!$B$14*Premissas!$B$75),0) | G63: =$D$63+ROUNDDOWN(MAX(0,'Projeção Receita'!G33-'Projeção Receita'!$D$33)/(Premissas!$B$14*Premissas!$B$75),0) | H63: =$D$63+ROUNDDOWN(MAX(0,'Projeção Receita'!H33-'Projeção Receita'!$D$33)/(Premissas!$B$14*Premissas!$B$75),0) | I63: =$D$63+ROUNDDOWN(MAX(0,'Projeção Receita'!I33-'Projeção Receita'!$D$33)/(Premissas!$B$14*Premissas!$B$75),0)
A64: AC | B64: Acre | C64: Baristas (B2B) | D64: 0 | E64: =ROUNDUP(E63*Premissas!$B$16,0) | F64: =ROUNDUP(F63*Premissas!$B$16,0) | G64: =ROUNDUP(G63*Premissas!$B$16,0) | H64: =ROUNDUP(H63*Premissas!$B$16,0) | I64: =ROUNDUP(I63*Premissas!$B$16,0)
A65: AL | B65: Alagoas | C65: Representante (Varejo terceiro) | D65: 0 | E65: =$D$65+ROUNDDOWN(MAX(0,'Projeção Receita'!E34-'Projeção Receita'!$D$34)/(Premissas!$B$14*Premissas!$B$75),0) | F65: =$D$65+ROUNDDOWN(MAX(0,'Projeção Receita'!F34-'Projeção Receita'!$D$34)/(Premissas!$B$14*Premissas!$B$75),0) | G65: =$D$65+ROUNDDOWN(MAX(0,'Projeção Receita'!G34-'Projeção Receita'!$D$34)/(Premissas!$B$14*Premissas!$B$75),0) | H65: =$D$65+ROUNDDOWN(MAX(0,'Projeção Receita'!H34-'Projeção Receita'!$D$34)/(Premissas!$B$14*Premissas!$B$75),0) | I65: =$D$65+ROUNDDOWN(MAX(0,'Projeção Receita'!I34-'Projeção Receita'!$D$34)/(Premissas!$B$14*Premissas!$B$75),0)
A66: AL | B66: Alagoas | C66: Promotores/Abordadores (via agência) | D66: 0 | E66: =ROUNDDOWN(MAX(0,('Projeção Receita'!E34-'Projeção Receita'!$D$34))/1000000*(Premissas!$B$15/Premissas!$B$76),0) | F66: =ROUNDDOWN(MAX(0,('Projeção Receita'!F34-'Projeção Receita'!$D$34))/1000000*(Premissas!$B$15/Premissas!$B$76),0) | G66: =ROUNDDOWN(MAX(0,('Projeção Receita'!G34-'Projeção Receita'!$D$34))/1000000*(Premissas!$B$15/Premissas!$B$76),0) | H66: =ROUNDDOWN(MAX(0,('Projeção Receita'!H34-'Projeção Receita'!$D$34))/1000000*(Premissas!$B$15/Premissas!$B$76),0) | I66: =ROUNDDOWN(MAX(0,('Projeção Receita'!I34-'Projeção Receita'!$D$34))/1000000*(Premissas!$B$15/Premissas!$B$76),0)
A67: AL | B67: Alagoas | C67: Comercial (B2B) | D67: 0 | E67: =$D$67+ROUNDDOWN(MAX(0,'Projeção Receita'!E35-'Projeção Receita'!$D$35)/(Premissas!$B$14*Premissas!$B$75),0) | F67: =$D$67+ROUNDDOWN(MAX(0,'Projeção Receita'!F35-'Projeção Receita'!$D$35)/(Premissas!$B$14*Premissas!$B$75),0) | G67: =$D$67+ROUNDDOWN(MAX(0,'Projeção Receita'!G35-'Projeção Receita'!$D$35)/(Premissas!$B$14*Premissas!$B$75),0) | H67: =$D$67+ROUNDDOWN(MAX(0,'Projeção Receita'!H35-'Projeção Receita'!$D$35)/(Premissas!$B$14*Premissas!$B$75),0) | I67: =$D$67+ROUNDDOWN(MAX(0,'Projeção Receita'!I35-'Projeção Receita'!$D$35)/(Premissas!$B$14*Premissas!$B$75),0)
A68: AL | B68: Alagoas | C68: Baristas (B2B) | D68: 0 | E68: =ROUNDUP(E67*Premissas!$B$16,0) | F68: =ROUNDUP(F67*Premissas!$B$16,0) | G68: =ROUNDUP(G67*Premissas!$B$16,0) | H68: =ROUNDUP(H67*Premissas!$B$16,0) | I68: =ROUNDUP(I67*Premissas!$B$16,0)
A69: AP | B69: Amapá | C69: Representante (Varejo terceiro) | D69: 0 | E69: =$D$69+ROUNDDOWN(MAX(0,'Projeção Receita'!E36-'Projeção Receita'!$D$36)/(Premissas!$B$14*Premissas!$B$75),0) | F69: =$D$69+ROUNDDOWN(MAX(0,'Projeção Receita'!F36-'Projeção Receita'!$D$36)/(Premissas!$B$14*Premissas!$B$75),0) | G69: =$D$69+ROUNDDOWN(MAX(0,'Projeção Receita'!G36-'Projeção Receita'!$D$36)/(Premissas!$B$14*Premissas!$B$75),0) | H69: =$D$69+ROUNDDOWN(MAX(0,'Projeção Receita'!H36-'Projeção Receita'!$D$36)/(Premissas!$B$14*Premissas!$B$75),0) | I69: =$D$69+ROUNDDOWN(MAX(0,'Projeção Receita'!I36-'Projeção Receita'!$D$36)/(Premissas!$B$14*Premissas!$B$75),0)
A70: AP | B70: Amapá | C70: Promotores/Abordadores (via agência) | D70: 0 | E70: =ROUNDDOWN(MAX(0,('Projeção Receita'!E36-'Projeção Receita'!$D$36))/1000000*(Premissas!$B$15/Premissas!$B$76),0) | F70: =ROUNDDOWN(MAX(0,('Projeção Receita'!F36-'Projeção Receita'!$D$36))/1000000*(Premissas!$B$15/Premissas!$B$76),0) | G70: =ROUNDDOWN(MAX(0,('Projeção Receita'!G36-'Projeção Receita'!$D$36))/1000000*(Premissas!$B$15/Premissas!$B$76),0) | H70: =ROUNDDOWN(MAX(0,('Projeção Receita'!H36-'Projeção Receita'!$D$36))/1000000*(Premissas!$B$15/Premissas!$B$76),0) | I70: =ROUNDDOWN(MAX(0,('Projeção Receita'!I36-'Projeção Receita'!$D$36))/1000000*(Premissas!$B$15/Premissas!$B$76),0)
A71: AP | B71: Amapá | C71: Comercial (B2B) | D71: 0 | E71: =$D$71+ROUNDDOWN(MAX(0,'Projeção Receita'!E37-'Projeção Receita'!$D$37)/(Premissas!$B$14*Premissas!$B$75),0) | F71: =$D$71+ROUNDDOWN(MAX(0,'Projeção Receita'!F37-'Projeção Receita'!$D$37)/(Premissas!$B$14*Premissas!$B$75),0) | G71: =$D$71+ROUNDDOWN(MAX(0,'Projeção Receita'!G37-'Projeção Receita'!$D$37)/(Premissas!$B$14*Premissas!$B$75),0) | H71: =$D$71+ROUNDDOWN(MAX(0,'Projeção Receita'!H37-'Projeção Receita'!$D$37)/(Premissas!$B$14*Premissas!$B$75),0) | I71: =$D$71+ROUNDDOWN(MAX(0,'Projeção Receita'!I37-'Projeção Receita'!$D$37)/(Premissas!$B$14*Premissas!$B$75),0)
A72: AP | B72: Amapá | C72: Baristas (B2B) | D72: 0 | E72: =ROUNDUP(E71*Premissas!$B$16,0) | F72: =ROUNDUP(F71*Premissas!$B$16,0) | G72: =ROUNDUP(G71*Premissas!$B$16,0) | H72: =ROUNDUP(H71*Premissas!$B$16,0) | I72: =ROUNDUP(I71*Premissas!$B$16,0)
A73: GO | B73: Goiás | C73: Representante (Varejo terceiro) | D73: 0 | E73: =$D$73+ROUNDDOWN(MAX(0,'Projeção Receita'!E38-'Projeção Receita'!$D$38)/(Premissas!$B$14*Premissas!$B$75),0) | F73: =$D$73+ROUNDDOWN(MAX(0,'Projeção Receita'!F38-'Projeção Receita'!$D$38)/(Premissas!$B$14*Premissas!$B$75),0) | G73: =$D$73+ROUNDDOWN(MAX(0,'Projeção Receita'!G38-'Projeção Receita'!$D$38)/(Premissas!$B$14*Premissas!$B$75),0) | H73: =$D$73+ROUNDDOWN(MAX(0,'Projeção Receita'!H38-'Projeção Receita'!$D$38)/(Premissas!$B$14*Premissas!$B$75),0) | I73: =$D$73+ROUNDDOWN(MAX(0,'Projeção Receita'!I38-'Projeção Receita'!$D$38)/(Premissas!$B$14*Premissas!$B$75),0)
A74: GO | B74: Goiás | C74: Promotores/Abordadores (via agência) | D74: 0 | E74: =ROUNDDOWN(MAX(0,('Projeção Receita'!E38-'Projeção Receita'!$D$38))/1000000*(Premissas!$B$15/Premissas!$B$76),0) | F74: =ROUNDDOWN(MAX(0,('Projeção Receita'!F38-'Projeção Receita'!$D$38))/1000000*(Premissas!$B$15/Premissas!$B$76),0) | G74: =ROUNDDOWN(MAX(0,('Projeção Receita'!G38-'Projeção Receita'!$D$38))/1000000*(Premissas!$B$15/Premissas!$B$76),0) | H74: =ROUNDDOWN(MAX(0,('Projeção Receita'!H38-'Projeção Receita'!$D$38))/1000000*(Premissas!$B$15/Premissas!$B$76),0) | I74: =ROUNDDOWN(MAX(0,('Projeção Receita'!I38-'Projeção Receita'!$D$38))/1000000*(Premissas!$B$15/Premissas!$B$76),0)
A75: GO | B75: Goiás | C75: Comercial (B2B) | D75: 0 | E75: =$D$75+ROUNDDOWN(MAX(0,'Projeção Receita'!E39-'Projeção Receita'!$D$39)/(Premissas!$B$14*Premissas!$B$75),0) | F75: =$D$75+ROUNDDOWN(MAX(0,'Projeção Receita'!F39-'Projeção Receita'!$D$39)/(Premissas!$B$14*Premissas!$B$75),0) | G75: =$D$75+ROUNDDOWN(MAX(0,'Projeção Receita'!G39-'Projeção Receita'!$D$39)/(Premissas!$B$14*Premissas!$B$75),0) | H75: =$D$75+ROUNDDOWN(MAX(0,'Projeção Receita'!H39-'Projeção Receita'!$D$39)/(Premissas!$B$14*Premissas!$B$75),0) | I75: =$D$75+ROUNDDOWN(MAX(0,'Projeção Receita'!I39-'Projeção Receita'!$D$39)/(Premissas!$B$14*Premissas!$B$75),0)
A76: GO | B76: Goiás | C76: Baristas (B2B) | D76: 0 | E76: =ROUNDUP(E75*Premissas!$B$16,0) | F76: =ROUNDUP(F75*Premissas!$B$16,0) | G76: =ROUNDUP(G75*Premissas!$B$16,0) | H76: =ROUNDUP(H75*Premissas!$B$16,0) | I76: =ROUNDUP(I75*Premissas!$B$16,0)
A77: MA | B77: Maranhão | C77: Representante (Varejo terceiro) | D77: 0 | E77: =$D$77+ROUNDDOWN(MAX(0,'Projeção Receita'!E40-'Projeção Receita'!$D$40)/(Premissas!$B$14*Premissas!$B$75),0) | F77: =$D$77+ROUNDDOWN(MAX(0,'Projeção Receita'!F40-'Projeção Receita'!$D$40)/(Premissas!$B$14*Premissas!$B$75),0) | G77: =$D$77+ROUNDDOWN(MAX(0,'Projeção Receita'!G40-'Projeção Receita'!$D$40)/(Premissas!$B$14*Premissas!$B$75),0) | H77: =$D$77+ROUNDDOWN(MAX(0,'Projeção Receita'!H40-'Projeção Receita'!$D$40)/(Premissas!$B$14*Premissas!$B$75),0) | I77: =$D$77+ROUNDDOWN(MAX(0,'Projeção Receita'!I40-'Projeção Receita'!$D$40)/(Premissas!$B$14*Premissas!$B$75),0)
A78: MA | B78: Maranhão | C78: Promotores/Abordadores (via agência) | D78: 0 | E78: =ROUNDDOWN(MAX(0,('Projeção Receita'!E40-'Projeção Receita'!$D$40))/1000000*(Premissas!$B$15/Premissas!$B$76),0) | F78: =ROUNDDOWN(MAX(0,('Projeção Receita'!F40-'Projeção Receita'!$D$40))/1000000*(Premissas!$B$15/Premissas!$B$76),0) | G78: =ROUNDDOWN(MAX(0,('Projeção Receita'!G40-'Projeção Receita'!$D$40))/1000000*(Premissas!$B$15/Premissas!$B$76),0) | H78: =ROUNDDOWN(MAX(0,('Projeção Receita'!H40-'Projeção Receita'!$D$40))/1000000*(Premissas!$B$15/Premissas!$B$76),0) | I78: =ROUNDDOWN(MAX(0,('Projeção Receita'!I40-'Projeção Receita'!$D$40))/1000000*(Premissas!$B$15/Premissas!$B$76),0)
A79: MA | B79: Maranhão | C79: Comercial (B2B) | D79: 0 | E79: =$D$79+ROUNDDOWN(MAX(0,'Projeção Receita'!E41-'Projeção Receita'!$D$41)/(Premissas!$B$14*Premissas!$B$75),0) | F79: =$D$79+ROUNDDOWN(MAX(0,'Projeção Receita'!F41-'Projeção Receita'!$D$41)/(Premissas!$B$14*Premissas!$B$75),0) | G79: =$D$79+ROUNDDOWN(MAX(0,'Projeção Receita'!G41-'Projeção Receita'!$D$41)/(Premissas!$B$14*Premissas!$B$75),0) | H79: =$D$79+ROUNDDOWN(MAX(0,'Projeção Receita'!H41-'Projeção Receita'!$D$41)/(Premissas!$B$14*Premissas!$B$75),0) | I79: =$D$79+ROUNDDOWN(MAX(0,'Projeção Receita'!I41-'Projeção Receita'!$D$41)/(Premissas!$B$14*Premissas!$B$75),0)
A80: MA | B80: Maranhão | C80: Baristas (B2B) | D80: 0 | E80: =ROUNDUP(E79*Premissas!$B$16,0) | F80: =ROUNDUP(F79*Premissas!$B$16,0) | G80: =ROUNDUP(G79*Premissas!$B$16,0) | H80: =ROUNDUP(H79*Premissas!$B$16,0) | I80: =ROUNDUP(I79*Premissas!$B$16,0)
A81: PA | B81: Pará | C81: Representante (Varejo terceiro) | D81: 1 | E81: =$D$81+ROUNDDOWN(MAX(0,'Projeção Receita'!E42-'Projeção Receita'!$D$42)/(Premissas!$B$14*Premissas!$B$75),0) | F81: =$D$81+ROUNDDOWN(MAX(0,'Projeção Receita'!F42-'Projeção Receita'!$D$42)/(Premissas!$B$14*Premissas!$B$75),0) | G81: =$D$81+ROUNDDOWN(MAX(0,'Projeção Receita'!G42-'Projeção Receita'!$D$42)/(Premissas!$B$14*Premissas!$B$75),0) | H81: =$D$81+ROUNDDOWN(MAX(0,'Projeção Receita'!H42-'Projeção Receita'!$D$42)/(Premissas!$B$14*Premissas!$B$75),0) | I81: =$D$81+ROUNDDOWN(MAX(0,'Projeção Receita'!I42-'Projeção Receita'!$D$42)/(Premissas!$B$14*Premissas!$B$75),0)
A82: PA | B82: Pará | C82: Promotores/Abordadores (via agência) | D82: 0 | E82: =ROUNDDOWN(MAX(0,('Projeção Receita'!E42-'Projeção Receita'!$D$42))/1000000*(Premissas!$B$15/Premissas!$B$76),0) | F82: =ROUNDDOWN(MAX(0,('Projeção Receita'!F42-'Projeção Receita'!$D$42))/1000000*(Premissas!$B$15/Premissas!$B$76),0) | G82: =ROUNDDOWN(MAX(0,('Projeção Receita'!G42-'Projeção Receita'!$D$42))/1000000*(Premissas!$B$15/Premissas!$B$76),0) | H82: =ROUNDDOWN(MAX(0,('Projeção Receita'!H42-'Projeção Receita'!$D$42))/1000000*(Premissas!$B$15/Premissas!$B$76),0) | I82: =ROUNDDOWN(MAX(0,('Projeção Receita'!I42-'Projeção Receita'!$D$42))/1000000*(Premissas!$B$15/Premissas!$B$76),0)
A83: PA | B83: Pará | C83: Comercial (B2B) | D83: 0 | E83: =$D$83+ROUNDDOWN(MAX(0,'Projeção Receita'!E43-'Projeção Receita'!$D$43)/(Premissas!$B$14*Premissas!$B$75),0) | F83: =$D$83+ROUNDDOWN(MAX(0,'Projeção Receita'!F43-'Projeção Receita'!$D$43)/(Premissas!$B$14*Premissas!$B$75),0) | G83: =$D$83+ROUNDDOWN(MAX(0,'Projeção Receita'!G43-'Projeção Receita'!$D$43)/(Premissas!$B$14*Premissas!$B$75),0) | H83: =$D$83+ROUNDDOWN(MAX(0,'Projeção Receita'!H43-'Projeção Receita'!$D$43)/(Premissas!$B$14*Premissas!$B$75),0) | I83: =$D$83+ROUNDDOWN(MAX(0,'Projeção Receita'!I43-'Projeção Receita'!$D$43)/(Premissas!$B$14*Premissas!$B$75),0)
A84: PA | B84: Pará | C84: Baristas (B2B) | D84: 0 | E84: =ROUNDUP(E83*Premissas!$B$16,0) | F84: =ROUNDUP(F83*Premissas!$B$16,0) | G84: =ROUNDUP(G83*Premissas!$B$16,0) | H84: =ROUNDUP(H83*Premissas!$B$16,0) | I84: =ROUNDUP(I83*Premissas!$B$16,0)
A85: PB | B85: Paraíba | C85: Representante (Varejo terceiro) | D85: 0 | E85: =$D$85+ROUNDDOWN(MAX(0,'Projeção Receita'!E44-'Projeção Receita'!$D$44)/(Premissas!$B$14*Premissas!$B$75),0) | F85: =$D$85+ROUNDDOWN(MAX(0,'Projeção Receita'!F44-'Projeção Receita'!$D$44)/(Premissas!$B$14*Premissas!$B$75),0) | G85: =$D$85+ROUNDDOWN(MAX(0,'Projeção Receita'!G44-'Projeção Receita'!$D$44)/(Premissas!$B$14*Premissas!$B$75),0) | H85: =$D$85+ROUNDDOWN(MAX(0,'Projeção Receita'!H44-'Projeção Receita'!$D$44)/(Premissas!$B$14*Premissas!$B$75),0) | I85: =$D$85+ROUNDDOWN(MAX(0,'Projeção Receita'!I44-'Projeção Receita'!$D$44)/(Premissas!$B$14*Premissas!$B$75),0)
A86: PB | B86: Paraíba | C86: Promotores/Abordadores (via agência) | D86: 0 | E86: =ROUNDDOWN(MAX(0,('Projeção Receita'!E44-'Projeção Receita'!$D$44))/1000000*(Premissas!$B$15/Premissas!$B$76),0) | F86: =ROUNDDOWN(MAX(0,('Projeção Receita'!F44-'Projeção Receita'!$D$44))/1000000*(Premissas!$B$15/Premissas!$B$76),0) | G86: =ROUNDDOWN(MAX(0,('Projeção Receita'!G44-'Projeção Receita'!$D$44))/1000000*(Premissas!$B$15/Premissas!$B$76),0) | H86: =ROUNDDOWN(MAX(0,('Projeção Receita'!H44-'Projeção Receita'!$D$44))/1000000*(Premissas!$B$15/Premissas!$B$76),0) | I86: =ROUNDDOWN(MAX(0,('Projeção Receita'!I44-'Projeção Receita'!$D$44))/1000000*(Premissas!$B$15/Premissas!$B$76),0)
A87: PB | B87: Paraíba | C87: Comercial (B2B) | D87: 0 | E87: =$D$87+ROUNDDOWN(MAX(0,'Projeção Receita'!E45-'Projeção Receita'!$D$45)/(Premissas!$B$14*Premissas!$B$75),0) | F87: =$D$87+ROUNDDOWN(MAX(0,'Projeção Receita'!F45-'Projeção Receita'!$D$45)/(Premissas!$B$14*Premissas!$B$75),0) | G87: =$D$87+ROUNDDOWN(MAX(0,'Projeção Receita'!G45-'Projeção Receita'!$D$45)/(Premissas!$B$14*Premissas!$B$75),0) | H87: =$D$87+ROUNDDOWN(MAX(0,'Projeção Receita'!H45-'Projeção Receita'!$D$45)/(Premissas!$B$14*Premissas!$B$75),0) | I87: =$D$87+ROUNDDOWN(MAX(0,'Projeção Receita'!I45-'Projeção Receita'!$D$45)/(Premissas!$B$14*Premissas!$B$75),0)
A88: PB | B88: Paraíba | C88: Baristas (B2B) | D88: 0 | E88: =ROUNDUP(E87*Premissas!$B$16,0) | F88: =ROUNDUP(F87*Premissas!$B$16,0) | G88: =ROUNDUP(G87*Premissas!$B$16,0) | H88: =ROUNDUP(H87*Premissas!$B$16,0) | I88: =ROUNDUP(I87*Premissas!$B$16,0)
A89: PI | B89: Piauí | C89: Representante (Varejo terceiro) | D89: 0 | E89: =$D$89+ROUNDDOWN(MAX(0,'Projeção Receita'!E46-'Projeção Receita'!$D$46)/(Premissas!$B$14*Premissas!$B$75),0) | F89: =$D$89+ROUNDDOWN(MAX(0,'Projeção Receita'!F46-'Projeção Receita'!$D$46)/(Premissas!$B$14*Premissas!$B$75),0) | G89: =$D$89+ROUNDDOWN(MAX(0,'Projeção Receita'!G46-'Projeção Receita'!$D$46)/(Premissas!$B$14*Premissas!$B$75),0) | H89: =$D$89+ROUNDDOWN(MAX(0,'Projeção Receita'!H46-'Projeção Receita'!$D$46)/(Premissas!$B$14*Premissas!$B$75),0) | I89: =$D$89+ROUNDDOWN(MAX(0,'Projeção Receita'!I46-'Projeção Receita'!$D$46)/(Premissas!$B$14*Premissas!$B$75),0)
A90: PI | B90: Piauí | C90: Promotores/Abordadores (via agência) | D90: 0 | E90: =ROUNDDOWN(MAX(0,('Projeção Receita'!E46-'Projeção Receita'!$D$46))/1000000*(Premissas!$B$15/Premissas!$B$76),0) | F90: =ROUNDDOWN(MAX(0,('Projeção Receita'!F46-'Projeção Receita'!$D$46))/1000000*(Premissas!$B$15/Premissas!$B$76),0) | G90: =ROUNDDOWN(MAX(0,('Projeção Receita'!G46-'Projeção Receita'!$D$46))/1000000*(Premissas!$B$15/Premissas!$B$76),0) | H90: =ROUNDDOWN(MAX(0,('Projeção Receita'!H46-'Projeção Receita'!$D$46))/1000000*(Premissas!$B$15/Premissas!$B$76),0) | I90: =ROUNDDOWN(MAX(0,('Projeção Receita'!I46-'Projeção Receita'!$D$46))/1000000*(Premissas!$B$15/Premissas!$B$76),0)
A91: PI | B91: Piauí | C91: Comercial (B2B) | D91: 0 | E91: =$D$91+ROUNDDOWN(MAX(0,'Projeção Receita'!E47-'Projeção Receita'!$D$47)/(Premissas!$B$14*Premissas!$B$75),0) | F91: =$D$91+ROUNDDOWN(MAX(0,'Projeção Receita'!F47-'Projeção Receita'!$D$47)/(Premissas!$B$14*Premissas!$B$75),0) | G91: =$D$91+ROUNDDOWN(MAX(0,'Projeção Receita'!G47-'Projeção Receita'!$D$47)/(Premissas!$B$14*Premissas!$B$75),0) | H91: =$D$91+ROUNDDOWN(MAX(0,'Projeção Receita'!H47-'Projeção Receita'!$D$47)/(Premissas!$B$14*Premissas!$B$75),0) | I91: =$D$91+ROUNDDOWN(MAX(0,'Projeção Receita'!I47-'Projeção Receita'!$D$47)/(Premissas!$B$14*Premissas!$B$75),0)
A92: PI | B92: Piauí | C92: Baristas (B2B) | D92: 0 | E92: =ROUNDUP(E91*Premissas!$B$16,0) | F92: =ROUNDUP(F91*Premissas!$B$16,0) | G92: =ROUNDUP(G91*Premissas!$B$16,0) | H92: =ROUNDUP(H91*Premissas!$B$16,0) | I92: =ROUNDUP(I91*Premissas!$B$16,0)
A93: RN | B93: Rio Grande do Norte | C93: Representante (Varejo terceiro) | D93: 0 | E93: =$D$93+ROUNDDOWN(MAX(0,'Projeção Receita'!E48-'Projeção Receita'!$D$48)/(Premissas!$B$14*Premissas!$B$75),0) | F93: =$D$93+ROUNDDOWN(MAX(0,'Projeção Receita'!F48-'Projeção Receita'!$D$48)/(Premissas!$B$14*Premissas!$B$75),0) | G93: =$D$93+ROUNDDOWN(MAX(0,'Projeção Receita'!G48-'Projeção Receita'!$D$48)/(Premissas!$B$14*Premissas!$B$75),0) | H93: =$D$93+ROUNDDOWN(MAX(0,'Projeção Receita'!H48-'Projeção Receita'!$D$48)/(Premissas!$B$14*Premissas!$B$75),0) | I93: =$D$93+ROUNDDOWN(MAX(0,'Projeção Receita'!I48-'Projeção Receita'!$D$48)/(Premissas!$B$14*Premissas!$B$75),0)
A94: RN | B94: Rio Grande do Norte | C94: Promotores/Abordadores (via agência) | D94: 0 | E94: =ROUNDDOWN(MAX(0,('Projeção Receita'!E48-'Projeção Receita'!$D$48))/1000000*(Premissas!$B$15/Premissas!$B$76),0) | F94: =ROUNDDOWN(MAX(0,('Projeção Receita'!F48-'Projeção Receita'!$D$48))/1000000*(Premissas!$B$15/Premissas!$B$76),0) | G94: =ROUNDDOWN(MAX(0,('Projeção Receita'!G48-'Projeção Receita'!$D$48))/1000000*(Premissas!$B$15/Premissas!$B$76),0) | H94: =ROUNDDOWN(MAX(0,('Projeção Receita'!H48-'Projeção Receita'!$D$48))/1000000*(Premissas!$B$15/Premissas!$B$76),0) | I94: =ROUNDDOWN(MAX(0,('Projeção Receita'!I48-'Projeção Receita'!$D$48))/1000000*(Premissas!$B$15/Premissas!$B$76),0)
A95: RN | B95: Rio Grande do Norte | C95: Comercial (B2B) | D95: 0 | E95: =$D$95+ROUNDDOWN(MAX(0,'Projeção Receita'!E49-'Projeção Receita'!$D$49)/(Premissas!$B$14*Premissas!$B$75),0) | F95: =$D$95+ROUNDDOWN(MAX(0,'Projeção Receita'!F49-'Projeção Receita'!$D$49)/(Premissas!$B$14*Premissas!$B$75),0) | G95: =$D$95+ROUNDDOWN(MAX(0,'Projeção Receita'!G49-'Projeção Receita'!$D$49)/(Premissas!$B$14*Premissas!$B$75),0) | H95: =$D$95+ROUNDDOWN(MAX(0,'Projeção Receita'!H49-'Projeção Receita'!$D$49)/(Premissas!$B$14*Premissas!$B$75),0) | I95: =$D$95+ROUNDDOWN(MAX(0,'Projeção Receita'!I49-'Projeção Receita'!$D$49)/(Premissas!$B$14*Premissas!$B$75),0)
A96: RN | B96: Rio Grande do Norte | C96: Baristas (B2B) | D96: 0 | E96: =ROUNDUP(E95*Premissas!$B$16,0) | F96: =ROUNDUP(F95*Premissas!$B$16,0) | G96: =ROUNDUP(G95*Premissas!$B$16,0) | H96: =ROUNDUP(H95*Premissas!$B$16,0) | I96: =ROUNDUP(I95*Premissas!$B$16,0)
A97: RO | B97: Rondônia | C97: Representante (Varejo terceiro) | D97: 0 | E97: =$D$97+ROUNDDOWN(MAX(0,'Projeção Receita'!E50-'Projeção Receita'!$D$50)/(Premissas!$B$14*Premissas!$B$75),0) | F97: =$D$97+ROUNDDOWN(MAX(0,'Projeção Receita'!F50-'Projeção Receita'!$D$50)/(Premissas!$B$14*Premissas!$B$75),0) | G97: =$D$97+ROUNDDOWN(MAX(0,'Projeção Receita'!G50-'Projeção Receita'!$D$50)/(Premissas!$B$14*Premissas!$B$75),0) | H97: =$D$97+ROUNDDOWN(MAX(0,'Projeção Receita'!H50-'Projeção Receita'!$D$50)/(Premissas!$B$14*Premissas!$B$75),0) | I97: =$D$97+ROUNDDOWN(MAX(0,'Projeção Receita'!I50-'Projeção Receita'!$D$50)/(Premissas!$B$14*Premissas!$B$75),0)
A98: RO | B98: Rondônia | C98: Promotores/Abordadores (via agência) | D98: 0 | E98: =ROUNDDOWN(MAX(0,('Projeção Receita'!E50-'Projeção Receita'!$D$50))/1000000*(Premissas!$B$15/Premissas!$B$76),0) | F98: =ROUNDDOWN(MAX(0,('Projeção Receita'!F50-'Projeção Receita'!$D$50))/1000000*(Premissas!$B$15/Premissas!$B$76),0) | G98: =ROUNDDOWN(MAX(0,('Projeção Receita'!G50-'Projeção Receita'!$D$50))/1000000*(Premissas!$B$15/Premissas!$B$76),0) | H98: =ROUNDDOWN(MAX(0,('Projeção Receita'!H50-'Projeção Receita'!$D$50))/1000000*(Premissas!$B$15/Premissas!$B$76),0) | I98: =ROUNDDOWN(MAX(0,('Projeção Receita'!I50-'Projeção Receita'!$D$50))/1000000*(Premissas!$B$15/Premissas!$B$76),0)
A99: RO | B99: Rondônia | C99: Comercial (B2B) | D99: 0 | E99: =$D$99+ROUNDDOWN(MAX(0,'Projeção Receita'!E51-'Projeção Receita'!$D$51)/(Premissas!$B$14*Premissas!$B$75),0) | F99: =$D$99+ROUNDDOWN(MAX(0,'Projeção Receita'!F51-'Projeção Receita'!$D$51)/(Premissas!$B$14*Premissas!$B$75),0) | G99: =$D$99+ROUNDDOWN(MAX(0,'Projeção Receita'!G51-'Projeção Receita'!$D$51)/(Premissas!$B$14*Premissas!$B$75),0) | H99: =$D$99+ROUNDDOWN(MAX(0,'Projeção Receita'!H51-'Projeção Receita'!$D$51)/(Premissas!$B$14*Premissas!$B$75),0) | I99: =$D$99+ROUNDDOWN(MAX(0,'Projeção Receita'!I51-'Projeção Receita'!$D$51)/(Premissas!$B$14*Premissas!$B$75),0)
A100: RO | B100: Rondônia | C100: Baristas (B2B) | D100: 0 | E100: =ROUNDUP(E99*Premissas!$B$16,0) | F100: =ROUNDUP(F99*Premissas!$B$16,0) | G100: =ROUNDUP(G99*Premissas!$B$16,0) | H100: =ROUNDUP(H99*Premissas!$B$16,0) | I100: =ROUNDUP(I99*Premissas!$B$16,0)
...

Sheet Funcionários por Função
A1: QUANTIDADE DE PESSOAS PROJETADAS POR FUNÇÃO NO TEMPO
A2: Soma de todos os estados por função (aba 'Funcionários', linhas 5–112). Direto (SP/RJ) = payroll Orfeu — Vendedor e Promotor/Abordador próprios. Representante terceiro e Promotores/Abordadores via agência (demais estados) NÃO entram na folha — ver seção de custo abaixo. Não modela gerência (Gerente Varejo/Gerente B2B) — foco nos times; ver nota na seção de gestão da rede abaixo.
A4: Função | B4: 2025 (atual) | C4: 2026 | D4: 2027 | E4: 2028 | F4: 2029 | G4: 2030
A5: Vendedor Varejo Direto (SP/RJ) | B5: =SUMIF(Funcionários!$C$5:$C$112,"Vendedor Varejo Direto (SP/RJ)",Funcionários!$D$5:$D$112) | C5: =SUMIF(Funcionários!$C$5:$C$112,"Vendedor Varejo Direto (SP/RJ)",Funcionários!$E$5:$E$112) | D5: =SUMIF(Funcionários!$C$5:$C$112,"Vendedor Varejo Direto (SP/RJ)",Funcionários!$F$5:$F$112) | E5: =SUMIF(Funcionários!$C$5:$C$112,"Vendedor Varejo Direto (SP/RJ)",Funcionários!$G$5:$G$112) | F5: =SUMIF(Funcionários!$C$5:$C$112,"Vendedor Varejo Direto (SP/RJ)",Funcionários!$H$5:$H$112) | G5: =SUMIF(Funcionários!$C$5:$C$112,"Vendedor Varejo Direto (SP/RJ)",Funcionários!$I$5:$I$112)
A6: Promotor/Abordador Próprio (SP/RJ) | B6: =SUMIF(Funcionários!$C$5:$C$112,"Promotor/Abordador Próprio (SP/RJ)",Funcionários!$D$5:$D$112) | C6: =SUMIF(Funcionários!$C$5:$C$112,"Promotor/Abordador Próprio (SP/RJ)",Funcionários!$E$5:$E$112) | D6: =SUMIF(Funcionários!$C$5:$C$112,"Promotor/Abordador Próprio (SP/RJ)",Funcionários!$F$5:$F$112) | E6: =SUMIF(Funcionários!$C$5:$C$112,"Promotor/Abordador Próprio (SP/RJ)",Funcionários!$G$5:$G$112) | F6: =SUMIF(Funcionários!$C$5:$C$112,"Promotor/Abordador Próprio (SP/RJ)",Funcionários!$H$5:$H$112) | G6: =SUMIF(Funcionários!$C$5:$C$112,"Promotor/Abordador Próprio (SP/RJ)",Funcionários!$I$5:$I$112)
A7: Representante (Varejo terceiro) | B7: =SUMIF(Funcionários!$C$5:$C$112,"Representante (Varejo terceiro)",Funcionários!$D$5:$D$112) | C7: =SUMIF(Funcionários!$C$5:$C$112,"Representante (Varejo terceiro)",Funcionários!$E$5:$E$112) | D7: =SUMIF(Funcionários!$C$5:$C$112,"Representante (Varejo terceiro)",Funcionários!$F$5:$F$112) | E7: =SUMIF(Funcionários!$C$5:$C$112,"Representante (Varejo terceiro)",Funcionários!$G$5:$G$112) | F7: =SUMIF(Funcionários!$C$5:$C$112,"Representante (Varejo terceiro)",Funcionários!$H$5:$H$112) | G7: =SUMIF(Funcionários!$C$5:$C$112,"Representante (Varejo terceiro)",Funcionários!$I$5:$I$112)
A8: Promotores/Abordadores (via agência) | B8: =SUMIF(Funcionários!$C$5:$C$112,"Promotores/Abordadores (via agência)",Funcionários!$D$5:$D$112) | C8: =SUMIF(Funcionários!$C$5:$C$112,"Promotores/Abordadores (via agência)",Funcionários!$E$5:$E$112) | D8: =SUMIF(Funcionários!$C$5:$C$112,"Promotores/Abordadores (via agência)",Funcionários!$F$5:$F$112) | E8: =SUMIF(Funcionários!$C$5:$C$112,"Promotores/Abordadores (via agência)",Funcionários!$G$5:$G$112) | F8: =SUMIF(Funcionários!$C$5:$C$112,"Promotores/Abordadores (via agência)",Funcionários!$H$5:$H$112) | G8: =SUMIF(Funcionários!$C$5:$C$112,"Promotores/Abordadores (via agência)",Funcionários!$I$5:$I$112)
A9: Comercial (B2B) | B9: =SUMIF(Funcionários!$C$5:$C$112,"Comercial (B2B)",Funcionários!$D$5:$D$112) | C9: =SUMIF(Funcionários!$C$5:$C$112,"Comercial (B2B)",Funcionários!$E$5:$E$112) | D9: =SUMIF(Funcionários!$C$5:$C$112,"Comercial (B2B)",Funcionários!$F$5:$F$112) | E9: =SUMIF(Funcionários!$C$5:$C$112,"Comercial (B2B)",Funcionários!$G$5:$G$112) | F9: =SUMIF(Funcionários!$C$5:$C$112,"Comercial (B2B)",Funcionários!$H$5:$H$112) | G9: =SUMIF(Funcionários!$C$5:$C$112,"Comercial (B2B)",Funcionários!$I$5:$I$112)
A10: Baristas (B2B) | B10: =SUMIF(Funcionários!$C$5:$C$112,"Baristas (B2B)",Funcionários!$D$5:$D$112) | C10: =SUMIF(Funcionários!$C$5:$C$112,"Baristas (B2B)",Funcionários!$E$5:$E$112) | D10: =SUMIF(Funcionários!$C$5:$C$112,"Baristas (B2B)",Funcionários!$F$5:$F$112) | E10: =SUMIF(Funcionários!$C$5:$C$112,"Baristas (B2B)",Funcionários!$G$5:$G$112) | F10: =SUMIF(Funcionários!$C$5:$C$112,"Baristas (B2B)",Funcionários!$H$5:$H$112) | G10: =SUMIF(Funcionários!$C$5:$C$112,"Baristas (B2B)",Funcionários!$I$5:$I$112)
A11: TOTAL — LINHA DE FRENTE | B11: =SUM(B5:B10) | C11: =SUM(C5:C10) | D11: =SUM(D5:D10) | E11: =SUM(E5:E10) | F11: =SUM(F5:F10) | G11: =SUM(G5:G10)
A12: Líderes sugeridos (Total ÷ Span médio) | B12: =ROUNDUP(B11/Premissas!$B$21,0) | C12: =ROUNDUP(C11/Premissas!$B$21,0) | D12: =ROUNDUP(D11/Premissas!$B$21,0) | E12: =ROUNDUP(E11/Premissas!$B$21,0) | F12: =ROUNDUP(F11/Premissas!$B$21,0) | G12: =ROUNDUP(G11/Premissas!$B$21,0)
A13: TOTAL COM LIDERANÇA (linha de frente + líderes) | B13: =B11+B12 | C13: =C11+C12 | D13: =D11+D12 | E13: =E11+E12 | F13: =F11+F12 | G13: =G11+G12
A15: GESTÃO DA REDE COMERCIAL — VAREJO
A16: Não modelamos Gerente Varejo nem Gerente B2B (foco nos times). A rede de representantes terceiro é coberta por 1 Comercial dedicado a cada 12 representantes (Premissas!B20, span de controle), sem gerência intermediária 'gratuita' — cobertura desde o 1º representante.
A17: Comercial — Gestão de Representantes (terceiro) | B17: =ROUNDUP(B7/Premissas!$B$20,0) | C17: =ROUNDUP(C7/Premissas!$B$20,0) | D17: =ROUNDUP(D7/Premissas!$B$20,0) | E17: =ROUNDUP(E7/Premissas!$B$20,0) | F17: =ROUNDUP(F7/Premissas!$B$20,0) | G17: =ROUNDUP(G7/Premissas!$B$20,0)
A19: MERCHANDISING — ESTRUTURA DE REFERÊNCIA (gestão da agência de promotores, demais estados)
A20: Coordenadora Merchandising | B20: 1 | C20: 1 | D20: 1 | E20: 1 | F20: 1 | G20: 1
A21: Analista Merchandising | B21: 1 | C21: 1 | D21: 1 | E21: 1 | F21: 1 | G21: 1
A23: CUSTO DE FOLHA — FUNÇÕES COM SALÁRIO DISPONÍVEL (Organograma)
A24: Custo = headcount (linhas acima) × salário médio (Premissas, seção 6). 'Com encargos' usa o multiplicador padrão CLT de 1,8x sobre o salário base — ajustável abaixo. Representante terceiro e Promotores/Abordadores via agência NÃO entram aqui — não são CLT. Promotor/Abordador Próprio (SP/RJ) também fica de fora por ora: é payroll Orfeu, mas sem salário localizado no Organograma. Sem linha de Gerente — não modelado (foco nos times).
A25: Multiplicador de encargos CLT (padrão) | B25: 1.8
A27: Função | B27: 2025 (atual) | C27: 2026 | D27: 2027 | E27: 2028 | F27: 2029 | G27: 2030
A28: Vendedor Varejo Direto (SP/RJ) — custo mensal base (sem encargos) | B28: =B5*Premissas!$B$67 | C28: =C5*Premissas!$B$67 | D28: =D5*Premissas!$B$67 | E28: =E5*Premissas!$B$67 | F28: =F5*Premissas!$B$67 | G28: =G5*Premissas!$B$67
A29: Vendedor Varejo Direto (SP/RJ) — custo mensal com encargos (×1,8) | B29: =B28*$B$25 | C29: =C28*$B$25 | D29: =D28*$B$25 | E29: =E28*$B$25 | F29: =F28*$B$25 | G29: =G28*$B$25
A30: Comercial — Gestão de Representantes — custo mensal base (sem encargos) | B30: =B17*Premissas!$B$68 | C30: =C17*Premissas!$B$68 | D30: =D17*Premissas!$B$68 | E30: =E17*Premissas!$B$68 | F30: =F17*Premissas!$B$68 | G30: =G17*Premissas!$B$68
A31: Comercial — Gestão de Representantes — custo mensal com encargos (×1,8) | B31: =B30*$B$25 | C31: =C30*$B$25 | D31: =D30*$B$25 | E31: =E30*$B$25 | F31: =F30*$B$25 | G31: =G30*$B$25
A32: Coordenadora Merchandising — custo mensal base (sem encargos) | B32: =B20*Premissas!$B$69 | C32: =C20*Premissas!$B$69 | D32: =D20*Premissas!$B$69 | E32: =E20*Premissas!$B$69 | F32: =F20*Premissas!$B$69 | G32: =G20*Premissas!$B$69
A33: Coordenadora Merchandising — custo mensal com encargos (×1,8) | B33: =B32*$B$25 | C33: =C32*$B$25 | D33: =D32*$B$25 | E33: =E32*$B$25 | F33: =F32*$B$25 | G33: =G32*$B$25
A34: Analista Merchandising — custo mensal base (sem encargos) | B34: =B21*Premissas!$B$70 | C34: =C21*Premissas!$B$70 | D34: =D21*Premissas!$B$70 | E34: =E21*Premissas!$B$70 | F34: =F21*Premissas!$B$70 | G34: =G21*Premissas!$B$70
A35: Analista Merchandising — custo mensal com encargos (×1,8) | B35: =B34*$B$25 | C35: =C34*$B$25 | D35: =D34*$B$25 | E35: =E34*$B$25 | F35: =F34*$B$25 | G35: =G34*$B$25
A36: Comercial (B2B) — custo mensal base (sem encargos) | B36: =B9*Premissas!$B$64 | C36: =C9*Premissas!$B$64 | D36: =D9*Premissas!$B$64 | E36: =E9*Premissas!$B$64 | F36: =F9*Premissas!$B$64 | G36: =G9*Premissas!$B$64
A37: Comercial (B2B) — custo mensal com encargos (×1,8) | B37: =B36*$B$25 | C37: =C36*$B$25 | D37: =D36*$B$25 | E37: =E36*$B$25 | F37: =F36*$B$25 | G37: =G36*$B$25
A38: Baristas (B2B) — custo mensal base (sem encargos) | B38: =B10*Premissas!$B$65 | C38: =C10*Premissas!$B$65 | D38: =D10*Premissas!$B$65 | E38: =E10*Premissas!$B$65 | F38: =F10*Premissas!$B$65 | G38: =G10*Premissas!$B$65
A39: Baristas (B2B) — custo mensal com encargos (×1,8) | B39: =B38*$B$25 | C39: =C38*$B$25 | D39: =D38*$B$25 | E39: =E38*$B$25 | F39: =F38*$B$25 | G39: =G38*$B$25
A40: TOTAL FOLHA MENSAL COM ENCARGOS (todas as funções com salário disponível) | B40: =B29+B31+B33+B35+B37+B39 | C40: =C29+C31+C33+C35+C37+C39 | D40: =D29+D31+D33+D35+D37+D39 | E40: =E29+E31+E33+E35+E37+E39 | F40: =F29+F31+F33+F35+F37+F39 | G40: =G29+G31+G33+G35+G37+G39
A42: ⚠ Não inclui Representante terceiro nem Promotores/Abordadores via agência — por desenho, não são CLT/payroll Orfeu. Promotor/Abordador Próprio (SP/RJ) TAMBÉM fica de fora — é payroll Orfeu, mas sem salário ainda localizado no Organograma (gap de dado, não de desenho). Não inclui custo de gerência (Gerente Varejo/Gerente B2B) — não modelado, foco nos times. Mapear com RH/Financeiro para completar a folha total.

Sheet Resumo
A1: RESUMO EXECUTIVO — SIMULADOR COMERCIAL ORFEU
B3: 2025 (base) | C3: 2026 | D3: 2027 | E3: 2028 | F3: 2029 | G3: 2030
A4: Receita Projetada — Varejo + B2B + Online | B4: ='Projeção Receita'!D59 | C4: ='Projeção Receita'!E59 | D4: ='Projeção Receita'!F59 | E4: ='Projeção Receita'!G59 | F4: ='Projeção Receita'!H59 | G4: ='Projeção Receita'!I59
A5: Ambição da Companhia (referência) | B5: n/d | C5: =Premissas!$B$24 | D5: =Premissas!$B$24+(0.25)*(Premissas!$B$25-Premissas!$B$24) | E5: =Premissas!$B$24+(0.5)*(Premissas!$B$25-Premissas!$B$24) | F5: =Premissas!$B$24+(0.75)*(Premissas!$B$25-Premissas!$B$24) | G5: =Premissas!$B$24+(1.0)*(Premissas!$B$25-Premissas!$B$24)
A6: Gap vs. Ambição (Varejo+B2B+Online como % da ambição total) | C6: =C4/C5 | D6: =D4/D5 | E6: =E4/E5 | F6: =F4/F5 | G6: =G4/G5
A8: Nota: 2026 usa o fechamento REAL (R$163M, Premissas!B24), distribuído pelo mix de estado/canal de 2025 (Premissas!B77) — atualizar quando o mix real de 2026 estiver disponível. Ambição 2030 = R$400M (Brasil, Premissas!B25). Este simulador cobre Varejo + B2B + Online (site próprio, Mercado Livre e Amazon). A partir de 2027: crescimento orgânico Varejo/B2B 25,5% a.a. (Premissas!B4/B5), Online 25% a.a. (Premissas!B9), bônus de aceleração de mercado 25%/20%/10% nos anos 1/2/3 de priorização (Premissas!B6/B7/B8). Estrutura comercial: fora de SP/RJ, Representante/Comercial B2B e Promotores/Abordadores usam sinergia geográfica regional (Premissas!B75/B76) para manter o Faturamento por QLP próximo ao patamar atual (~R$5M/pessoa/ano) ao longo da projeção — ver seção 7 de Premissas. Fora do escopo: Distribuidor, Indústria, Exportação, Consumidor.
B10: 2025 (base) | C10: 2026 | D10: 2027 | E10: 2028 | F10: 2029 | G10: 2030
A11: Total Funcionários Comerciais (linha de frente) | B11: =Funcionários!D114 | C11: =Funcionários!E114 | D11: =Funcionários!F114 | E11: =Funcionários!G114 | F11: =Funcionários!H114 | G11: =Funcionários!I114
A12: Receita / Funcionário (R$/ano) | B12: =IF(B11=0,"n/d",B4/B11) | C12: =IF(C11=0,"n/d",C4/C11) | D12: =IF(D11=0,"n/d",D4/D11) | E12: =IF(E11=0,"n/d",E4/E11) | F12: =IF(F11=0,"n/d",F4/F11) | G12: =IF(G11=0,"n/d",G4/G11)
A14: Fontes: Simulador Orfeu.xlsx (Base_Unitaria, hist. 2025), Organograma_Time_Comercial_SNomes.xlsx (headcount atual), Mercados foco jul/2026 (priorização de estados/cidades).
